Workbook

Sheet Fr-01
B1: รายละเอียดขององค์กร | I1: TCFO_R_01 Version 04 : 21/2/2020
B3: ชื่อฟอร์ม | C3: บัญชีรายการก๊าซเรือนกระจก | E3: องค์กร | G3: =B6 | I3: หน้าที่ | J3: 1
B4: รหัสฟอร์ม | C4: Fr-01 | E4: ผู้จัดทำ | G4: บริษัท อีโค เซ็นทริก คอร์ปอเรชั่น จำกัด | I4: วันที่จัดทำ | J4: 243820
B6: บริษัท มัลติแบกซ์ จำกัด (มหาชน)
A8: รูปขององค์กร | F8: ขอบเขตขององค์กร
F9: ประเภท 1 | H9: ='Fr-04.1'!B10
H10: ='Fr-04.1'!B11
H11: ='Fr-04.1'!B12
H12: ='Fr-04.1'!B13
H13: ='Fr-04.1'!B14
H14: ='Fr-04.1'!B15
H15: ='Fr-04.1'!B16
H16: ='Fr-04.1'!B17
H17: ='Fr-04.1'!B19
H18: ='Fr-04.1'!B21
H19: ='Fr-04.1'!B22
H20: ='Fr-04.1'!B24
H21: ='Fr-04.1'!B25
H22: ='Fr-04.1'!B26
H23: ='Fr-04.1'!B27
H24: ='Fr-04.1'!B28
H25: ='Fr-04.1'!B29
H26: ='Fr-04.1'!B30
H27: ='Fr-04.1'!B31
H28: ='Fr-04.1'!B32
F29: ประเภท 2 | H29: ='Fr-04.1'!B45
F32: ประเภท 3 | H32: ='Fr-04.1'!B50
H33: ='Fr-04.1'!B51
H34: ='Fr-04.1'!B52
H35: ='Fr-04.1'!B53
F36: ระยะเวลาเก็บข้อมูล | H36: 1 มกราคม - 31 ธันวาคม 2566
F37: ผลผลิต | H37: 9586 | J37: ตัน
F38: ปีฐาน | H38: 1 มกราคม - 31 ธันวาคม 2566
F39: ผลผลิตปีฐาน | H39: 9586 | J39: =J37
F40: ข้อมูลองค์กร
F41: 1 | G41: ผลิตสินค้าเม็ดพลาสติก
F42: 2 | G42: ผลิตสินค้าถุงพลาสติก
F43: 3
F44: 4
F45: 5
F46: สถานที่ติดต่อ | I46: 211 หมู่ที่ 3 ต.ทุ่งสุขลา อ.ศรีราชา จ.ชลบุรี
F47: วันที่ขอขึ้นทะเบียน | I47: 243865
A49: การแสดงเครื่องหมาย | F49: กราฟแท่งแสดงการปล่อย GHG แต่ละขอบเขต

Sheet Fr-02
B1: แผนภาพองค์กร | L1: TCFO_R_01 Version 04 : 21/2/2020
B3: ชื่อฟอร์ม | C3: บัญชีรายการก๊าซเรือนกระจก | F3: องค์กร | G3: ='Fr-01'!$B$6 | L3: หน้าที่ | M3: 2
B4: รหัสฟอร์ม | C4: Fr-02 | F4: ผู้จัดทำ | G4: ='Fr-01'!$G$4 | L4: วันที่ | M4: ='Fr-01'!J4

Sheet Fr-03.1
B1: แผนภาพแสดงโครงสร้างขององค์กรและหน้าที่ความรับผิดชอบ | L1: TCFO_R_01 Version 04 : 21/2/2020
B3: ชื่อฟอร์ม | C3: บัญชีรายการก๊าซเรือนกระจก | F3: องค์กร | G3: ='Fr-01'!$B$6 | L3: หน้าที่ | M3: 3
B4: รหัสฟอร์ม | C4: Fr-03.1 | F4: ผู้จัดทำ | G4: ='Fr-01'!$G$4 | L4: วันที่ | M4: ='Fr-01'!J4
A35: จัดทำโดย | B35: ='Fr-01'!G4 | J35: เสร็จสิ้นวันที่ | K35: 243829

Sheet Fr-03.2
B1: ประเมินความมีนัยสำคัญของการปล่อยก๊าซเรือนกระจกทางอ้อม (SCOPE 3) | O1: TCFO_R_01 Version 04 : 21/2/2020
B3: ชื่อฟอร์ม | C3: ประเมินความมีนัยสำคัญ Scope3 | E3: องค์กร | F3: ='Fr-01'!G3 | O3: หน้าที่ | P3: 3
B4: รหัสฟอร์ม | C4: Fr-03.2 | E4: ผู้จัดทำ | F4: ='Fr-01'!G4 | O4: วันที่ | P4: ='Fr-01'!J4
A6: คำอธิบาย | B6: องค์กรจะต้องคัดเลือกแหล่งปล่อยก๊าซเรือนกระจกทางอ้อม (Scope 3) โดยกำหนดเกณฑ์ในการประเมินความมีนัยสำคัญของการปล่อยก๊าซเรือนกระจกทางอ้อม (Scope 3)
A8: ประเด็นที่ต้องพิจารณา | C8: คำอธิบาย
A9: Source of GHG | C9: องค์กรมีแหล่งปล่อยก๊าซเรือนกระจกนี้หรือไม่
A10: ขนาด (Magnitude or Size) | C10: เป็นกิจกรรมการปล่อยหรือดูดกลับก๊าซเรือนกระจกทางอ้อมซึ่งถูกสันนิษฐานว่ามีปริมาณการปล่อยหรือดูดกลับก๊าซเรือนกระจกในปริมาณมากอย่างมีนัยสำคัญ
A11: ระดับของแรงจูงใจ (Level of influence (Reduction of potential)) | C11: เป็นกิจกรรมการปล่อยหรือดูดกลับก๊าซเรือนกระจกที่องค์กรมีความสามารถในการตรวจติดตามและลดปริมาณการปล่อยหรือดูดกลับก๊าซเรือนกระจกจากกิจกรรมนั้น(ตัวอย่างเช่นเป็นกิจกรรมที่เกี่ยวข้องกับการประเมินประสิทธิภาพพลังงาน การออกแบบเชิงนิเวศเศรษฐกิจ, เกี่ยวข้องกับข้อตกลงที่มีกับลูกค้า, เกี่ยวข้องกับข้อกำหนดขอบเขตงานจากผู้ว่าจ้าง)
A12: ความเสี่ยง หรือ โอกาส Risk or opportunity | C12: เป็นกิจกรรมการปล่อยหรือดูดกลับก๊าซเรือนกระจกทางอ้อมซึ่งมีส่วนทำให้องค์กรได้รับความเสี่ยง (ตัวอย่างของความเสี่ยงที่มีความเชื่อมโยงกับการเปลี่ยนแปลงสภาพภูมิอากาศ เช่น ความเสี่ยงทางด้านการเงิน, ความเสี่ยงทางด้านกฎระเบียบข้อบังคับ, ความเสี่ยงตลอดห่วงโซ่อุปทาน, ความเสี่ยงเกี่ยวกับสินค้าและลูกค้า, ความเสี่ยงเกี่ยวกับการดำเนินคดี และ ความเสี่ยงด้านชื่อเสียง) หรือได้รับโอกาสต่างๆ ทางธุรกิจ (เช่น การเข้าสู่ช่องทางตลาดใหม่ การเข้าสู่ระบบธุรกิจในรูปแบบใหม่)
A13: Sector Guidance | C13: เป็นกิจกรรมการปล่อยก๊าซเรือนกระจกที่ถูกถือว่ามีนัยสำคัญสำหรับอุตสาหกรรมที่กำลังพิจารณา ตามที่กำหนดไว้ในคู่มือหรือแนวทางที่เฉพาะเจาะจงสำหรับอุตสาหกรรมนั้น
A14: Outsourcing | C14: เป็นกิจกรรมการปล่อยและดูดกลับก๊าซเรือนกระจกทางอ้อมที่เกิดจากการจัดจ้างบุคคลหรือหน่วยงานภายนอกเข้ามาดำเนินกิจกรรมที่ถือว่า เป็นกิจกรรมหลักในการดำเนินธุรกิจขององค์กร
A15: Employee engagement | C15: เป็นกิจกรรมการปล่อยก๊าซเรือนกระจกทางอ้อมที่สามารถส่งเสริมให้เกิดการกระตุ้นให้พนักงานมีส่วนร่วมในการลดการปล่อยก๊าซเรือนกระจก ผ่านการลดการใช้พลังงาน หรือการทำงานร่วมกันเป็นทีมภายใต้หลักคิดที่เกี่ยวข้องกับการเปลี่ยนแปลงสภาพภูมิอากาศ (เช่น การสร้างแรงจูงใจในการอนุรักษ์พลังงาน, การเดินทาง โดยใช้รถร่วมกัน, การประเมินราคาคาร์บอนภายในองค์กร เป็นต้น)
A16: ที่มา : หัวข้อที่ 12 ข้อกำหนดในการคำนวณและรายงานคาร์บอนฟุตพริ้นท์ขององค์กร พิมพ์ครั้งที่ 7 (ฉบับปรับปรุงครั้งที่ 5, มกราคม 2564)
C19: น้ำหนักประเด็นที่พิจารณา | F19: 0.6 | G19: 0.2 | H19: 0.1 | I19: 0.1
A20: No. TGO | B20: Scope in ISO 14064-1 | C20: Category | D20: Source of GHG | E20: Source of EF | F20: Magnitude | G20: Level of influence (Reduction of potential) | H20: Risk | I20: Oppoturnity | J20: ผลคะแนน | K20: ผลการประเมิน | L20: ผลการคัดเลือก | M20: GHG (tCO2eq.) | N20: %
A21: 3.1 | B21: 4.1 | C21: Purchased Goods & Services
C22: ='Screen scope 3'!C3 | D22: 1 | E22: 1 | F22: 3 | G22: 3 | H22: 3 | I22: 5 | J22: =D22+E22+(F22*$F$19)+(G22*$G$19)+(H22*$H$19)+(I22*$I$19) | K22: มีนัยสำคัญ | L22: เลือกประเมิน | M22: ='Screen scope 3'!I3 | N22: ='Screen scope 3'!J3
C23: ='Screen scope 3'!C4 | D23: 1 | E23: 1 | F23: 3 | G23: 3 | H23: 3 | I23: 5 | J23: =D23+E23+(F23*$F$19)+(G23*$G$19)+(H23*$H$19)+(I23*$I$19) | K23: มีนัยสำคัญ | L23: เลือกประเมิน | M23: ='Screen scope 3'!I4 | N23: ='Screen scope 3'!J4
C24: ='Screen scope 3'!C5 | D24: 1 | E24: 1 | F24: 3 | G24: 3 | H24: 3 | I24: 5 | J24: =D24+E24+(F24*$F$19)+(G24*$G$19)+(H24*$H$19)+(I24*$I$19) | K24: มีนัยสำคัญ | L24: เลือกประเมิน | M24: ='Screen scope 3'!I5 | N24: ='Screen scope 3'!J5
C25: ='Screen scope 3'!C6 | D25: 1 | E25: 1 | F25: 1 | G25: 1 | H25: 1 | I25: 1 | J25: =D25+E25+(F25*$F$19)+(G25*$G$19)+(H25*$H$19)+(I25*$I$19) | K25: ไม่มีนัยสำคัญ | M25: ='Screen scope 3'!I6 | N25: ='Screen scope 3'!J6
C26: ='Screen scope 3'!C7 | D26: 1 | E26: 1 | F26: 1 | G26: 1 | H26: 1 | I26: 1 | J26: =D26+E26+(F26*$F$19)+(G26*$G$19)+(H26*$H$19)+(I26*$I$19) | K26: ไม่มีนัยสำคัญ | M26: ='Screen scope 3'!I7 | N26: ='Screen scope 3'!J7
C27: ='Screen scope 3'!C8 | D27: 1 | E27: 1 | F27: 1 | G27: 1 | H27: 1 | I27: 1 | J27: =D27+E27+(F27*$F$19)+(G27*$G$19)+(H27*$H$19)+(I27*$I$19) | K27: ไม่มีนัยสำคัญ | M27: ='Screen scope 3'!I8 | N27: ='Screen scope 3'!J8
C28: ='Screen scope 3'!C9 | D28: 1 | E28: 1 | F28: 1 | G28: 1 | H28: 1 | I28: 1 | J28: =D28+E28+(F28*$F$19)+(G28*$G$19)+(H28*$H$19)+(I28*$I$19) | K28: ไม่มีนัยสำคัญ | M28: ='Screen scope 3'!I9 | N28: ='Screen scope 3'!J9
C29: ='Screen scope 3'!C10 | D29: 1 | E29: 1 | F29: 1 | G29: 1 | H29: 1 | I29: 1 | J29: =D29+E29+(F29*$F$19)+(G29*$G$19)+(H29*$H$19)+(I29*$I$19) | K29: ไม่มีนัยสำคัญ | M29: ='Screen scope 3'!I10 | N29: ='Screen scope 3'!J10
C30: ='Screen scope 3'!C11 | D30: 1 | E30: 1 | F30: 1 | G30: 1 | H30: 1 | I30: 1 | J30: =D30+E30+(F30*$F$19)+(G30*$G$19)+(H30*$H$19)+(I30*$I$19) | K30: ไม่มีนัยสำคัญ | M30: ='Screen scope 3'!I11 | N30: ='Screen scope 3'!J11
C31: ='Screen scope 3'!C12 | D31: 1 | E31: 1 | F31: 1 | G31: 1 | H31: 1 | I31: 1 | J31: =D31+E31+(F31*$F$19)+(G31*$G$19)+(H31*$H$19)+(I31*$I$19) | K31: ไม่มีนัยสำคัญ | M31: ='Screen scope 3'!I12 | N31: ='Screen scope 3'!J12
C32: ='Screen scope 3'!C13 | D32: 1 | E32: 1 | F32: 1 | G32: 1 | H32: 1 | I32: 1 | J32: =D32+E32+(F32*$F$19)+(G32*$G$19)+(H32*$H$19)+(I32*$I$19) | K32: ไม่มีนัยสำคัญ | M32: ='Screen scope 3'!I13+'Screen scope 3'!I14 | N32: ='Screen scope 3'!J13+'Screen scope 3'!J14
A33: 3.2 | B33: 4.2 | C33: Capital goods | D33: 1 | E33: 0 | J33: =D33+E33+(F33*$F$19)+(G33*$G$19)+(H33*$H$19)+(I33*$I$19) | K33: ไม่มีนัยสำคัญ/มีนัยสำคัญ
A34: 3.3 | B34: 2.2 | C34: Fuel- and energy related activities
C35: ='Screen scope 3'!C16 | D35: 1 | E35: 1 | F35: 1 | G35: 1 | H35: 1 | I35: 1 | J35: =D35+E35+(F35*$F$19)+(G35*$G$19)+(H35*$H$19)+(I35*$I$19) | K35: ไม่มีนัยสำคัญ | M35: ='Screen scope 3'!I16 | N35: ='Screen scope 3'!J16
C36: ='Screen scope 3'!C17 | D36: 1 | E36: 1 | F36: 1 | G36: 1 | H36: 1 | I36: 1 | J36: =D36+E36+(F36*$F$19)+(G36*$G$19)+(H36*$H$19)+(I36*$I$19) | K36: ไม่มีนัยสำคัญ | M36: ='Screen scope 3'!I17 | N36: ='Screen scope 3'!J17
C37: ='Screen scope 3'!C18 | D37: 1 | E37: 1 | F37: 1 | G37: 1 | H37: 1 | I37: 1 | J37: =D37+E37+(F37*$F$19)+(G37*$G$19)+(H37*$H$19)+(I37*$I$19) | K37: ไม่มีนัยสำคัญ | M37: ='Screen scope 3'!I18 | N37: ='Screen scope 3'!J18
C38: ='Screen scope 3'!C19 | D38: 1 | E38: 1 | F38: 1 | G38: 1 | H38: 1 | I38: 1 | J38: =D38+E38+(F38*$F$19)+(G38*$G$19)+(H38*$H$19)+(I38*$I$19) | K38: ไม่มีนัยสำคัญ | M38: ='Screen scope 3'!I19 | N38: ='Screen scope 3'!J19
A39: 3.4 | B39: 3.1 | C39: Upstream transportation and distribution
C40: ='Screen scope 3'!C21 | D40: 1 | E40: 1 | F40: 1 | G40: 1 | H40: 1 | I40: 1 | J40: =D40+E40+(F40*$F$19)+(G40*$G$19)+(H40*$H$19)+(I40*$I$19) | K40: ไม่มีนัยสำคัญ | M40: ='Screen scope 3'!I21 | N40: ='Screen scope 3'!J21
C41: ='Screen scope 3'!C22 | D41: 1 | E41: 1 | F41: 1 | G41: 1 | H41: 1 | I41: 1 | J41: =D41+E41+(F41*$F$19)+(G41*$G$19)+(H41*$H$19)+(I41*$I$19) | K41: ไม่มีนัยสำคัญ | M41: ='Screen scope 3'!I22 | N41: ='Screen scope 3'!J22
C42: ='Screen scope 3'!C23 | D42: 1 | E42: 1 | F42: 1 | G42: 1 | H42: 1 | I42: 1 | J42: =D42+E42+(F42*$F$19)+(G42*$G$19)+(H42*$H$19)+(I42*$I$19) | K42: ไม่มีนัยสำคัญ | M42: ='Screen scope 3'!I23 | N42: ='Screen scope 3'!J23
C43: ='Screen scope 3'!C24 | D43: 1 | E43: 1 | F43: 1 | G43: 1 | H43: 1 | I43: 1 | J43: =D43+E43+(F43*$F$19)+(G43*$G$19)+(H43*$H$19)+(I43*$I$19) | K43: ไม่มีนัยสำคัญ | M43: ='Screen scope 3'!I24 | N43: ='Screen scope 3'!J24
C44: ='Screen scope 3'!C25 | D44: 1 | E44: 1 | F44: 1 | G44: 1 | H44: 1 | I44: 1 | J44: =D44+E44+(F44*$F$19)+(G44*$G$19)+(H44*$H$19)+(I44*$I$19) | K44: ไม่มีนัยสำคัญ | M44: ='Screen scope 3'!I25 | N44: ='Screen scope 3'!J25
C45: ='Screen scope 3'!C26 | D45: 1 | E45: 1 | F45: 1 | G45: 1 | H45: 1 | I45: 1 | J45: =D45+E45+(F45*$F$19)+(G45*$G$19)+(H45*$H$19)+(I45*$I$19) | K45: ไม่มีนัยสำคัญ | M45: ='Screen scope 3'!I26 | N45: ='Screen scope 3'!J26
C46: ='Screen scope 3'!C27 | D46: 1 | E46: 1 | F46: 1 | G46: 1 | H46: 1 | I46: 1 | J46: =D46+E46+(F46*$F$19)+(G46*$G$19)+(H46*$H$19)+(I46*$I$19) | K46: ไม่มีนัยสำคัญ | M46: ='Screen scope 3'!I27 | N46: ='Screen scope 3'!J27
A47: 3.5 | B47: 4.3 | C47: Waste generated in operations
C48: ='Screen scope 3'!C29
C49: ='Screen scope 3'!C30 | D49: 1 | E49: 1 | F49: 1 | G49: 1 | H49: 1 | I49: 1 | J49: =D49+E49+(F49*$F$19)+(G49*$G$19)+(H49*$H$19)+(I49*$I$19) | K49: ไม่มีนัยสำคัญ | M49: ='Screen scope 3'!I30 | N49: ='Screen scope 3'!J30
C50: ='Screen scope 3'!C31 | D50: 1 | E50: 1 | F50: 1 | G50: 1 | H50: 1 | I50: 1 | J50: =D50+E50+(F50*$F$19)+(G50*$G$19)+(H50*$H$19)+(I50*$I$19) | K50: ไม่มีนัยสำคัญ | M50: ='Screen scope 3'!I31 | N50: ='Screen scope 3'!J31
C51: ='Screen scope 3'!C32
C52: ='Screen scope 3'!C33 | D52: 1 | E52: 1 | F52: 1 | G52: 1 | H52: 1 | I52: 1 | J52: =D52+E52+(F52*$F$19)+(G52*$G$19)+(H52*$H$19)+(I52*$I$19) | K52: ไม่มีนัยสำคัญ | M52: ='Screen scope 3'!H33 | N52: ='Screen scope 3'!J33
C53: ='Screen scope 3'!C34 | D53: 1 | E53: 1 | F53: 1 | G53: 1 | H53: 1 | I53: 1 | J53: =D53+E53+(F53*$F$19)+(G53*$G$19)+(H53*$H$19)+(I53*$I$19) | K53: ไม่มีนัยสำคัญ | M53: ='Screen scope 3'!I34 | N53: ='Screen scope 3'!J34
C54: ='Screen scope 3'!C35 | D54: 1 | E54: 1 | F54: 1 | G54: 1 | H54: 1 | I54: 1 | J54: =D54+E54+(F54*$F$19)+(G54*$G$19)+(H54*$H$19)+(I54*$I$19) | K54: ไม่มีนัยสำคัญ | M54: ='Screen scope 3'!I35 | N54: ='Screen scope 3'!J35
C55: ='Screen scope 3'!C36 | D55: 1 | E55: 1 | F55: 1 | G55: 1 | H55: 1 | I55: 1 | J55: =D55+E55+(F55*$F$19)+(G55*$G$19)+(H55*$H$19)+(I55*$I$19) | K55: ไม่มีนัยสำคัญ | M55: ='Screen scope 3'!I36 | N55: ='Screen scope 3'!J36
A56: 3.6 | B56: 3.5 | C56: Business travel
C57: ไม่มี | D57: 1 | E57: 1 | F57: 1 | G57: 1 | H57: 1 | I57: 1 | J57: =D57+E57+(F57*$F$19)+(G57*$G$19)+(H57*$H$19)+(I57*$I$19) | K57: ไม่มีนัยสำคัญ | M57: 0 | N57: 0
A58: 3.7 | B58: 3.3 | C58: Employee commuting
C59: ='Screen scope 3'!C38 | D59: 1 | E59: 1 | F59: 1 | G59: 1 | H59: 1 | I59: 1 | J59: =D59+E59+(F59*$F$19)+(G59*$G$19)+(H59*$H$19)+(I59*$I$19) | K59: ไม่มีนัยสำคัญ | M59: ='Screen scope 3'!I38 | N59: ='Screen scope 3'!J38
C60: ='Screen scope 3'!C39 | D60: 1 | E60: 1 | F60: 1 | G60: 1 | H60: 1 | I60: 1 | J60: =D60+E60+(F60*$F$19)+(G60*$G$19)+(H60*$H$19)+(I60*$I$19) | K60: ไม่มีนัยสำคัญ | M60: ='Screen scope 3'!I39 | N60: ='Screen scope 3'!J39
A61: 3.8 | B61: 4.4 | C61: Upstream leased assets | D61: 1 | J61: =D61+E61+(F61*$F$19)+(G61*$G$19)+(H61*$H$19)+(I61*$I$19) | K61: ไม่มีนัยสำคัญ/มีนัยสำคัญ
A62: 3.9 | B62: 3.2 | C62: Downstream transportation and distribution
C63: ='Screen scope 3'!C41 | D63: 1 | E63: 1 | F63: 1 | G63: 1 | H63: 1 | I63: 1 | J63: =D63+E63+(F63*$F$19)+(G63*$G$19)+(H63*$H$19)+(I63*$I$19) | K63: ไม่มีนัยสำคัญ | M63: ='Screen scope 3'!I41 | N63: ='Screen scope 3'!J41
C64: ='Screen scope 3'!C42 | D64: 1 | E64: 1 | F64: 1 | G64: 1 | H64: 1 | I64: 1 | J64: =D64+E64+(F64*$F$19)+(G64*$G$19)+(H64*$H$19)+(I64*$I$19) | K64: ไม่มีนัยสำคัญ | M64: ='Screen scope 3'!I42 | N64: ='Screen scope 3'!J42
C65: ='Screen scope 3'!C43 | D65: 1 | E65: 1 | F65: 1 | G65: 1 | H65: 1 | I65: 1 | J65: =D65+E65+(F65*$F$19)+(G65*$G$19)+(H65*$H$19)+(I65*$I$19) | K65: ไม่มีนัยสำคัญ | M65: ='Screen scope 3'!I43 | N65: ='Screen scope 3'!J43
A66: *3.10 | B66: 5 | C66: Processing of sold products | D66: 0 | J66: =D66+E66+(F66*$F$19)+(G66*$G$19)+(H66*$H$19)+(I66*$I$19) | K66: ไม่มีนัยสำคัญ/มีนัยสำคัญ
A67: 3.11 | B67: 4.4 | C67: Use of sold products | D67: 0 | J67: =D67+E67+(F67*$F$19)+(G67*$G$19)+(H67*$H$19)+(I67*$I$19) | K67: ไม่มีนัยสำคัญ/มีนัยสำคัญ
A68: 3.12 | B68: 5 | C68: End-of-life treatment of sold products
C69: ='Screen scope 3'!C45 | D69: 1 | E69: 1 | F69: 3 | G69: 1 | H69: 1 | I69: 1 | J69: =D69+E69+(F69*$F$19)+(G69*$G$19)+(H69*$H$19)+(I69*$I$19) | K69: ไม่มีนัยสำคัญ | M69: ='Screen scope 3'!I45 | N69: ='Screen scope 3'!J45
A70: 3.13 | B70: 6 | C70: Downstream leased assets | D70: 0 | J70: =D70+E70+(F70*$F$19)+(G70*$G$19)+(H70*$H$19)+(I70*$I$19) | K70: ไม่มีนัยสำคัญ/มีนัยสำคัญ
A71: 3.14 | B71: 6 | C71: Franchises | D71: 0 | J71: =D71+E71+(F71*$F$19)+(G71*$G$19)+(H71*$H$19)+(I71*$I$19) | K71: ไม่มีนัยสำคัญ/มีนัยสำคัญ
A72: 3.15 | B72: 6 | C72: Investments | D72: 0 | J72: =D72+E72+(F72*$F$19)+(G72*$G$19)+(H72*$H$19)+(I72*$I$19) | K72: ไม่มีนัยสำคัญ/มีนัยสำคัญ
A74: อธิบาย หลักเกณฑ์ในการประเมินความมีนัยสำคัญ
C76: เกณฑ์การประเมินความมีนัยสำคัญ
B77: ประเด็นที่ต้องพิจารณา | D77: ระดับคะแนน | H77: น้ำหนักประเด็นที่พิจารณา
D78: 0 | E78: 1 | F78: 3 | G78: 5
B79: Source of GHG | D79: ไม่มี | E79: มี | H79: ถ้า Source of GHG and Source of Ef อันใดอันหนึ่งไม่มี จะไม่ทำการประเมินต่อ
B80: Source of EF | D80: ไม่ได้ | E80: ได้
B81: Magnitude/ Size | E81: 0<GHG of Scope 3<5% | F81: 5%≤GHG of Scope 3≤40% | G81: >40% of Scope 3 | H81: 0.6
B82: Level of influence (Reduction of potential) | E82: องค์กรไม่มีเป้าประสงค์ในการลดก๊าซเรือนกระจก | F82: องค์กรยังไม่มีเป้าประสงค์ในการลดก๊าซเรือนกระจก แต่มีแนวทางในการลดก๊าซเรือนกระจกที่อาจประยุกต์ใช้ได้ | G82: องค์กรมีเป้าประสงค์ในการลดก๊าซเรือนกระจกและมีแนวทางในการลดก๊าซเรือนกระจกที่ประยุกต์ใช้ได้ | H82: 0.2
B83: Risk | E83: ไม่มีกฎระเบียบหรือข้อบังคับให้ต้องทำการรายงาน | F83: ลูกค้า/ผู้มีส่วนได้เสีย ร้องขอให้รายงาน | G83: กฎหมายบังคับให้รายงาน | H83: 0.1
B84: Opportunity | E84: ยังไม่มีช่องทางของโอกาสด้านธุรกิจเกี่ยวกับการรายงาน GHG | F84: - | G84: มีโอกาสเข้าสู่ช่องทางตลาดใหม่ หากทำรายงาน GHG | H84: 0.1
C85: >5 - 7 คะแนน เป็นแหล่งปล่อยที่มีนัยสำคัญ นับรวมในขอบเขตการประเมิน
C86: 0 - <=5 คะแนน เป็นแหล่งปล่อยที่ไม่มีนัยสำคัญ ไม่นับรวมในขอบเขตการประเมิน

Sheet Screen scope 3
A1: No. TGO | B1: Scope in ISO 14064-1 | C1: Category | D1: หน่วย | E1: ปริมาณ (ต่อปี) | F1: หมายเหตุ | G1: หลักฐานอ้างอิง (การได้มาซึ่งข้อมูล) | H1: ค่าการปล่อยก๊าซเรือนกระจก (EF) | I1: GHG (tCO2eq.) | J1: % | K1: หลักฐานอ้างอิง (Emission Factor)
A2: Scope 3.1 | B2: Scope 4.1 in ISO 14064-1 | C2: Purchased Goods & Services
C3: ='Scope 3.1.1 วัตถุดิบผลิต'!A4 | D3: ='Scope 3.1.1 วัตถุดิบผลิต'!E4 | E3: ='Scope 3.1.1 วัตถุดิบผลิต'!F4 | G3: ระบบ ERP | H3: =2.6258 | I3: =E3*H3/1000 | J3: =I3/$I$46*100 | K3: TGO-CFP-EF-(ก.ค. 65)-6 LDPE
C4: ='Scope 3.1.1 วัตถุดิบผลิต'!A7 | D4: ='Scope 3.1.1 วัตถุดิบผลิต'!E7 | E4: ='Scope 3.1.1 วัตถุดิบผลิต'!F7 | G4: ระบบ ERP | H4: =2.1356 | I4: =E4*H4/1000 | J4: =I4/$I$46*100 | K4: TGO-CFP-EF-(ก.ค. 65)-5 LLDPE
C5: ='Scope 3.1.1 วัตถุดิบผลิต'!A12 | D5: ='Scope 3.1.1 วัตถุดิบผลิต'!E12 | E5: ='Scope 3.1.1 วัตถุดิบผลิต'!F12 | G5: ระบบ ERP | H5: =6.7071 | I5: =E5*H5/1000 | J5: =I5/$I$46*100 | K5: TGO-CFP-EF-(ก.ค. 65)-3 HDPE
C6: ='Scope 3.1.1 วัตถุดิบผลิต'!A15 | D6: ='Scope 3.1.1 วัตถุดิบผลิต'!E15 | E6: ='Scope 3.1.1 วัตถุดิบผลิต'!F15 | G6: ระบบ ERP | H6: 1.8679 | I6: =E6*H6/1000 | J6: =I6/$I$46*100 | K6: TGO-CFP-EF-(ก.ค. 65)-597 กระดาษกล่องขาวเคลือบแป้ง/กระดาษกล่องแป้งหลังเทา
C7: ='Scope 3.1.1 วัตถุดิบผลิต'!A19 | D7: ='Scope 3.1.1 วัตถุดิบผลิต'!E19 | E7: ='Scope 3.1.1 วัตถุดิบผลิต'!F19 | G7: ระบบ ERP | H7: 1.6184 | I7: =E7*H7/1000 | J7: =I7/$I$46*100 | K7: TGO-CFP-EF-(ก.ค. 65)-596 กระดาษคราฟท์ ชนิดท าลอน
C8: ='Scope 3.1.2 น้ำประปา'!A3 | D8: ='Scope 3.1.2 น้ำประปา'!D3 | E8: ='Scope 3.1.2 น้ำประปา'!E3 | G8: ='Scope 3.1.2 น้ำประปา'!C3 | H8: 0.2575 | I8: =E8*H8/1000 | J8: =I8/$I$46*100 | K8: TGO-CFP-EF-(ก.ค. 65)-62 น้ำประปา-การนิคมอุตสาหกรรม
C9: ='Scope 3.1.2 น้ำประปา'!A8 | D9: ='Scope 3.1.2 น้ำประปา'!D8 | E9: ='Scope 3.1.2 น้ำประปา'!E8 | G9: ='Scope 3.1.2 น้ำประปา'!C8 | H9: 0.7948 | I9: =E9*H9/1000 | J9: =I9/$I$46*100 | K9: TGO-CFP-EF-(ก.ค. 65)-60 น้ำประปา-การประปานครหลวง
C10: ='Scope 3.1.3 กระดาษ A4'!A5 | D10: ='Scope 3.1.3 กระดาษ A4'!C5 | E10: ='Scope 3.1.3 กระดาษ A4'!D5 | G10: ใบสั่งซื้อ | H10: 2.102 | I10: =E10*H10/1000 | J10: =I10/$I$46*100 | K10: TGO-CFP-EF-(ก.ค. 65)-592 กระดาษพิมพ์เขียนแบบไม่เคลือบผิว
C11: ='Scope 3.1.3 กระดาษ A4'!A8 | D11: ='Scope 3.1.3 กระดาษ A4'!C8 | E11: ='Scope 3.1.3 กระดาษ A4'!D8 | G11: ใบสั่งซื้อ | H11: 2.102 | I11: =E11*H11/1000 | J11: =I11/$I$46*100 | K11: TGO-CFP-EF-(ก.ค. 65)-592 กระดาษพิมพ์เขียนแบบไม่เคลือบผิว
C12: ='1.4.4 ปุ๋ย'!A3 | D12: ='1.4.4 ปุ๋ย'!C3 | E12: ='1.4.4 ปุ๋ย'!D3 | G12: ='1.4.4 ปุ๋ย'!B3 | H12: ='1.4.4 ปุ๋ย'!Q4 | I12: =E12*H12/1000 | J12: =I12/$I$46*100 | K12: TGO guildline
C13: ='Scope 3.1.4 จ้างเหมารถพนักงาน'!A4 | D13: L | E13: ='Scope 3.1.4 จ้างเหมารถพนักงาน'!J4 | G13: ใบแจ้งหนี้ | H13: ='EF TGO AR5'!H29 | I13: =E13*H13/1000 | J13: =I13/$I$46*100 | K13: TGO-CFO-EF: sheet ET TGO AR5
C14: ='Scope 3.1.4 จ้างเหมารถพนักงาน'!A4 | D14: kg | E14: =E13*0.83 | G14: ใบแจ้งหนี้ | H14: 0.3522 | I14: =E14*H14/1000 | J14: =I14/$I$46*100 | K14: TGO-CFP-EF-(ก.ค. 65)-55 Diesel (น้ำมันดีเซล / น้ำมันโซล่าร์)
A15: Scope 3.3 | B15: Scope 2.2 in ISO 14064-1 | C15: Capital goods
C16: การได้มาของไฟฟ้า | D16: kwh | E16: ='Scope 2.1 Purchased Electricity'!E3+'Scope 2.1 Purchased Electricity'!E7+'Scope 2.1 Purchased Electricity'!E12+'Scope 2.1 Purchased Electricity'!E15 | G16: ใบแจ้งหนี้/หนังสือแจ้งค่าไฟฟ้า | H16: =0.5986-0.4999 | I16: =E16*H16/1000 | J16: =I16/$I$46*100 | K16: CFO-EF - CFP-EF-ไฟฟ้า
C17: การได้มา Acetylene | D17: kg | E17: ='1.1 Stationary'!D11 | G17: บิลเงินสด/ใบเสร็จรับเงิน | H17: 2.2804 | I17: =E17*H17/1000 | J17: =I17/$I$46*100 | K17: TGO-CFP-EF-(ก.ค. 65)-654 acetylene
C18: การได้มา Diesel | D18: kg | E18: =('1.1 Stationary'!D9+'1.2 Mobile'!F13+'1.2 Mobile'!F57)*0.83 | G18: Fleet card/ใบเสร็จรับเงิน | H18: 0.3522 | I18: =E18*H18/1000 | J18: =I18/$I$46*100 | K18: TGO-CFP-EF-(ก.ค. 65)-55 Diesel (น้ำมันดีเซล / น้ำมันโซล่าร์)
C19: การได้มา Gasoline | D19: kg | E19: =('1.1 Stationary'!D10+'1.2 Mobile'!F43)*0.75 | G19: Fleet card/ใบเสร็จรับเงิน | H19: 0.4024 | I19: =E19*H19/1000 | J19: =I19/$I$46*100 | K19: TGO-CFP-EF-(ก.ค. 65)-52 Gasoline (แก๊สโซลีน)
A20: Scope 3.4 | B20: Scope 3.1 in ISO 14064-1 | C20: Upstream transportation and distribution
C21: รถตู้บรรทุก 10 ล้อ 100% loading | D21: tkm | E21: ='Scope 3.4'!I4 | G21: ใบส่งสินค้า/ใบกำกับภาษี | H21: 0.0454 | I21: =E21*H21/1000 | J21: =I21/$I$46*100 | K21: TGO-CFP-EF-(ก.ค. 65)-125 รถตู้บรรทุก 10 ล้อ วิ่งปกติ 100% Loading
C22: รถตู้บรรทุก 10 ล้อ 0% loading | D22: km | E22: ='Scope 3.4'!J4 | G22: ใบส่งสินค้า/ใบกำกับภาษี | H22: 0.5747 | I22: =E22*H22/1000 | J22: =I22/$I$46*100 | K22: TGO-CFP-EF-(ก.ค. 65)-122 รถตู้บรรทุก 10 ล้อ วิ่งปกติ 0% Loading
C23: รถตู้บรรทุก 6 ล้อ ขนาดใหญ่ 100% loading | D23: tkm | E23: ='Scope 3.4'!K4 | G23: ใบส่งสินค้า/ใบกำกับภาษี | H23: 0.0547 | I23: =E23*H23/1000 | J23: =I23/$I$46*100 | K23: TGO-CFP-EF-(ก.ค. 65)-109 รถตู้บรรทุก 6 ล้อ ขนาดใหญ่ วิ่งปกติ 100% Loading
C24: รถตู้บรรทุก 6 ล้อ ขนาดใหญ่ 0% loading | D24: km | E24: ='Scope 3.4'!L4 | G24: ใบส่งสินค้า/ใบกำกับภาษี | H24: 0.4373 | I24: =E24*H24/1000 | J24: =I24/$I$46*100 | K24: TGO-CFP-EF-(ก.ค. 65)-106 รถตู้บรรทุก 6 ล้อ ขนาดใหญ่ วิ่งปกติ 0% Loading
C25: รถตู้บรรทุก 4 ล้อ 100% loading | D25: tkm | E25: ='Scope 3.4'!M4 | G25: ใบส่งสินค้า/ใบกำกับภาษี | H25: 0.1835 | I25: =E25*H25/1000 | J25: =I25/$I$46*100 | K25: TGO-CFP-EF-(ก.ค. 65)-77 รถตู้บรรทุก 4 ล้อ วิ่งแบบปกติ 100% Loading
C26: รถตู้บรรทุก 4 ล้อ 0% loading | D26: km | E26: ='Scope 3.4'!N4 | G26: ใบส่งสินค้า/ใบกำกับภาษี | H26: 0.3345 | I26: =E26*H26/1000 | J26: =I26/$I$46*100 | K26: TGO-CFP-EF-(ก.ค. 65)-74 รถตู้บรรทุก 4 ล้อ วิ่งแบบปกติ 0% Loading
C27: เรือบรรทุก container | D27: tkm | E27: ='Scope 3.4'!O4 | G27: ใบส่งสินค้า/ใบกำกับภาษี | H27: 0.0107 | I27: =E27*H27/1000 | J27: =I27/$I$46*100 | K27: TGO-CFP-EF-(ก.ค. 65)-255 เรือบรรทุก container
A28: Scope 3.5 | B28: Scope 4.3 in ISO 14064-1 | C28: Waste generated in operations
C29: การกำจัดของเสีย
C30: ='Scope 3.5'!A4 | D30: kg | E30: ='Scope 3.5'!F4 | G30: ใบกำกับการขนส่งขยะมูลฝอย | H30: 0.7933 | I30: =E30*H30/1000 | J30: =I30/$I$46*100 | K30: TGO-CFP-EF-(ก.ค. 65)-การฝังกลบขยะมูลฝอยชุมชนแบบถูกหลักสุขาภิบาล
C31: ='Scope 3.5'!A5 | D31: kg | E31: ='Scope 3.5'!F5 | G31: ใบกำกับการขนส่งของเสียอันตราย | H31: 0.7933 | I31: =E31*H31/1000 | J31: =I31/$I$46*100 | K31: TGO-CFP-EF-(ก.ค. 65)-การฝังกลบขยะมูลฝอยชุมชนแบบถูกหลักสุขาภิบาล (แทน)
C32: การขนส่ง
C33: รถกระบะบรรทุก 10 ล้อ วิ่งปกติ 100% loading | D33: tkm | E33: ='Scope 3.5'!F23 | G33: การประมาณการ | H33: 0.0533 | I33: =E33*H33/1000 | J33: =I33/$I$46*100
C34: รถกระบะบรรทุก 10 ล้อ วิ่งปกติ 0% loading | D34: km | E34: ='Scope 3.5'!G23 | G34: การประมาณการ | H34: 0.59 | I34: =E34*H34/1000 | J34: =I34/$I$46*100
C35: รถบรรทุกขยะ 6 ล้อ 100% loading | D35: tkm | E35: ='Scope 3.5'!J23 | G35: การประมาณการ | H35: 0.0475 | I35: =E35*H35/1000 | J35: =I35/$I$46*100 | K35: TGO-CFP-EF-(ก.ค. 65)-รถบรรทุกขยะ 6 ล้อ วิ่ง แบบปกติ 100% Loading
C36: รถบรรทุกขยะ 6 ล้อ 0% loading | D36: km | E36: ='Scope 3.5'!K23 | G36: การประมาณการ | H36: 0.4923 | I36: =E36*H36/1000 | J36: =I36/$I$46*100 | K36: TGO-CFP-EF-(ก.ค. 65)-รถบรรทุกขยะ 6 ล้อ วิ่งแบบปกติ 0% Loading
A37: Scope 3.7 | B37: Scope 3.3 in ISO 14064-1 | C37: Employee commuting
C38: น้ำมัน Gasoline จากการเดินทางของพนักงาน | D38: L | E38: ='Scope 3.7'!Q4 | G38: แบบสำรวจการเดินทางของพนักงาน | H38: ='EF TGO AR5'!H30 | I38: =E38*H38/1000 | J38: =I38/$I$46*100 | K38: TGO-CFO-EF-(เม.ย. 65)-Motor Gasoline - Mobile on road
C39: น้ำมัน Diesel จากการเดินทางของพนักงาน | D39: L | E39: ='Scope 3.7'!P4 | G39: แบบสำรวจการเดินทางของพนักงาน | H39: ='EF TGO AR5'!H32 | I39: =E39*H39/1000 | J39: =I39/$I$46*100 | K39: TGO-CFO-EF-(เม.ย. 65)-Gas/ Diesel Oil-Mobile on road
A40: Scope 3.9 | B40: Scope 3.2 in ISO 14064-1 | C40: Downstream transportation and distribution
C41: รถตู้บรรทุกพ่วง 18 ล้อ วิ่งปกติ 100% loading | D41: ='Scope 3.9'!O3 | E41: ='Scope 3.9'!O4 | G41: Invoice , google map และ เว็ปไซต์ searate | H41: 0.0404 | I41: =E41*H41/1000 | J41: =I41/$I$46*100 | K41: TGO-CFP-EF-(ก.ค. 65)-รถตู้บรรทุกพ่วง 18 ล้อ วิ่งปกติ 100% loading
C42: รถตู้บรรทุกพ่วง 18 ล้อ วิ่งปกติ 0% loading | D42: ='Scope 3.9'!P3 | E42: ='Scope 3.9'!P4 | G42: Invoice , google map และ เว็ปไซต์ searate | H42: 0.787 | I42: =E42*H42/1000 | J42: =I42/$I$46*100 | K42: TGO-CFP-EF-(ก.ค. 65)-รถตู้บรรทุกพ่วง 18 ล้อ วิ่งปกติ 0% loading
C43: เรือบรรทุก container | D43: ='Scope 3.9'!Q3 | E43: ='Scope 3.9'!Q4 | G43: Invoice , google map และ เว็ปไซต์ searate | H43: 0.0107 | I43: =E43*H43/1000 | J43: =I43/$I$46*100 | K43: TGO-CFP-EF-(ก.ค. 65)-เรือบรรทุก container
A44: Scope 3.12 | B44: Scope 5 in ISO 14064-1 | C44: End-of-life treatment of sold products
C45: การฝังกลบถุงขยะ | D45: kg | E45: ='Scope 3.12'!N3 | G45: Invoice | H45: 0.7933 | I45: =E45*H45/1000 | J45: =I45/$I$46*100 | K45: TGO-CFP-EF-(ก.ค. 65)-การฝังกลบขยะมูลฝอยชุมชนแบบถูกหลักสุขาภิบาล (แทน)
C46: รวม | I46: =SUM(I3:I45) | J46: =SUM(J3:J45)

Sheet Fr-04.1
B1: บัญชีรายการก๊าซเรือนกระจก | AO1: TCFO_R_01 Version 04 : 21/2/2020
B3: ชื่อฟอร์ม | C3: บัญชีรายการก๊าซเรือนกระจก | H3: องค์กร | I3: ='Fr-01'!$B$6 | AB3: ปีที่เก็บข้อมูล | AE3: ='Fr-01'!H36 | AO3: หน้าที่ | AR3: 4
B4: รหัสฟอร์ม | C4: Fr-04.1 | H4: ผู้จัดทำ | I4: ='Fr-01'!$G$4 | AO4: วันที่ | AR4: 45494
A6: ขอบเขต | B6: รายการ | C6: ค่า LCI | E6: GHG ที่ต้องรายงานตามข้อกำหนด | O6: GHG ที่อยู่นอกข้อกำหนด | Q6: Total (kgCO2e/หน่วย) | R6: ที่มา | Y6: Subsitute | Z6: แหล่งอ้างอิง | AA6: ผลคูณ (Ton GHG) | AG6: ผลคูณ (TonCO2e) | AO6: Total GHG | AP6: สัดส่วน (%) | AQ6: สัดส่วน (%) (SCOPE 1+2) | AR6: สัดส่วน (%) (SCOPE 1+2+3) | AS6: คำอธิบายเพิ่มเติม | AU6: GWP100
R7: 1st | T7: 2nd | X7: Other | AU7: ที่มา | AV7: IPCC, AR5
E8: ค่า EF (kg GHG/หน่วย) | M8: GWP100 | O8: ค่า EF (kg GHG/หน่วย) | P8: GWP100 | R8: Self collct | S8: Supplier | T8: TH LCI DB | U8: TGO EF | V8: Thai Res. | W8: Int. DB | AO8: (TonCO2e) | AU8: CO2 | AV8: 1
C9: หน่วย | D9: ปริมาณ | E9: CO2 | F9: Fossil CH4 | G9: CH4 | H9: N2O | I9: SF6 | J9: NF3 | K9: HFCs | L9: PFCs | M9: HFCs | N9: PFCs | AA9: CO2 | AB9: Fossil CH4 | AC9: CH4 | AD9: N2O | AE9: SF6 | AF9: NF3 | AG9: Fossil CH4 | AH9: CH4 | AI9: N2O | AJ9: SF6 | AK9: NF3 | AL9: HFCs | AM9: PFCs | AN9: Other | AU9: Fossil CH4 | AV9: 30
A10: ขอบเขต 1 | B10: Stationary combustion | Q10: =(E10*$AV$8)+(F10*$AV$9)+(G10*$AV$10)+(H10*$AV$11)+(I10*$AV$12)+(J10*$AV$13)+(K10*M10)+(L10*N10) | AA10: =D10*E10/1000 | AB10: =D10*F10/1000 | AC10: =D10*G10/1000 | AD10: =D10*H10/1000 | AE10: =D10*I10/1000 | AF10: =D10*J10/1000 | AG10: =D10*F10*$AV$9/1000 | AH10: =D10*G10*$AV$10/1000 | AI10: =D10*H10*$AV$11/1000 | AJ10: =D10*I10*$AV$12/1000 | AK10: =D10*J10*$AV$13/1000 | AL10: =D10*K10*M10/1000 | AM10: =D10*L10*N10/1000 | AO10: =D10*Q10/1000 | AP10: =AO10/$AO$36 | AQ10: =AO10/$AO$58 | AR10: =AO10/$AO$59 | AU10: CH4 | AV10: 28
B11: ='1.1 Stationary'!A9 | C11: ='1.1 Stationary'!C9 | D11: ='1.1 Stationary'!G4 | E11: ='EF TGO AR5'!D11 | F11: ='EF TGO AR5'!E11 | G11: ='EF TGO AR5'!F11 | H11: ='EF TGO AR5'!G11 | Q11: =(E11*$AV$8)+(F11*$AV$9)+(G11*$AV$10)+(H11*$AV$11)+(I11*$AV$12)+(J11*$AV$13)+(K11*M11)+(L11*N11) | U11: / | Z11: TGO CFO EF (เมษายน 2565):Gas/Diesel oil | AA11: =D11*E11/1000 | AB11: =D11*F11/1000 | AC11: =D11*G11/1000 | AD11: =D11*H11/1000 | AE11: =D11*I11/1000 | AF11: =D11*J11/1000 | AG11: =D11*F11*AJ13/1000 | AH11: =D11*G11*$AV$10/1000 | AI11: =D11*H11*$AV$11/1000 | AJ11: =D11*I11*$AV$12/1000 | AK11: =D11*J11*$AV$13/1000 | AL11: =D11*K11*M11/1000 | AM11: =D11*L11*N11/1000 | AO11: =D11*Q11/1000 | AP11: =AO11/$AO$36 | AQ11: =AO11/$AO$58 | AR11: =AO11/$AO$59 | AU11: N2O | AV11: 265
B12: ='1.1 Stationary'!A10 | C12: ='1.1 Stationary'!C10 | D12: ='1.1 Stationary'!J5 | E12: ='EF TGO AR5'!D17 | F12: ='EF TGO AR5'!E17 | G12: ='EF TGO AR5'!F17 | H12: ='EF TGO AR5'!G17 | Q12: =(E12*$AV$8)+(F12*$AV$9)+(G12*$AV$10)+(H12*$AV$11)+(I12*$AV$12)+(J12*$AV$13)+(K12*M12)+(L12*N12) | U12: / | Z12: TGO CFO EF (เมษายน 2565): Motor Gasoline | AA12: =D12*E12/1000 | AB12: =D12*F12/1000 | AC12: =D12*G12/1000 | AD12: =D12*H12/1000 | AE12: =D12*I12/1000 | AF12: =D12*J12/1000 | AG12: =D12*F12*$AV$9/1000 | AH12: =D12*G12*$AV$10/1000 | AI12: =D12*H12*$AV$11/1000 | AJ12: =D12*I12*$AV$12/1000 | AK12: =D12*J12*$AV$13/1000 | AL12: =D12*K12*M12/1000 | AM12: =D12*L12*N12/1000 | AO12: =D12*Q12/1000 | AP12: =AO12/$AO$36 | AQ12: =AO12/$AO$58 | AR12: =AO12/$AO$59 | AU12: SF6 | AV12: 23500 | AX12: =0.0025*265
B13: ='1.1 Stationary'!A11 | C13: ='1.1 Stationary'!C11 | D13: ='1.1 Stationary'!D11 | E13: ='EF (1)'!B9 | Q13: =(E13*$AV$8)+(F13*$AV$9)+(G13*$AV$10)+(H13*$AV$11)+(I13*$AV$12)+(J13*$AV$13)+(K13*M13)+(L13*N13) | X13: / | Z13: EF (1) สมการเคมี | AA13: =D13*E13/1000 | AB13: =D13*F13/1000 | AC13: =D13*G13/1000 | AD13: =D13*H13/1000 | AE13: =D13*I13/1000 | AF13: =D13*J13/1000 | AG13: =D13*F13*$AV$9/1000 | AH13: =D13*G13*$AV$10/1000 | AI13: =D13*H13*$AV$11/1000 | AJ13: =D13*I13*$AV$12/1000 | AK13: =D13*J13*$AV$13/1000 | AL13: =D13*K13*M13/1000 | AM13: =D13*L13*N13/1000 | AO13: =D13*Q13/1000 | AP13: =AO13/$AO$36 | AQ13: =AO13/$AO$58 | AR13: =AO13/$AO$59 | AU13: NF3 | AV13: 16100
B14: Biodiesel (Stationary combustion) | C14: kg | D14: ='1.1 Stationary'!I4 | G14: ='EF (1)'!F28*'EF (1)'!D28 | H14: ='EF (1)'!F28*'EF (1)'!E28 | Q14: =(E14*$AV$8)+(F14*$AV$9)+(G14*$AV$10)+(H14*$AV$11)+(I14*$AV$12)+(J14*$AV$13)+(K14*M14)+(L14*N14) | W14: / | Z14: IPCC, 2006 | AA14: =D14*E14/1000 | AB14: =D14*F14/1000 | AC14: =D14*G14/1000 | AD14: =D14*H14/1000 | AE14: =D14*I14/1000 | AF14: =D14*J14/1000 | AG14: =D14*F14*$AV$9/1000 | AH14: =D14*G14*$AV$10/1000 | AI14: =D14*H14*$AV$11/1000 | AJ14: =D14*I14*$AV$12/1000 | AK14: =D14*J14*$AV$13/1000 | AL14: =D14*K14*M14/1000 | AM14: =D14*L14*N14/1000 | AO14: =D14*Q14/1000 | AP14: =AO14/$AO$36 | AQ14: =AO14/$AO$58 | AR14: =AO14/$AO$59
B15: Biogasoline (Ethanol) (Stationary combustion) | C15: kg | D15: ='1.1 Stationary'!L5 | G15: ='EF (1)'!F29*'EF (1)'!D29 | H15: ='EF (1)'!F29*'EF (1)'!E29 | Q15: =(E15*$AV$8)+(F15*$AV$9)+(G15*$AV$10)+(H15*$AV$11)+(I15*$AV$12)+(J15*$AV$13)+(K15*M15)+(L15*N15) | W15: / | Z15: IPCC, 2006 | AA15: =D15*E15/1000 | AB15: =D15*F15/1000 | AC15: =D15*G15/1000 | AD15: =D15*H15/1000 | AE15: =D15*I15/1000 | AF15: =D15*J15/1000 | AG15: =D15*F15*$AV$9/1000 | AH15: =D15*G15*$AV$10/1000 | AI15: =D15*H15*$AV$11/1000 | AJ15: =D15*I15*$AV$12/1000 | AK15: =D15*J15*$AV$13/1000 | AL15: =D15*K15*M15/1000 | AM15: =D15*L15*N15/1000 | AO15: =D15*Q15/1000 | AP15: =AO15/$AO$36 | AQ15: =AO15/$AO$58 | AR15: =AO15/$AO$59
B16: Mobile combustion | Q16: =(E16*$AV$8)+(F16*$AV$9)+(G16*$AV$10)+(H16*$AV$11)+(I16*$AV$12)+(J16*$AV$13)+(K16*M16)+(L16*N16) | AA16: =D16*E16/1000 | AB16: =D16*F16/1000 | AC16: =D16*G16/1000 | AD16: =D16*H16/1000 | AE16: =D16*I16/1000 | AF16: =D16*J16/1000 | AG16: =D16*F16*$AV$9/1000 | AH16: =D16*G16*$AV$10/1000 | AI16: =D16*H16*$AV$11/1000 | AJ16: =D16*I16*$AV$12/1000 | AK16: =D16*J16*$AV$13/1000 | AL16: =D16*K16*M16/1000 | AM16: =D16*L16*N16/1000 | AO16: =D16*Q16/1000 | AP16: =AO16/$AO$36 | AQ16: =AO16/$AO$58 | AR16: =AO16/$AO$59
B17: น้ำมัน Diesel B7 รถยนต์องค์กร | C17: L | D17: ='1.2 Mobile'!G5 | E17: ='EF TGO AR5'!D32 | F17: ='EF TGO AR5'!E32 | G17: ='EF TGO AR5'!F32 | H17: ='EF TGO AR5'!G32 | Q17: =(E17*$AV$8)+(F17*$AV$9)+(G17*$AV$10)+(H17*$AV$11)+(I17*$AV$12)+(J17*$AV$13)+(K17*M17)+(L17*N17) | U17: / | Z17: TGO CFO EF (เมษายน 2565):Gas/Diesel (Mobile Combustion) | AA17: =D17*E17/1000 | AB17: =D17*F17/1000 | AC17: =D17*G17/1000 | AD17: =D17*H17/1000 | AE17: =D17*I17/1000 | AF17: =D17*J17/1000 | AG17: =D17*F17*$AV$9/1000 | AH17: =D17*G17*$AV$10/1000 | AI17: =D17*H17*$AV$11/1000 | AJ17: =D17*I17*$AV$12/1000 | AK17: =D17*J17*$AV$13/1000 | AL17: =D17*K17*M17/1000 | AM17: =D17*L17*N17/1000 | AO17: =D17*Q17/1000 | AP17: =AO17/$AO$36 | AQ17: =AO17/$AO$58 | AR17: =AO17/$AO$59
B18: น้ำมัน Diesel B10 รถยนต์องค์กร | C18: L | D18: ='1.2 Mobile'!G6 | E18: ='EF TGO AR5'!D32 | F18: ='EF TGO AR5'!E32 | G18: ='EF TGO AR5'!F32 | H18: ='EF TGO AR5'!G32 | Q18: =(E18*$AV$8)+(F18*$AV$9)+(G18*$AV$10)+(H18*$AV$11)+(I18*$AV$12)+(J18*$AV$13)+(K18*M18)+(L18*N18) | U18: / | Z18: TGO CFO EF (เมษายน 2565):Gas/Diesel (Mobile Combustion) | AA18: =D18*E18/1000 | AB18: =D18*F18/1000 | AC18: =D18*G18/1000 | AD18: =D18*H18/1000 | AE18: =D18*I18/1000 | AF18: =D18*J18/1000 | AG18: =D18*F18*$AV$9/1000 | AH18: =D18*G18*$AV$10/1000 | AI18: =D18*H18*$AV$11/1000 | AJ18: =D18*I18*$AV$12/1000 | AK18: =D18*J18*$AV$13/1000 | AL18: =D18*K18*M18/1000 | AM18: =D18*L18*N18/1000 | AO18: =D18*Q18/1000 | AP18: =AO18/$AO$36 | AQ18: =AO18/$AO$58 | AR18: =AO18/$AO$59
B19: น้ำมัน Gasohol 91/95 รถยนต์องค์กร | C19: L | D19: ='1.2 Mobile'!J7 | E19: ='EF TGO AR5'!D30 | F19: ='EF TGO AR5'!E30 | G19: ='EF TGO AR5'!F30 | H19: ='EF TGO AR5'!G30 | Q19: =(E19*$AV$8)+(F19*$AV$9)+(G19*$AV$10)+(H19*$AV$11)+(I19*$AV$12)+(J19*$AV$13)+(K19*M19)+(L19*N19) | U19: / | Z19: TGO CFO EF (เมษายน 2565): Motor gasoline-oxidation catalyst (Mobile Combustion on road) | AA19: =D19*E19/1000 | AB19: =D19*F19/1000 | AC19: =D19*G19/1000 | AD19: =D19*H19/1000 | AE19: =D19*I19/1000 | AF19: =D19*J19/1000 | AG19: =D19*F19*$AV$9/1000 | AH19: =D19*G19*$AV$10/1000 | AI19: =D19*H19*$AV$11/1000 | AJ19: =D19*I19*$AV$12/1000 | AK19: =D19*J19*$AV$13/1000 | AL19: =D19*K19*M19/1000 | AM19: =D19*L19*N19/1000 | AO19: =D19*Q19/1000 | AP19: =AO19/$AO$36 | AQ19: =AO19/$AO$58 | AR19: =AO19/$AO$59
B20: น้ำมัน Gasohol E20 รถยนต์องค์กร | C20: L | D20: ='1.2 Mobile'!J8 | E20: ='EF TGO AR5'!D30 | F20: ='EF TGO AR5'!E30 | G20: ='EF TGO AR5'!F30 | H20: ='EF TGO AR5'!G30 | Q20: =(E20*$AV$8)+(F20*$AV$9)+(G20*$AV$10)+(H20*$AV$11)+(I20*$AV$12)+(J20*$AV$13)+(K20*M20)+(L20*N20) | U20: / | Z20: TGO CFO EF (เมษายน 2565): Motor gasoline-oxidation catalyst (Mobile Combustion on road) | AA20: =D20*E20/1000 | AB20: =D20*F20/1000 | AC20: =D20*G20/1000 | AD20: =D20*H20/1000 | AE20: =D20*I20/1000 | AF20: =D20*J20/1000 | AG20: =D20*F20*$AV$9/1000 | AH20: =D20*G20*$AV$10/1000 | AI20: =D20*H20*$AV$11/1000 | AJ20: =D20*I20*$AV$12/1000 | AK20: =D20*J20*$AV$13/1000 | AL20: =D20*K20*M20/1000 | AM20: =D20*L20*N20/1000 | AO20: =D20*Q20/1000 | AP20: =AO20/$AO$36 | AQ20: =AO20/$AO$58 | AR20: =AO20/$AO$59
B21: น้ำมัน Diesel B7 FL/รถใช้ขนส่งภายในองค์กร (off-road) | C21: L | D21: ='1.2 Mobile'!G9 | E21: ='EF TGO AR5'!D40 | F21: ='EF TGO AR5'!E40 | G21: ='EF TGO AR5'!F40 | H21: ='EF TGO AR5'!G40 | Q21: =(E21*$AV$8)+(F21*$AV$9)+(G21*$AV$10)+(H21*$AV$11)+(I21*$AV$12)+(J21*$AV$13)+(K21*M21)+(L21*N21) | U21: / | Z21: TGO CFO EF (เมษายน 2565): Diesel Industry (Mobile Combustion off road) | AA21: =D21*E21/1000 | AB21: =D21*F21/1000 | AC21: =D21*G21/1000 | AD21: =D21*H21/1000 | AE21: =D21*I21/1000 | AF21: =D21*J21/1000 | AG21: =D21*F21*$AV$9/1000 | AH21: =D21*G21*$AV$10/1000 | AI21: =D21*H21*$AV$11/1000 | AJ21: =D21*I21*$AV$12/1000 | AK21: =D21*J21*$AV$13/1000 | AL21: =D21*K21*M21/1000 | AM21: =D21*L21*N21/1000 | AO21: =D21*Q21/1000 | AP21: =AO21/$AO$36 | AQ21: =AO21/$AO$58 | AR21: =AO21/$AO$59
B22: Biodiesel (Mobile combustion-on road) | C22: kg | D22: ='1.2 Mobile'!I5+'1.2 Mobile'!I6 | G22: ='EF (1)'!F30*'EF (1)'!D30 | H22: ='EF (1)'!F30*'EF (1)'!E30 | Q22: =(E22*$AV$8)+(F22*$AV$9)+(G22*$AV$10)+(H22*$AV$11)+(I22*$AV$12)+(J22*$AV$13)+(K22*M22)+(L22*N22) | W22: / | Z22: IPCC, 2006 | AA22: =D22*E22/1000 | AB22: =D22*F22/1000 | AC22: =D22*G22/1000 | AD22: =D22*H22/1000 | AE22: =D22*I22/1000 | AF22: =D22*J22/1000 | AG22: =D22*F22*$AV$9/1000 | AH22: =D22*G22*$AV$10/1000 | AI22: =D22*H22*$AV$11/1000 | AJ22: =D22*I22*$AV$12/1000 | AK22: =D22*J22*$AV$13/1000 | AL22: =D22*K22*M22/1000 | AM22: =D22*L22*N22/1000 | AO22: =D22*Q22/1000 | AP22: =AO22/$AO$36 | AQ22: =AO22/$AO$58 | AR22: =AO22/$AO$59
B23: Biodiesel (Mobile combustion-off road) | C23: kg | D23: ='1.2 Mobile'!I9 | G23: ='EF (1)'!F32*'EF (1)'!D32 | H23: ='EF (1)'!F32*'EF (1)'!E32 | Q23: =(E23*$AV$8)+(F23*$AV$9)+(G23*$AV$10)+(H23*$AV$11)+(I23*$AV$12)+(J23*$AV$13)+(K23*M23)+(L23*N23) | W23: / | Z23: IPCC, 2006 | AA23: =D23*E23/1000 | AB23: =D23*F23/1000 | AC23: =D23*G23/1000 | AD23: =D23*H23/1000 | AE23: =D23*I23/1000 | AF23: =D23*J23/1000 | AG23: =D23*F23*$AV$9/1000 | AH23: =D23*G23*$AV$10/1000 | AI23: =D23*H23*$AV$11/1000 | AJ23: =D23*I23*$AV$12/1000 | AK23: =D23*J23*$AV$13/1000 | AL23: =D23*K23*M23/1000 | AM23: =D23*L23*N23/1000 | AO23: =D23*Q23/1000 | AP23: =AO23/$AO$36 | AQ23: =AO23/$AO$58 | AR23: =AO23/$AO$59
B24: Biogasoline (Ethanol) (Mobile combustion) | C24: kg | D24: ='1.2 Mobile'!L7+'1.2 Mobile'!L8 | G24: ='EF (1)'!F31*'EF (1)'!D31 | H24: ='EF (1)'!F31*'EF (1)'!E31 | Q24: =(E24*$AV$8)+(F24*$AV$9)+(G24*$AV$10)+(H24*$AV$11)+(I24*$AV$12)+(J24*$AV$13)+(K24*M24)+(L24*N24) | W24: / | Z24: IPCC, 2006 | AA24: =D24*E24/1000 | AB24: =D24*F24/1000 | AC24: =D24*G24/1000 | AD24: =D24*H24/1000 | AE24: =D24*I24/1000 | AF24: =D24*J24/1000 | AG24: =D24*F24*$AV$9/1000 | AH24: =D24*G24*$AV$10/1000 | AI24: =D24*H24*$AV$11/1000 | AJ24: =D24*I24*$AV$12/1000 | AK24: =D24*J24*$AV$13/1000 | AL24: =D24*K24*M24/1000 | AM24: =D24*L24*N24/1000 | AO24: =D24*Q24/1000 | AP24: =AO24/$AO$36 | AQ24: =AO24/$AO$58 | AR24: =AO24/$AO$59
B25: Fugitive | Q25: =(E25*$AV$8)+(F25*$AV$9)+(G25*$AV$10)+(H25*$AV$11)+(I25*$AV$12)+(J25*$AV$13)+(K25*M25)+(L25*N25) | AA25: =D25*E25/1000 | AB25: =D25*F25/1000 | AC25: =D25*G25/1000 | AD25: =D25*H25/1000 | AE25: =D25*I25/1000 | AF25: =D25*J25/1000 | AG25: =D25*F25*$AV$9/1000 | AH25: =D25*G25*$AV$10/1000 | AI25: =D25*H25*$AV$11/1000 | AJ25: =D25*I25*$AV$12/1000 | AK25: =D25*J25*$AV$13/1000 | AL25: =D25*K25*M25/1000 | AM25: =D25*L25*N25/1000 | AO25: =D25*Q25/1000 | AP25: =AO25/$AO$36 | AQ25: =AO25/$AO$58 | AR25: =AO25/$AO$59
B26: ='1.4.1 สารทำความเย็น'!A6 | C26: ='1.4.1 สารทำความเย็น'!D6 | D26: ='1.4.1 สารทำความเย็น'!E6 | K26: 1 | M26: ='EF TGO AR5'!H56 | Q26: =(E26*$AV$8)+(F26*$AV$9)+(G26*$AV$10)+(H26*$AV$11)+(I26*$AV$12)+(J26*$AV$13)+(K26*M26)+(L26*N26) | W26: / | Z26: IPCC : GWP (AR5) | AA26: =D26*E26/1000 | AB26: =D26*F26/1000 | AC26: =D26*G26/1000 | AD26: =D26*H26/1000 | AE26: =D26*I26/1000 | AF26: =D26*J26/1000 | AG26: =D26*F26*$AV$9/1000 | AH26: =D26*G26*$AV$10/1000 | AI26: =D26*H26*$AV$11/1000 | AJ26: =D26*I26*$AV$12/1000 | AK26: =D26*J26*$AV$13/1000 | AL26: =D26*K26*M26/1000 | AM26: =D26*L26*N26/1000 | AO26: =D26*Q26/1000 | AP26: =AO26/$AO$36 | AQ26: =AO26/$AO$58 | AR26: =AO26/$AO$59
B27: ='1.4.1 สารทำความเย็น'!A7 | C27: ='1.4.1 สารทำความเย็น'!D7 | D27: ='1.4.1 สารทำความเย็น'!E7 | K27: 1 | M27: ='EF (1)'!E16 | Q27: =(E27*$AV$8)+(F27*$AV$9)+(G27*$AV$10)+(H27*$AV$11)+(I27*$AV$12)+(J27*$AV$13)+(K27*M27)+(L27*N27) | W27: / | Z27: IPCC : GWP (AR5) | AA27: =D27*E27/1000 | AB27: =D27*F27/1000 | AC27: =D27*G27/1000 | AD27: =D27*H27/1000 | AE27: =D27*I27/1000 | AF27: =D27*J27/1000 | AG27: =D27*F27*$AV$9/1000 | AH27: =D27*G27*$AV$10/1000 | AI27: =D27*H27*$AV$11/1000 | AJ27: =D27*I27*$AV$12/1000 | AK27: =D27*J27*$AV$13/1000 | AL27: =D27*K27*M27/1000 | AM27: =D27*L27*N27/1000 | AO27: =D27*Q27/1000 | AP27: =AO27/$AO$36 | AQ27: =AO27/$AO$58 | AR27: =AO27/$AO$59
B28: ='1.4.1 สารทำความเย็น'!A8 | C28: ='1.4.1 สารทำความเย็น'!D8 | D28: ='1.4.1 สารทำความเย็น'!E8 | K28: 1 | M28: ='EF TGO AR5'!H59 | Q28: =(E28*$AV$8)+(F28*$AV$9)+(G28*$AV$10)+(H28*$AV$11)+(I28*$AV$12)+(J28*$AV$13)+(K28*M28)+(L28*N28) | W28: / | Z28: IPCC : GWP (AR5) | AA28: =D28*E28/1000 | AB28: =D28*F28/1000 | AC28: =D28*G28/1000 | AD28: =D28*H28/1000 | AE28: =D28*I28/1000 | AF28: =D28*J28/1000 | AG28: =D28*F28*$AV$9/1000 | AH28: =D28*G28*$AV$10/1000 | AI28: =D28*H28*$AV$11/1000 | AJ28: =D28*I28*$AV$12/1000 | AK28: =D28*J28*$AV$13/1000 | AL28: =D28*K28*M28/1000 | AM28: =D28*L28*N28/1000 | AO28: =D28*Q28/1000 | AP28: =AO28/$AO$36 | AQ28: =AO28/$AO$58 | AR28: =AO28/$AO$59
B29: ='1.4.1 สารทำความเย็น'!A9 | C29: ='1.4.1 สารทำความเย็น'!D9 | D29: ='1.4.1 สารทำความเย็น'!E9 | K29: 1 | M29: ='EF (1)'!E19 | Q29: =(E29*$AV$8)+(F29*$AV$9)+(G29*$AV$10)+(H29*$AV$11)+(I29*$AV$12)+(J29*$AV$13)+(K29*M29)+(L29*N29) | W29: / | Z29: IPCC : GWP (AR5) | AA29: =D29*E29/1000 | AB29: =D29*F29/1000 | AC29: =D29*G29/1000 | AD29: =D29*H29/1000 | AE29: =D29*I29/1000 | AF29: =D29*J29/1000 | AG29: =D29*F29*$AV$9/1000 | AH29: =D29*G29*$AV$10/1000 | AI29: =D29*H29*$AV$11/1000 | AJ29: =D29*I29*$AV$12/1000 | AK29: =D29*J29*$AV$13/1000 | AL29: =D29*K29*M29/1000 | AM29: =D29*L29*N29/1000 | AO29: =D29*Q29/1000 | AP29: =AO29/$AO$36 | AQ29: =AO29/$AO$58 | AR29: =AO29/$AO$59
B30: ='1.4.2 สารดับเพลิง'!A4 | C30: ='1.4.2 สารดับเพลิง'!D4 | D30: ='1.4.2 สารดับเพลิง'!E4 | E30: 1 | Q30: =(E30*$AV$8)+(F30*$AV$9)+(G30*$AV$10)+(H30*$AV$11)+(I30*$AV$12)+(J30*$AV$13)+(K30*M30)+(L30*N30) | W30: / | Z30: IPCC : GWP (AR5) | AA30: =D30*E30/1000 | AB30: =D30*F30/1000 | AC30: =D30*G30/1000 | AD30: =D30*H30/1000 | AE30: =D30*I30/1000 | AF30: =D30*J30/1000 | AG30: =D30*F30*$AV$9/1000 | AH30: =D30*G30*$AV$10/1000 | AI30: =D30*H30*$AV$11/1000 | AJ30: =D30*I30*$AV$12/1000 | AK30: =D30*J30*$AV$13/1000 | AL30: =D30*K30*M30/1000 | AM30: =D30*L30*N30/1000 | AO30: =D30*Q30/1000 | AP30: =AO30/$AO$36 | AQ30: =AO30/$AO$58 | AR30: =AO30/$AO$59
B31: Septic tank | C31: kgCH4 | D31: ='1.4.3 Septic'!I16+'1.4.3 Septic'!I32+'1.4.3 Septic'!I48+'1.4.3 Septic'!I64 | G31: 1 | Q31: =(E31*$AV$8)+(F31*$AV$9)+(G31*$AV$10)+(H31*$AV$11)+(I31*$AV$12)+(J31*$AV$13)+(K31*M31)+(L31*N31) | W31: / | Z31: IPCC : GWP (AR5) | AA31: =D31*E31/1000 | AB31: =D31*F31/1000 | AC31: =D31*G31/1000 | AD31: =D31*H31/1000 | AE31: =D31*I31/1000 | AF31: =D31*J31/1000 | AG31: =D31*F31*$AV$9/1000 | AH31: =D31*G31*$AV$10/1000 | AI31: =D31*H31*$AV$11/1000 | AJ31: =D31*I31*$AV$12/1000 | AK31: =D31*J31*$AV$13/1000 | AL31: =D31*K31*M31/1000 | AM31: =D31*L31*N31/1000 | AO31: =D31*Q31/1000 | AP31: =AO31/$AO$36 | AQ31: =AO31/$AO$58 | AR31: =AO31/$AO$59
B32: ='1.4.4 ปุ๋ย'!A3 | C32: ='1.4.4 ปุ๋ย'!C3 | D32: ='1.4.4 ปุ๋ย'!D3 | H32: ='1.4.4 ปุ๋ย'!Q3 | Q32: =(E32*$AV$8)+(F32*$AV$9)+(G32*$AV$10)+(H32*$AV$11)+(I32*$AV$12)+(J32*$AV$13)+(K32*M32)+(L32*N32) | W32: / | Z32: IPCC : GWP (AR5) | AA32: =D32*E32/1000 | AB32: =D32*F32/1000 | AC32: =D32*G32/1000 | AD32: =D32*H32/1000 | AE32: =D32*I32/1000 | AF32: =D32*J32/1000 | AG32: =D32*F32*$AV$9/1000 | AH32: =D32*G32*$AV$10/1000 | AI32: =D32*H32*$AV$11/1000 | AJ32: =D32*I32*$AV$12/1000 | AK32: =D32*J32*$AV$13/1000 | AL32: =D32*K32*M32/1000 | AM32: =D32*L32*N32/1000 | AO32: =D32*Q32/1000 | AP32: =AO32/$AO$36 | AQ32: =AO32/$AO$58 | AR32: =AO32/$AO$59
Q33: =(E33*$AV$8)+(F33*$AV$9)+(G33*$AV$10)+(H33*$AV$11)+(I33*$AV$12)+(J33*$AV$13)+(K33*M33)+(L33*N33) | AA33: =D33*E33/1000 | AB33: =D33*F33/1000 | AC33: =D33*G33/1000 | AD33: =D33*H33/1000 | AE33: =D33*I33/1000 | AF33: =D33*J33/1000 | AG33: =D33*F33*$AV$9/1000 | AH33: =D33*G33*$AV$10/1000 | AI33: =D33*H33*$AV$11/1000 | AJ33: =D33*I33*$AV$12/1000 | AK33: =D33*J33*$AV$13/1000 | AL33: =D33*K33*M33/1000 | AM33: =D33*L33*N33/1000 | AO33: =D33*Q33/1000 | AP33: =AO33/$AO$36 | AQ33: =AO33/$AO$58 | AR33: =AO33/$AO$59
Q34: =(E34*$AV$8)+(F34*$AV$9)+(G34*$AV$10)+(H34*$AV$11)+(I34*$AV$12)+(J34*$AV$13)+(K34*M34)+(L34*N34) | AA34: =D34*E34/1000 | AB34: =D34*F34/1000 | AC34: =D34*G34/1000 | AD34: =D34*H34/1000 | AE34: =D34*I34/1000 | AF34: =D34*J34/1000 | AG34: =D34*F34*$AV$9/1000 | AH34: =D34*G34*$AV$10/1000 | AI34: =D34*H34*$AV$11/1000 | AJ34: =D34*I34*$AV$12/1000 | AK34: =D34*J34*$AV$13/1000 | AL34: =D34*K34*M34/1000 | AM34: =D34*L34*N34/1000 | AO34: =D34*Q34/1000 | AP34: =AO34/$AO$36 | AQ34: =AO34/$AO$58 | AR34: =AO34/$AO$59
Q35: =(E35*$AV$8)+(F35*$AV$9)+(G35*$AV$10)+(H35*$AV$11)+(I35*$AV$12)+(J35*$AV$13)+(K35*M35)+(L35*N35) | AA35: =D35*E35/1000 | AB35: =D35*F35/1000 | AC35: =D35*G35/1000 | AD35: =D35*H35/1000 | AE35: =D35*I35/1000 | AF35: =D35*J35/1000 | AG35: =D35*F35*$AV$9/1000 | AH35: =D35*G35*$AV$10/1000 | AI35: =D35*H35*$AV$11/1000 | AJ35: =D35*I35*$AV$12/1000 | AK35: =D35*J35*$AV$13/1000 | AL35: =D35*K35*M35/1000 | AM35: =D35*L35*N35/1000 | AO35: =D35*Q35/1000 | AP35: =AO35/$AO$36 | AQ35: =AO35/$AO$58 | AR35: =AO35/$AO$59
AA36: =SUM(AA10:AA35) | AB36: =SUM(AB10:AB35) | AC36: =SUM(AC10:AC35) | AD36: =SUM(AD10:AD35) | AE36: =SUM(AE10:AE35) | AF36: =SUM(AF10:AF35) | AG36: =SUM(AG10:AG35) | AH36: =SUM(AH10:AH35) | ... AP36: =SUM(AP10:AP35)
A37: รายงานแยก | B37: ='1.4.1 สารทำความเย็น'!A4 | C37: ='1.4.1 สารทำความเย็น'!D4 | D37: ='1.4.1 สารทำความเย็น'!E4 | O37: 1 | P37: ='EF TGO AR5'!H55 | Q37: =(E37*$AV$8)+(O37*P37) | W37: / | Z37: IPCC : GWP (AR5) | AA37: =D37*E37*$AV$8/1000 | AN37: =D37*O37*P37/1000 | AO37: =D37*Q37/1000 | AP37: =AO37/$AO$44
B38: ='1.4.2 สารดับเพลิง'!A5 | C38: ='1.4.2 สารดับเพลิง'!D5 | D38: ='1.4.2 สารดับเพลิง'!E5 | O38: 1 | P38: ='EF (1)'!E13 | Q38: =(E38*$AV$8)+(O38*P38) | W38: / | Z38: IPCC : GWP (AR5) | AA38: =D38*E38*$AV$8/1000 | AN38: =D38*O38*P38/1000 | AO38: =D38*Q38/1000 | AP38: =AO38/$AO$44
B39: CO2 -Biodiesel (Stationary combustion) | C39: kg | D39: =D14 | E39: ='EF (1)'!F28*'EF (1)'!C28 | Q39: =(E39*$AV$8)+(O39*P39) | W39: / | Z39: IPCC, 2006 | AA39: =D39*E39*$AV$8/1000 | AN39: =D39*O39*P39/1000 | AO39: =D39*Q39/1000 | AP39: =AO39/$AO$44
B40: CO2-Biogasoline (Ethanol) (Stationary combustion) | C40: kg | D40: =D15 | E40: ='EF (1)'!F29*'EF (1)'!C29 | Q40: =(E40*$AV$8)+(O40*P40) | W40: / | Z40: IPCC, 2006 | AA40: =D40*E40*$AV$8/1000 | AN40: =D40*O40*P40/1000 | AO40: =D40*Q40/1000 | AP40: =AO40/$AO$44
B41: CO2-Biodiesel (Mobile combustion-on road) | C41: kg | D41: =D22 | E41: ='EF (1)'!$C$34 | Q41: =(E41*$AV$8)+(O41*P41) | W41: / | Z41: IPCC, 2006 | AA41: =D41*E41*$AV$8/1000 | AN41: =D41*O41*P41/1000 | AO41: =D41*Q41/1000 | AP41: =AO41/$AO$44
B42: CO2-Biodiesel (Mobile combustion-off road) | C42: kg | D42: =D23 | E42: ='EF (1)'!$C$36 | Q42: =(E42*$AV$8)+(O41*P42) | W42: / | Z42: IPCC, 2006 | AA42: =D42*E42*$AV$8/1000 | AN42: =D42*O42*P42/1000 | AO42: =D42*Q42/1000 | AP42: =AO42/$AO$44
B43: CO2-Biogasoline (Ethanol) (Mobile combustion) | C43: kg | D43: =D24 | E43: ='EF (1)'!$C$35 | Q43: =(E43*$AV$8)+(O42*P43) | W43: / | Z43: IPCC, 2006 | AA43: =D43*E43*$AV$8/1000 | AN43: =D43*O43*P43/1000 | AO43: =D43*Q43/1000 | AP43: =AO43/$AO$44
AO44: =SUM(AO37:AO43) | AP44: =SUM(AP37:AP43)
A45: ขอบเขต 2 | B45: การใช้ไฟฟ้า โรงงาน/สำนักงาน | C45: kwh | D45: ='Scope 2.1 Purchased Electricity'!E3+'Scope 2.1 Purchased Electricity'!E7+'Scope 2.1 Purchased Electricity'!E12+'Scope 2.1 Purchased Electricity'!E15 | Q45: ='EF TGO AR5'!H53 | U45: / | Z45: TGO CFO EF (เมษายน 2565): ไฟฟ้า Grid mix | AO45: =D45*Q45/1000 | AP45: =AO45/$AO$49 | AQ45: =AO45/$AO$58 | AR45: =AO45/$AO$59
B46: การใช้ไฟฟ้า Solar cell โรงงาน | C46: kwh | D46: ='Scope 2.1 Purchased Electricity'!E8 | Q46: 0 | U46: / | Z46: ข้อกำหนด TGO | AO46: =D46*Q46/1000 | AP46: =AO46/$AO$49 | AQ46: =AO46/$AO$58 | AR46: =AO46/$AO$59
AO47: =D47*Q47/1000 | AP47: =AO47/$AO$49 | AQ47: =AO47/$AO$58 | AR47: =AO47/$AO$59
AP48: =AO48/$AO$49 | AQ48: =AO48/$AO$58 | AR48: =AO48/$AO$59
AO49: =SUM(AO45:AO48) | AP49: =SUM(AP45:AP48)
A50: ขอบเขต 3 | B50: #Cat 1 | AO50: =D50*Q50/1000 | AP50: =AO50/$AO$57 | AR50: =AO50/$AO$59
B51: ='Fr-03.2'!C22 | C51: ='Screen scope 3'!D3 | D51: ='Screen scope 3'!E3 | Q51: ='Screen scope 3'!H3 | U51: / | Z51: ='Screen scope 3'!K3 | AO51: =D51*Q51/1000 | AP51: =AO51/$AO$57 | AR51: =AO51/$AO$59
B52: ='Fr-03.2'!C23 | C52: ='Screen scope 3'!D4 | D52: ='Screen scope 3'!E4 | Q52: ='Screen scope 3'!H4 | U52: / | Z52: ='Screen scope 3'!K4 | AO52: =D52*Q52/1000 | AP52: =AO52/$AO$57 | AR52: =AO52/$AO$59
B53: ='Fr-03.2'!C24 | C53: ='Screen scope 3'!D5 | D53: ='Screen scope 3'!E5 | Q53: ='Screen scope 3'!H5 | U53: / | Z53: ='Screen scope 3'!K5 | AO53: =D53*Q53/1000 | AP53: =AO53/$AO$57 | AR53: =AO53/$AO$59
AO54: =D54*Q54/1000 | AP54: =AO54/$AO$57 | AR54: =AO54/$AO$59
AO55: =D55*Q55/1000 | AP55: =AO55/$AO$57 | AR55: =AO55/$AO$59
AP56: =AO56/$AO$57 | AR56: =AO56/$AO$59
AO57: =SUM(AO50:AO56) | AP57: =SUM(AP50:AP56)
AA58: =AA36+AA49 | AB58: =AB36+AB49 | AD58: =AD36+AD49 | AE58: =AE36+AE49 | AF58: =AF36+AF49 | AG58: =AG36+AG49 | AI58: =AI36+AI49 | AJ58: =AJ36+AJ49 | AK58: =AK36+AK49 | AL58: =AL36+AL49 | AM58: =AM36+AM49 | AN58: =AN36+AN49 | AO58: =AO36+AO49 | AQ58: =SUM(AQ10:AQ35)+SUM(AQ45:AQ48) | AR58: =SUM(AR10:AR35)+SUM(AR45:AR48)+SUM(AR50:AR56)
AA59: =AA36+AA49+AA57 | AB59: =AB36+AB49+AB57 | AD59: =AD36+AD49+AD57 | AE59: =AE36+AE49+AE57 | AF59: =AF36+AF49+AF57 | AG59: =AG36+AG49+AG57 | AI59: =AI36+AI49+AI57 | AJ59: =AJ36+AJ49+AJ57 | AK59: =AK36+AK49+AK57 | AL59: =AL36+AL49+AL57 | AM59: =AM36+AM49+AM57 | AN59: =AN36+AN49+AN57 | AO59: =AO36+AO49+AO57
A60: จัดทำโดย | B60: ='Fr-03.1'!B35 | AS60: {='Fr-03.1'!K35:M35} | AT60: 0 | AU60: 0

Sheet Fr-04.2
B1: บัญชีรายการก๊าซเรือนกระจก ปีฐาน (base year) | AO1: TCFO_R_01 Version 04 : 21/2/2020
B3: ชื่อฟอร์ม | C3: บัญชีรายการก๊าซเรือนกระจก | H3: องค์กร | I3: ='Fr-01'!$B$6 | AB3: ปีฐาน | AE3: ='Fr-01'!H38 | AO3: หน้าที่ | AR3: 5
B4: รหัสฟอร์ม | C4: Fr-04.2 | H4: ผู้จัดทำ | I4: ='Fr-01'!$G$4 | AO4: วันที่ | AR4: ='Fr-04.1'!AR4
A6: ขอบเขต | B6: รายการ | C6: ค่า LCI | E6: GHG ที่ต้องรายงานตามข้อกำหนด | O6: GHG ที่อยู่นอกข้อกำหนด | Q6: Total (kgCO2e/หน่วย) | R6: ที่มา | Y6: Subsitute | Z6: แหล่งอ้างอิง | AA6: ผลคูณ (Ton GHG) | AG6: ผลคูณ (TonCO2e) | AO6: Total GHG | AP6: สัดส่วน (%) | AQ6: สัดส่วน (%) (SCOPE 1+2) | AR6: สัดส่วน (%) (SCOPE 1+2+3) | AS6: ระบุความแตกต่างระหว่างการรายงานปริมาณก๊าซเรือนกระจกของปีฐานและปีปัจจุบัน | AU6: GWP100
R7: 1st | T7: 2nd | X7: Other | AU7: ที่มา | AV7: IPCC, AR5
E8: ค่า EF (kg GHG/หน่วย) | M8: GWP100 | O8: ค่า EF (kg GHG/หน่วย) | P8: GWP100 | R8: Self collct | S8: Supplier | T8: TH LCI DB | U8: TGO EF | V8: Thai Res. | W8: Int. DB | AO8: (TonCO2e) | AU8: CO2 | AV8: 1
C9: หน่วย | D9: ปริมาณ | E9: CO2 | F9: Fossil CH4 | G9: CH4 | H9: N2O | I9: SF6 | J9: NF3 | K9: HFCs | L9: PFCs | M9: HFCs | N9: PFCs | AA9: CO2 | AB9: Fossil CH4 | AC9: CH4 | AD9: N2O | AE9: SF6 | AF9: NF3 | AG9: Fossil CH4 | AH9: CH4 | AI9: N2O | AJ9: SF6 | AK9: NF3 | AL9: HFCs | AM9: PFCs | AN9: Other | AU9: Fossil CH4 | AV9: 30
A10: ขอบเขต 1 | B10: ='Fr-04.1'!B10 | Q10: =(E10*$AV$8)+(F10*$AV$9)+(G10*$AV$10)+(H10*$AV$11)+(I10*$AV$12)+(J10*$AV$13)+(K10*M10)+(L10*N10) | AA10: =D10*E10/1000 | AB10: =D10*F10/1000 | AC10: =D10*G10/1000 | AD10: =D10*H10/1000 | AE10: =D10*I10/1000 | AF10: =D10*J10/1000 | AG10: =D10*F10*$AV$9/1000 | AH10: =D10*G10*$AV$10/1000 | AI10: =D10*H10*$AV$11/1000 | AJ10: =D10*I10*$AV$12/1000 | AK10: =D10*J10*$AV$13/1000 | AL10: =D10*K10*M10/1000 | AM10: =D10*L10*N10/1000 | AO10: =D10*Q10/1000 | AP10: =AO10/$AO$35 | AQ10: =AO10/$AO$57 | AR10: =AO10/$AO$58 | AU10: CH4 | AV10: 28
B11: ='Fr-04.1'!B11 | C11: ='Fr-04.1'!C11 | D11: ='Fr-04.1'!D11 | E11: ='EF TGO AR5'!D11 | F11: ='EF TGO AR5'!E11 | G11: ='EF TGO AR5'!F11 | H11: ='EF TGO AR5'!G11 | Q11: =(E11*$AV$8)+(F11*$AV$9)+(G11*$AV$10)+(H11*$AV$11)+(I11*$AV$12)+(J11*$AV$13)+(K11*M11)+(L11*N11) | U11: / | Z11: ='Fr-04.1'!Z11 | AA11: =D11*E11/1000 | AB11: =D11*F11/1000 | AC11: =D11*G11/1000 | AD11: =D11*H11/1000 | AE11: =D11*I11/1000 | AF11: =D11*J11/1000 | AG11: =D11*F11*$AV$9/1000 | AH11: =D11*G11*$AV$10/1000 | AI11: =D11*H11*$AV$11/1000 | AJ11: =D11*I11*$AV$12/1000 | AK11: =D11*J11*$AV$13/1000 | AL11: =D11*K11*M11/1000 | AM11: =D11*L11*N11/1000 | AO11: =D11*Q11/1000 | AP11: =AO11/$AO$35 | AQ11: =AO11/$AO$57 | AR11: =AO11/$AO$58 | AU11: N2O | AV11: 265
B12: ='Fr-04.1'!B12 | C12: ='Fr-04.1'!C12 | D12: ='Fr-04.1'!D12 | E12: ='EF TGO AR5'!D17 | F12: ='EF TGO AR5'!E17 | G12: ='EF TGO AR5'!F17 | H12: ='EF TGO AR5'!G17 | Q12: =(E12*$AV$8)+(F12*$AV$9)+(G12*$AV$10)+(H12*$AV$11)+(I12*$AV$12)+(J12*$AV$13)+(K12*M12)+(L12*N12) | U12: / | Z12: ='Fr-04.1'!Z12 | AA12: =D12*E12/1000 | AB12: =D12*F12/1000 | AC12: =D12*G12/1000 | AD12: =D12*H12/1000 | AE12: =D12*I12/1000 | AF12: =D12*J12/1000 | AG12: =D12*F12*$AV$9/1000 | AH12: =D12*G12*$AV$10/1000 | AI12: =D12*H12*$AV$11/1000 | AJ12: =D12*I12*$AV$12/1000 | AK12: =D12*J12*$AV$13/1000 | AL12: =D12*K12*M12/1000 | AM12: =D12*L12*N12/1000 | AO12: =D12*Q12/1000 | AP12: =AO12/$AO$35 | AQ12: =AO12/$AO$57 | AR12: =AO12/$AO$58 | AU12: SF6 | AV12: 23500
B13: ='Fr-04.1'!B13 | C13: ='Fr-04.1'!C13 | D13: ='Fr-04.1'!D13 | E13: ='EF (1)'!B9 | Q13: =(E13*$AV$8)+(F13*$AV$9)+(G13*$AV$10)+(H13*$AV$11)+(I13*$AV$12)+(J13*$AV$13)+(K13*M13)+(L13*N13) | X13: / | Z13: ='Fr-04.1'!Z13 | AA13: =D13*E13/1000 | AB13: =D13*F13/1000 | AC13: =D13*G13/1000 | AD13: =D13*H13/1000 | AE13: =D13*I13/1000 | AF13: =D13*J13/1000 | AG13: =D13*F13*$AV$9/1000 | AH13: =D13*G13*$AV$10/1000 | AI13: =D13*H13*$AV$11/1000 | AJ13: =D13*I13*$AV$12/1000 | AK13: =D13*J13*$AV$13/1000 | AL13: =D13*K13*M13/1000 | AM13: =D13*L13*N13/1000 | AO13: =D13*Q13/1000 | AP13: =AO13/$AO$35 | AQ13: =AO13/$AO$57 | AR13: =AO13/$AO$58 | AU13: NF3 | AV13: 16100
B14: ='Fr-04.1'!B14 | C14: ='Fr-04.1'!C14 | D14: ='Fr-04.1'!D14 | G14: ='EF (1)'!F28*'EF (1)'!D28 | H14: ='EF (1)'!F28*'EF (1)'!E28 | Q14: =(E14*$AV$8)+(F14*$AV$9)+(G14*$AV$10)+(H14*$AV$11)+(I14*$AV$12)+(J14*$AV$13)+(K14*M14)+(L14*N14) | W14: / | Z14: ='Fr-04.1'!Z14 | AA14: =D14*E14/1000 | AB14: =D14*F14/1000 | AC14: =D14*G14/1000 | AD14: =D14*H14/1000 | AE14: =D14*I14/1000 | AF14: =D14*J14/1000 | AG14: =D14*F14*$AV$9/1000 | AH14: =D14*G14*$AV$10/1000 | AI14: =D14*H14*$AV$11/1000 | AJ14: =D14*I14*$AV$12/1000 | AK14: =D14*J14*$AV$13/1000 | AL14: =D14*K14*M14/1000 | AM14: =D14*L14*N14/1000 | AO14: =D14*Q14/1000 | AP14: =AO14/$AO$35 | AQ14: =AO14/$AO$57 | AR14: =AO14/$AO$58
B15: ='Fr-04.1'!B15 | C15: ='Fr-04.1'!C15 | D15: ='Fr-04.1'!D15 | G15: ='EF (1)'!F29*'EF (1)'!D29 | H15: ='EF (1)'!F29*'EF (1)'!E29 | Q15: =(E15*$AV$8)+(F15*$AV$9)+(G15*$AV$10)+(H15*$AV$11)+(I15*$AV$12)+(J15*$AV$13)+(K15*M15)+(L15*N15) | W15: / | Z15: ='Fr-04.1'!Z15 | AA15: =D15*E15/1000 | AB15: =D15*F15/1000 | AC15: =D15*G15/1000 | AD15: =D15*H15/1000 | AE15: =D15*I15/1000 | AF15: =D15*J15/1000 | AG15: =D15*F15*$AV$9/1000 | AH15: =D15*G15*$AV$10/1000 | AI15: =D15*H15*$AV$11/1000 | AJ15: =D15*I15*$AV$12/1000 | AK15: =D15*J15*$AV$13/1000 | AL15: =D15*K15*M15/1000 | AM15: =D15*L15*N15/1000 | AO15: =D15*Q15/1000 | AP15: =AO15/$AO$35 | AQ15: =AO15/$AO$57 | AR15: =AO15/$AO$58
B16: ='Fr-04.1'!B16 | Q16: =(E16*$AV$8)+(F16*$AV$9)+(G16*$AV$10)+(H16*$AV$11)+(I16*$AV$12)+(J16*$AV$13)+(K16*M16)+(L16*N16) | Z16: ='Fr-04.1'!Z16 | AA16: =D16*E16/1000 | AB16: =D16*F16/1000 | AC16: =D16*G16/1000 | AD16: =D16*H16/1000 | AE16: =D16*I16/1000 | AF16: =D16*J16/1000 | AG16: =D16*F16*$AV$9/1000 | AH16: =D16*G16*$AV$10/1000 | AI16: =D16*H16*$AV$11/1000 | AJ16: =D16*I16*$AV$12/1000 | AK16: =D16*J16*$AV$13/1000 | AL16: =D16*K16*M16/1000 | AM16: =D16*L16*N16/1000 | AO16: =D16*Q16/1000 | AP16: =AO16/$AO$35 | AQ16: =AO16/$AO$57 | AR16: =AO16/$AO$58
B17: ='Fr-04.1'!B17 | C17: ='Fr-04.1'!C17 | D17: ='Fr-04.1'!D17 | E17: ='EF TGO AR5'!D32 | F17: ='EF TGO AR5'!E32 | G17: ='EF TGO AR5'!F32 | H17: ='EF TGO AR5'!G32 | Q17: =(E17*$AV$8)+(F17*$AV$9)+(G17*$AV$10)+(H17*$AV$11)+(I17*$AV$12)+(J17*$AV$13)+(K17*M17)+(L17*N17) | U17: / | Z17: ='Fr-04.1'!Z17 | AA17: =D17*E17/1000 | AB17: =D17*F17/1000 | AC17: =D17*G17/1000 | AD17: =D17*H17/1000 | AE17: =D17*I17/1000 | AF17: =D17*J17/1000 | AG17: =D17*F17*$AV$9/1000 | AH17: =D17*G17*$AV$10/1000 | AI17: =D17*H17*$AV$11/1000 | AJ17: =D17*I17*$AV$12/1000 | AK17: =D17*J17*$AV$13/1000 | AL17: =D17*K17*M17/1000 | AM17: =D17*L17*N17/1000 | AO17: =D17*Q17/1000 | AP17: =AO17/$AO$35 | AQ17: =AO17/$AO$57 | AR17: =AO17/$AO$58
B18: ='Fr-04.1'!B18 | C18: ='Fr-04.1'!C18 | D18: ='Fr-04.1'!D18 | E18: ='EF TGO AR5'!D32 | F18: ='EF TGO AR5'!E32 | G18: ='EF TGO AR5'!F32 | H18: ='EF TGO AR5'!G32 | Q18: =(E18*$AV$8)+(F18*$AV$9)+(G18*$AV$10)+(H18*$AV$11)+(I18*$AV$12)+(J18*$AV$13)+(K18*M18)+(L18*N18) | U18: / | Z18: ='Fr-04.1'!Z18 | AA18: =D18*E18/1000 | AB18: =D18*F18/1000 | AC18: =D18*G18/1000 | AD18: =D18*H18/1000 | AE18: =D18*I18/1000 | AF18: =D18*J18/1000 | AG18: =D18*F18*$AV$9/1000 | AH18: =D18*G18*$AV$10/1000 | AI18: =D18*H18*$AV$11/1000 | AJ18: =D18*I18*$AV$12/1000 | AK18: =D18*J18*$AV$13/1000 | AL18: =D18*K18*M18/1000 | AM18: =D18*L18*N18/1000 | AO18: =D18*Q18/1000 | AP18: =AO18/$AO$35 | AQ18: =AO18/$AO$57 | AR18: =AO18/$AO$58
B19: ='Fr-04.1'!B19 | C19: ='Fr-04.1'!C19 | D19: ='Fr-04.1'!D19 | E19: ='EF TGO AR5'!D30 | F19: ='EF TGO AR5'!E30 | G19: ='EF TGO AR5'!F30 | H19: ='EF TGO AR5'!G30 | Q19: =(E19*$AV$8)+(F19*$AV$9)+(G19*$AV$10)+(H19*$AV$11)+(I19*$AV$12)+(J19*$AV$13)+(K19*M19)+(L19*N19) | U19: / | Z19: ='Fr-04.1'!Z19 | AA19: =D19*E19/1000 | AB19: =D19*F19/1000 | AC19: =D19*G19/1000 | AD19: =D19*H19/1000 | AE19: =D19*I19/1000 | AF19: =D19*J19/1000 | AG19: =D19*F19*$AV$9/1000 | AH19: =D19*G19*$AV$10/1000 | AI19: =D19*H19*$AV$11/1000 | AJ19: =D19*I19*$AV$12/1000 | AK19: =D19*J19*$AV$13/1000 | AL19: =D19*K19*M19/1000 | AM19: =D19*L19*N19/1000 | AO19: =D19*Q19/1000 | AP19: =AO19/$AO$35 | AQ19: =AO19/$AO$57 | AR19: =AO19/$AO$58
B20: ='Fr-04.1'!B20 | C20: ='Fr-04.1'!C20 | D20: ='Fr-04.1'!D20 | E20: ='EF TGO AR5'!D30 | F20: ='EF TGO AR5'!E30 | G20: ='EF TGO AR5'!F30 | H20: ='EF TGO AR5'!G30 | Q20: =(E20*$AV$8)+(F20*$AV$9)+(G20*$AV$10)+(H20*$AV$11)+(I20*$AV$12)+(J20*$AV$13)+(K20*M20)+(L20*N20) | W20: / | Z20: ='Fr-04.1'!Z20 | AA20: =D20*E20/1000 | AB20: =D20*F20/1000 | AC20: =D20*G20/1000 | AD20: =D20*H20/1000 | AE20: =D20*I20/1000 | AF20: =D20*J20/1000 | AG20: =D20*F20*$AV$9/1000 | AH20: =D20*G20*$AV$10/1000 | AI20: =D20*H20*$AV$11/1000 | AJ20: =D20*I20*$AV$12/1000 | AK20: =D20*J20*$AV$13/1000 | AL20: =D20*K20*M20/1000 | AM20: =D20*L20*N20/1000 | AO20: =D20*Q20/1000 | AP20: =AO20/$AO$35 | AQ20: =AO20/$AO$57 | AR20: =AO20/$AO$58
B21: ='Fr-04.1'!B21 | C21: ='Fr-04.1'!C21 | D21: ='Fr-04.1'!D21 | E21: ='EF TGO AR5'!D40 | F21: ='EF TGO AR5'!E40 | G21: ='EF TGO AR5'!F40 | H21: ='EF TGO AR5'!G40 | Q21: =(E21*$AV$8)+(F21*$AV$9)+(G21*$AV$10)+(H21*$AV$11)+(I21*$AV$12)+(J21*$AV$13)+(K21*M21)+(L21*N21) | W21: / | Z21: ='Fr-04.1'!Z21 | AA21: =D21*E21/1000 | AB21: =D21*F21/1000 | AC21: =D21*G21/1000 | AD21: =D21*H21/1000 | AE21: =D21*I21/1000 | AF21: =D21*J21/1000 | AG21: =D21*F21*$AV$9/1000 | AH21: =D21*G21*$AV$10/1000 | AI21: =D21*H21*$AV$11/1000 | AJ21: =D21*I21*$AV$12/1000 | AK21: =D21*J21*$AV$13/1000 | AL21: =D21*K21*M21/1000 | AM21: =D21*L21*N21/1000 | AO21: =D21*Q21/1000 | AP21: =AO21/$AO$35 | AQ21: =AO21/$AO$57 | AR21: =AO21/$AO$58
B22: ='Fr-04.1'!B22 | C22: ='Fr-04.1'!C22 | D22: ='Fr-04.1'!D22 | G22: ='EF (1)'!F30*'EF (1)'!D30 | H22: ='EF (1)'!F30*'EF (1)'!E30 | Q22: =(E22*$AV$8)+(F22*$AV$9)+(G22*$AV$10)+(H22*$AV$11)+(I22*$AV$12)+(J22*$AV$13)+(K22*M22)+(L22*N22) | W22: / | Z22: ='Fr-04.1'!Z22 | AA22: =D22*E22/1000 | AB22: =D22*F22/1000 | AC22: =D22*G22/1000 | AD22: =D22*H22/1000 | AE22: =D22*I22/1000 | AF22: =D22*J22/1000 | AG22: =D22*F22*$AV$9/1000 | AH22: =D22*G22*$AV$10/1000 | AI22: =D22*H22*$AV$11/1000 | AJ22: =D22*I22*$AV$12/1000 | AK22: =D22*J22*$AV$13/1000 | AL22: =D22*K22*M22/1000 | AM22: =D22*L22*N22/1000 | AO22: =D22*Q22/1000 | AP22: =AO22/$AO$35 | AQ22: =AO22/$AO$57 | AR22: =AO22/$AO$58
B23: ='Fr-04.1'!B23 | C23: ='Fr-04.1'!C23 | D23: ='Fr-04.1'!D23 | G23: ='EF (1)'!F32*'EF (1)'!D32 | H23: ='EF (1)'!F32*'EF (1)'!E32 | Q23: =(E23*$AV$8)+(F23*$AV$9)+(G23*$AV$10)+(H23*$AV$11)+(I23*$AV$12)+(J23*$AV$13)+(K23*M23)+(L23*N23) | W23: / | Z23: ='Fr-04.1'!Z23 | AA23: =D23*E23/1000 | AB23: =D23*F23/1000 | AC23: =D23*G23/1000 | AD23: =D23*H23/1000 | AE23: =D23*I23/1000 | AF23: =D23*J23/1000 | AG23: =D23*F23*$AV$9/1000 | AH23: =D23*G23*$AV$10/1000 | AI23: =D23*H23*$AV$11/1000 | AJ23: =D23*I23*$AV$12/1000 | AK23: =D23*J23*$AV$13/1000 | AL23: =D23*K23*M23/1000 | AM23: =D23*L23*N23/1000 | AO23: =D23*Q23/1000 | AP23: =AO23/$AO$35 | AQ23: =AO23/$AO$57 | AR23: =AO23/$AO$58
B24: ='Fr-04.1'!B24 | C24: ='Fr-04.1'!C24 | D24: ='Fr-04.1'!D24 | G24: ='EF (1)'!F31*'EF (1)'!D31 | H24: ='EF (1)'!F31*'EF (1)'!E31 | Q24: =(E24*$AV$8)+(F24*$AV$9)+(G24*$AV$10)+(H24*$AV$11)+(I24*$AV$12)+(J24*$AV$13)+(K24*M24)+(L24*N24) | W24: / | Z24: ='Fr-04.1'!Z24 | AA24: =D24*E24/1000 | AB24: =D24*F24/1000 | AC24: =D24*G24/1000 | AD24: =D24*H24/1000 | AE24: =D24*I24/1000 | AF24: =D24*J24/1000 | AG24: =D24*F24*$AV$9/1000 | AH24: =D24*G24*$AV$10/1000 | AI24: =D24*H24*$AV$11/1000 | AJ24: =D24*I24*$AV$12/1000 | AK24: =D24*J24*$AV$13/1000 | AL24: =D24*K24*M24/1000 | AM24: =D24*L24*N24/1000 | AO24: =D24*Q24/1000 | AP24: =AO24/$AO$35 | AQ24: =AO24/$AO$57 | AR24: =AO24/$AO$58
B25: ='Fr-04.1'!B25 | Q25: =(E25*$AV$8)+(F25*$AV$9)+(G25*$AV$10)+(H25*$AV$11)+(I25*$AV$12)+(J25*$AV$13)+(K25*M25)+(L25*N25) | Z25: ='Fr-04.1'!Z25 | AA25: =D25*E25/1000 | AB25: =D25*F25/1000 | AC25: =D25*G25/1000 | AD25: =D25*H25/1000 | AE25: =D25*I25/1000 | AF25: =D25*J25/1000 | AG25: =D25*F25*$AV$9/1000 | AH25: =D25*G25*$AV$10/1000 | AI25: =D25*H25*$AV$11/1000 | AJ25: =D25*I25*$AV$12/1000 | AK25: =D25*J25*$AV$13/1000 | AL25: =D25*K25*M25/1000 | AM25: =D25*L25*N25/1000 | AO25: =D25*Q25/1000 | AP25: =AO25/$AO$35 | AQ25: =AO25/$AO$57 | AR25: =AO25/$AO$58
B26: ='Fr-04.1'!B26 | C26: ='Fr-04.1'!C26 | D26: ='Fr-04.1'!D26 | K26: 1 | M26: ='EF TGO AR5'!H56 | Q26: =(E26*$AV$8)+(F26*$AV$9)+(G26*$AV$10)+(H26*$AV$11)+(I26*$AV$12)+(J26*$AV$13)+(K26*M26)+(L26*N26) | W26: / | Z26: ='Fr-04.1'!Z26 | AA26: =D26*E26/1000 | AB26: =D26*F26/1000 | AC26: =D26*G26/1000 | AD26: =D26*H26/1000 | AE26: =D26*I26/1000 | AF26: =D26*J26/1000 | AG26: =D26*F26*$AV$9/1000 | AH26: =D26*G26*$AV$10/1000 | AI26: =D26*H26*$AV$11/1000 | AJ26: =D26*I26*$AV$12/1000 | AK26: =D26*J26*$AV$13/1000 | AL26: =D26*K26*M26/1000 | AM26: =D26*L26*N26/1000 | AO26: =D26*Q26/1000 | AP26: =AO26/$AO$35 | AQ26: =AO26/$AO$57 | AR26: =AO26/$AO$58
B27: ='Fr-04.1'!B27 | C27: ='Fr-04.1'!C27 | D27: ='Fr-04.1'!D27 | K27: 1 | M27: ='EF (1)'!E16 | Q27: =(E27*$AV$8)+(F27*$AV$9)+(G27*$AV$10)+(H27*$AV$11)+(I27*$AV$12)+(J27*$AV$13)+(K27*M27)+(L27*N27) | W27: / | Z27: ='Fr-04.1'!Z27 | AA27: =D27*E27/1000 | AB27: =D27*F27/1000 | AC27: =D27*G27/1000 | AD27: =D27*H27/1000 | AE27: =D27*I27/1000 | AF27: =D27*J27/1000 | AG27: =D27*F27*$AV$9/1000 | AH27: =D27*G27*$AV$10/1000 | AI27: =D27*H27*$AV$11/1000 | AJ27: =D27*I27*$AV$12/1000 | AK27: =D27*J27*$AV$13/1000 | AL27: =D27*K27*M27/1000 | AM27: =D27*L27*N27/1000 | AO27: =D27*Q27/1000 | AP27: =AO27/$AO$35 | AQ27: =AO27/$AO$57 | AR27: =AO27/$AO$58
B28: ='Fr-04.1'!B28 | C28: ='Fr-04.1'!C28 | D28: ='Fr-04.1'!D28 | K28: 1 | M28: ='EF TGO AR5'!H59 | Q28: =(E28*$AV$8)+(F28*$AV$9)+(G28*$AV$10)+(H28*$AV$11)+(I28*$AV$12)+(J28*$AV$13)+(K28*M28)+(L28*N28) | W28: / | Z28: ='Fr-04.1'!Z28 | AA28: =D28*E28/1000 | AB28: =D28*F28/1000 | AC28: =D28*G28/1000 | AD28: =D28*H28/1000 | AE28: =D28*I28/1000 | AF28: =D28*J28/1000 | AG28: =D28*F28*$AV$9/1000 | AH28: =D28*G28*$AV$10/1000 | AI28: =D28*H28*$AV$11/1000 | AJ28: =D28*I28*$AV$12/1000 | AK28: =D28*J28*$AV$13/1000 | AL28: =D28*K28*M28/1000 | AM28: =D28*L28*N28/1000 | AO28: =D28*Q28/1000 | AP28: =AO28/$AO$35 | AQ28: =AO28/$AO$57 | AR28: =AO28/$AO$58
B29: ='Fr-04.1'!B29 | C29: ='Fr-04.1'!C29 | D29: ='Fr-04.1'!D29 | K29: 1 | M29: ='EF (1)'!E19 | Q29: =(E29*$AV$8)+(F29*$AV$9)+(G29*$AV$10)+(H29*$AV$11)+(I29*$AV$12)+(J29*$AV$13)+(K29*M29)+(L29*N29) | W29: / | Z29: ='Fr-04.1'!Z29 | AA29: =D29*E29/1000 | AB29: =D29*F29/1000 | AC29: =D29*G29/1000 | AD29: =D29*H29/1000 | AE29: =D29*I29/1000 | AF29: =D29*J29/1000 | AG29: =D29*F29*$AV$9/1000 | AH29: =D29*G29*$AV$10/1000 | AI29: =D29*H29*$AV$11/1000 | AJ29: =D29*I29*$AV$12/1000 | AK29: =D29*J29*$AV$13/1000 | AL29: =D29*K29*M29/1000 | AM29: =D29*L29*N29/1000 | AO29: =D29*Q29/1000 | AP29: =AO29/$AO$35 | AQ29: =AO29/$AO$57 | AR29: =AO29/$AO$58
B30: ='Fr-04.1'!B30 | C30: ='Fr-04.1'!C30 | D30: ='Fr-04.1'!D30 | E30: 1 | Q30: =(E30*$AV$8)+(F30*$AV$9)+(G30*$AV$10)+(H30*$AV$11)+(I30*$AV$12)+(J30*$AV$13)+(K30*M30)+(L30*N30) | W30: / | Z30: ='Fr-04.1'!Z30 | AA30: =D30*E30/1000 | AB30: =D30*F30/1000 | AC30: =D30*G30/1000 | AD30: =D30*H30/1000 | AE30: =D30*I30/1000 | AF30: =D30*J30/1000 | AG30: =D30*F30*$AV$9/1000 | AH30: =D30*G30*$AV$10/1000 | AI30: =D30*H30*$AV$11/1000 | AJ30: =D30*I30*$AV$12/1000 | AK30: =D30*J30*$AV$13/1000 | AL30: =D30*K30*M30/1000 | AM30: =D30*L30*N30/1000 | AO30: =D30*Q30/1000 | AP30: =AO30/$AO$35 | AQ30: =AO30/$AO$57 | AR30: =AO30/$AO$58
B31: ='Fr-04.1'!B31 | C31: ='Fr-04.1'!C31 | D31: ='Fr-04.1'!D31 | G31: 1 | Q31: =(E31*$AV$8)+(F31*$AV$9)+(G31*$AV$10)+(H31*$AV$11)+(I31*$AV$12)+(J31*$AV$13)+(K31*M31)+(L31*N31) | W31: / | Z31: ='Fr-04.1'!Z31 | AA31: =D31*E31/1000 | AB31: =D31*F31/1000 | AC31: =D31*G31/1000 | AD31: =D31*H31/1000 | AE31: =D31*I31/1000 | AF31: =D31*J31/1000 | AG31: =D31*F31*$AV$9/1000 | AH31: =D31*G31*$AV$10/1000 | AI31: =D31*H31*$AV$11/1000 | AJ31: =D31*I31*$AV$12/1000 | AK31: =D31*J31*$AV$13/1000 | AL31: =D31*K31*M31/1000 | AM31: =D31*L31*N31/1000 | AO31: =D31*Q31/1000 | AP31: =AO31/$AO$35 | AQ31: =AO31/$AO$57 | AR31: =AO31/$AO$58
B32: ='Fr-04.1'!B32 | C32: ='Fr-04.1'!C32 | D32: ='Fr-04.1'!D32 | H32: ='1.4.4 ปุ๋ย'!Q3 | Q32: =(E32*$AV$8)+(F32*$AV$9)+(G32*$AV$10)+(H32*$AV$11)+(I32*$AV$12)+(J32*$AV$13)+(K32*M32)+(L32*N32) | W32: / | Z32: ='Fr-04.1'!Z32 | AA32: =D32*E32/1000 | AB32: =D32*F32/1000 | AC32: =D32*G32/1000 | AD32: =D32*H32/1000 | AE32: =D32*I32/1000 | AF32: =D32*J32/1000 | AG32: =D32*F32*$AV$9/1000 | AH32: =D32*G32*$AV$10/1000 | AI32: =D32*H32*$AV$11/1000 | AJ32: =D32*I32*$AV$12/1000 | AK32: =D32*J32*$AV$13/1000 | AL32: =D32*K32*M32/1000 | AM32: =D32*L32*N32/1000 | AO32: =D32*Q32/1000 | AP32: =AO32/$AO$35 | AQ32: =AO32/$AO$57 | AR32: =AO32/$AO$58
Q33: =(E33*$AV$8)+(F33*$AV$9)+(G33*$AV$10)+(H33*$AV$11)+(I33*$AV$12)+(J33*$AV$13)+(K33*M33)+(L33*N33) | AA33: =D33*E33/1000 | AB33: =D33*F33/1000 | AC33: =D33*G33/1000 | AD33: =D33*H33/1000 | AE33: =D33*I33/1000 | AF33: =D33*J33/1000 | AG33: =D33*F33*$AV$9/1000 | AH33: =D33*G33*$AV$10/1000 | AI33: =D33*H33*$AV$11/1000 | AJ33: =D33*I33*$AV$12/1000 | AK33: =D33*J33*$AV$13/1000 | AL33: =D33*K33*M33/1000 | AM33: =D33*L33*N33/1000 | AO33: =D33*Q33/1000 | AP33: =AO33/$AO$35 | AQ33: =AO33/$AO$57 | AR33: =AO33/$AO$58
Q34: =(E34*$AV$8)+(F34*$AV$9)+(G34*$AV$10)+(H34*$AV$11)+(I34*$AV$12)+(J34*$AV$13)+(K34*M34)+(L34*N34) | AA34: =D34*E34/1000 | AB34: =D34*F34/1000 | AC34: =D34*G34/1000 | AD34: =D34*H34/1000 | AE34: =D34*I34/1000 | AF34: =D34*J34/1000 | AG34: =D34*F34*$AV$9/1000 | AH34: =D34*G34*$AV$10/1000 | AI34: =D34*H34*$AV$11/1000 | AJ34: =D34*I34*$AV$12/1000 | AK34: =D34*J34*$AV$13/1000 | AL34: =D34*K34*M34/1000 | AM34: =D34*L34*N34/1000 | AO34: =D34*Q34/1000 | AP34: =AO34/$AO$35 | AQ34: =AO34/$AO$57 | AR34: =AO34/$AO$58
AA35: =SUM(AA10:AA34) | AB35: =SUM(AB10:AB34) | AC35: =SUM(AC10:AC34) | AD35: =SUM(AD10:AD34) | AE35: =SUM(AE10:AE34) | AF35: =SUM(AF10:AF34) | AG35: =SUM(AG10:AG34) | AH35: =SUM(AH10:AH34) | ... AP35: =SUM(AP10:AP34)
A36: การปล่อย GHG โดยตรงที่ทำการรายงานแยก | B36: ='Fr-04.1'!B37 | C36: ='Fr-04.1'!C37 | D36: ='Fr-04.1'!D37 | O36: 1 | P36: ='EF TGO AR5'!H55 | Q36: =(E36*$AV$8)+(O36*P36) | W36: / | Z36: ='Fr-04.1'!Z37 | AA36: =D36*E36*$AV$8/1000 | AN36: =D36*O36*P36/1000 | AO36: =D36*Q36/1000 | AP36: =AO36/$AO$43
B37: ='Fr-04.1'!B38 | C37: ='Fr-04.1'!C38 | D37: ='Fr-04.1'!D38 | O37: 1 | P37: ='EF (1)'!E13 | Q37: =(E37*$AV$8)+(O37*P37) | W37: / | Z37: ='Fr-04.1'!Z38 | AA37: =D37*E37*$AV$8/1000 | AN37: =D37*O37*P37/1000 | AO37: =D37*Q37/1000 | AP37: =AO37/$AO$43
B38: ='Fr-04.1'!B39 | C38: ='Fr-04.1'!C39 | D38: ='Fr-04.1'!D39 | E38: ='EF (1)'!F28*'EF (1)'!C28 | Q38: =(E38*$AV$8)+(O38*P38) | W38: / | Z38: ='Fr-04.1'!Z39 | AA38: =D38*E38*$AV$8/1000 | AN38: =D38*O38*P38/1000 | AO38: =D38*Q38/1000 | AP38: =AO38/$AO$43
B39: ='Fr-04.1'!B40 | C39: ='Fr-04.1'!C40 | D39: ='Fr-04.1'!D40 | E39: ='EF (1)'!F29*'EF (1)'!C29 | Q39: =(E39*$AV$8)+(O39*P39) | W39: / | Z39: ='Fr-04.1'!Z40 | AA39: =D39*E39*$AV$8/1000 | AN39: =D39*O39*P39/1000 | AO39: =D39*Q39/1000 | AP39: =AO39/$AO$43
B40: ='Fr-04.1'!B41 | C40: ='Fr-04.1'!C41 | D40: ='Fr-04.1'!D41 | E40: ='EF (1)'!C34 | Q40: =(E40*$AV$8)+(O40*P40) | W40: / | Z40: ='Fr-04.1'!Z41 | AA40: =D40*E40*$AV$8/1000 | AN40: =D40*O40*P40/1000 | AO40: =D40*Q40/1000 | AP40: =AO40/$AO$43
B41: ='Fr-04.1'!B42 | C41: ='Fr-04.1'!C42 | D41: ='Fr-04.1'!D42 | E41: ='EF (1)'!C36 | Q41: =(E41*$AV$8)+(O41*P41) | W41: / | Z41: ='Fr-04.1'!Z42 | AA41: =D41*E41*$AV$8/1000 | AN41: =D41*O41*P41/1000 | AO41: =D41*Q41/1000 | AP41: =AO41/$AO$43
B42: ='Fr-04.1'!B43 | C42: ='Fr-04.1'!C43 | D42: ='Fr-04.1'!D43 | E42: ='EF (1)'!C35 | Q42: =(E42*$AV$8)+(O42*P42) | W42: / | Z42: ='Fr-04.1'!Z43 | AA42: =D42*E42*$AV$8/1000 | AN42: =D42*O42*P42/1000 | AO42: =D42*Q42/1000 | AP42: =AO42/$AO$43
AO43: =SUM(AO36:AO42) | AP43: =SUM(AP36:AP42)
A44: ขอบเขต 2 | B44: ='Fr-04.1'!B45 | C44: ='Fr-04.1'!C45 | D44: ='Fr-04.1'!D45 | Q44: ='Fr-04.1'!Q45 | U44: / | Z44: ='Fr-04.1'!Z45 | AO44: =D44*Q44/1000 | AP44: =AO44/$AO$48 | AQ44: =AO44/$AO$57 | AR44: =AO44/$AO$58
B45: ='Fr-04.1'!B46 | C45: ='Fr-04.1'!C46 | D45: ='Fr-04.1'!D46 | Q45: ='Fr-04.1'!Q46 | U45: / | Z45: ='Fr-04.1'!Z46 | AO45: =D45*Q45/1000 | AP45: =AO45/$AO$48 | AQ45: =AO45/$AO$57 | AR45: =AO45/$AO$58
AO46: =D46*Q46/1000 | AP46: =AO46/$AO$48 | AQ46: =AO46/$AO$57 | AR46: =AO46/$AO$58
AP47: =AO47/$AO$48 | AQ47: =AO47/$AO$57 | AR47: =AO47/$AO$58
AO48: =SUM(AO44:AO47) | AP48: =SUM(AP44:AP47)
A49: ขอบเขต 3 | B49: ='Fr-04.1'!B50 | AO49: =D49*Q49/1000 | AP49: =AO49/$AO$56 | AR49: =AO49/$AO$58
B50: ='Fr-04.1'!B51 | C50: ='Fr-04.1'!C51 | D50: ='Fr-04.1'!D51 | Q50: ='Fr-04.1'!Q51 | U50: / | Z50: ='Fr-04.1'!Z51 | AO50: =D50*Q50/1000 | AP50: =AO50/$AO$56 | AR50: =AO50/$AO$58
B51: ='Fr-04.1'!B52 | C51: ='Fr-04.1'!C52 | D51: ='Fr-04.1'!D52 | Q51: ='Fr-04.1'!Q52 | U51: / | Z51: ='Fr-04.1'!Z52 | AO51: =D51*Q51/1000 | AP51: =AO51/$AO$56 | AR51: =AO51/$AO$58
B52: ='Fr-04.1'!B53 | C52: ='Fr-04.1'!C53 | D52: ='Fr-04.1'!D53 | Q52: ='Fr-04.1'!Q53 | U52: / | Z52: ='Fr-04.1'!Z53 | AO52: =D52*Q52/1000 | AP52: =AO52/$AO$56 | AR52: =AO52/$AO$58
AO53: =D53*Q53/1000 | AP53: =AO53/$AO$56 | AR53: =AO53/$AO$58
AO54: =D54*Q54/1000 | AP54: =AO54/$AO$56 | AR54: =AO54/$AO$58
AP55: =AO55/$AO$56 | AR55: =AO55/$AO$58
AO56: =SUM(AO49:AO55) | AP56: =SUM(AP49:AP55)
AA57: =AA35+AA48 | AB57: =AB35+AB48 | AD57: =AD35+AD48 | AE57: =AE35+AE48 | AF57: =AF35+AF48 | AG57: =AG35+AG48 | AI57: =AI35+AI48 | AJ57: =AJ35+AJ48 | AK57: =AK35+AK48 | AL57: =AL35+AL48 | AM57: =AM35+AM48 | AN57: =AN35+AN48 | AO57: =AO35+AO48 | AQ57: =SUM(AQ10:AQ34)+SUM(AQ44:AQ47) | AR57: =SUM(AR10:AR34)+SUM(AR44:AR47)+SUM(AR49:AR55)
AA58: =AA35+AA48+AA56 | AB58: =AB35+AB48+AB56 | AD58: =AD35+AD48+AD56 | AE58: =AE35+AE48+AE56 | AF58: =AF35+AF48+AF56 | AG58: =AG35+AG48+AG56 | AI58: =AI35+AI48+AI56 | AJ58: =AJ35+AJ48+AJ56 | AK58: =AK35+AK48+AK56 | AL58: =AL35+AL48+AL56 | AM58: =AM35+AM48+AM56 | AN58: =AN35+AN48+AN56 | AO58: =AO35+AO48+AO56
A59: จัดทำโดย | B59: ='Fr-04.1'!B60 | AS59: {='Fr-03.1'!K35:M35} | AT59: 0 | AU59: 0

Sheet Fr-05
B1: สรุปการปล่อยก๊าซเรือนกระจกขององค์กร | I1: TCFO_R_01 Version 04 : 21/2/2020
B3: ชื่อฟอร์ม | C3: บัญชีรายการก๊าซเรือนกระจก | E3: องค์กร | F3: ='Fr-01'!$B$6 | I3: หน้าที่ | J3: 6
B4: รหัสฟอร์ม | C4: Fr-05 | E4: ผู้จัดทำ | F4: ='Fr-01'!$G$4 | I4: วันที่จัดทำ | J4: ='Fr-01'!J4
A5: ปีปัจจุบัน | B5: ='Fr-01'!H36
B6: ขอบเขต | C6: การปล่อยก๊าซเรือนกระจกขององค์กร | D6: สัดส่วนเมื่อเทียบขอบเขต 1 และ 2 | E6: สัดส่วนเมื่อเทียบขอบเขต 1, 2 และ 3
B10: ประเภท 1 | C10: =ROUNDUP('Fr-04.1'!AO36,0) | D10: =C10/C$14% | E10: =C10/SUM(C10:C12)%
B11: ประเภท 2 | C11: =ROUNDUP('Fr-04.1'!AO49,0) | D11: =C11/C$14% | E11: =C11/SUM(C10:C12)%
B12: ประเภท 3 | C12: =ROUNDUP('Fr-04.1'!AO57,0) | E12: =C12/SUM(C10:C12)%
B13: อื่น ๆ | C13: =ROUNDUP('Fr-04.1'!AO44,0)
B14: รวม Scope 1 & 2 | C14: =SUM(C10:C11) | D14: =SUM(D10:D11)
B15: รวม Scope 1 & 2 & 3 | C15: =SUM(C10:C12) | E15: =SUM(E10:E12)
B17: Carbon intensity (Scope 1+2) | D17: =C14/'Fr-01'!H37 | E17: TonCO2eq/ | F17: ='Fr-01'!J37
B18: Carbon intensity (Scope 1+2+3) | D18: =C15/'Fr-01'!H37 | E18: TonCO2eq/ | F18: ='Fr-01'!J37
A20: ปีฐาน | B20: ='Fr-01'!H38
B22: ขอบเขต | C22: การปล่อยก๊าซเรือนกระจกขององค์กร | D22: สัดส่วนเมื่อเทียบขอบเขต 1 และ 2 | E22: สัดส่วนเมื่อเทียบขอบเขต 1, 2 และ 3 | G22: เปรียบเทียบ
B26: ประเภท 1 | C26: =ROUNDUP('Fr-04.2'!AO35,0) | D26: =C26/C$14% | E26: =C26/SUM(C26:C28)%
B27: ประเภท 2 | C27: =ROUNDUP('Fr-04.2'!AO48,0) | D27: =C27/C$14% | E27: =C27/SUM(C26:C28)%
B28: ประเภท 3 | C28: =ROUNDUP('Fr-04.2'!AO56,0) | E28: =C28/SUM(C26:C28)%
B29: อื่น ๆ | C29: =ROUNDUP('Fr-04.2'!AO43,0)
B30: รวม Scope 1 & 2 | C30: =SUM(C26:C27) | D30: =SUM(D26:D27)
B31: รวม Scope 1 & 2 & 3 | C31: =SUM(C26:C28) | E31: =SUM(E26:E28)
B33: Carbon intensity (Scope 1+2) | D33: =C30/'Fr-01'!H39 | E33: TonCO2eq/ | F33: =F17
B34: Carbon intensity (Scope 1+2+3) | D34: =C31/'Fr-01'!H39 | E34: TonCO2eq/ | F34: =F18
A37: จัดทำโดย | B37: ='Fr-04.2'!B59 | G37: เสร็จสิ้นวันที่ | H37: ='Fr-03.1'!K35

Sheet EF TGO AR4
B2: ชื่อ | C2: Units | D2: EMISSION FACTORS | H2: แหล่งอ้างอิงข้อมูล | J2: GWP100
D3: CO2 | E3: CH4 | F3: N2O | G3: Total | J3: ที่มา | K3: IPCC, AR4 | L3: IPCC, AR5
D4: [kg CO2/unit] | E4: [kg CH4/unit] | F4: [kg N2O/unit] | G4: [kg CO2eq/unit] | J4: CO2 | K4: 1 | L4: 1
A5: Stationary Combustion | J5: CH4 | K5: 25 | L5: 28
B6: Natural gas | C6: scf | D6: =D48*$G$48*10^-6 | E6: =E48*$G$48*10^-6 | F6: =F48*$G$48*10^-6 | G6: =D6+(E6*$K$5)+(F6*$K$6) | H6: IPCC Vol.2 table 2.2, DEDE | J6: N2O | K6: 298 | L6: 265
B7: Natural gas | C7: MJ | D7: =D48/1000000 | E7: =E48/1000000 | F7: =F48/1000000 | G7: =D7+(E7*$K$5)+(F7*$K$6) | H7: IPCC Vol.2 table 2.2, DEDE | J7: SF6 | K7: 22800 | L7: 23500
B8: Lignite | C8: kg | D8: =D49*$G$49*10^-6 | E8: =E49*$G$49*10^-6 | F8: =F49*$G$49*10^-6 | G8: =D8+(E8*$K$5)+(F8*$K$6) | H8: IPCC Vol.2 table 2.2, DEDE | J8: NF3 | K8: 17200 | L8: 16100
B9: Fuel oil A | C9: litre | D9: =D50*$G$50*10^-6 | E9: =E50*$G$50*10^-6 | F9: =F50*$G$50*10^-6 | G9: =D9+(E9*$K$5)+(F9*$K$6) | H9: IPCC Vol.2 table 2.2, PTT | J9: PASS: 12345678
B10: Fuel oil C | C10: litre | D10: =D51*$G$51*10^-6 | E10: =E51*$G$51*10^-6 | F10: =F51*$G$51*10^-6 | G10: =D10+(E10*$K$5)+(F10*$K$6) | H10: IPCC Vol.2 table 2.2, PTT
B11: Gas/Diesel oil | C11: litre | D11: =D52*$G$52*10^-6 | E11: =E52*$G$52*10^-6 | F11: =F52*$G$52*10^-6 | G11: =D11+(E11*$K$5)+(F11*$K$6) | H11: IPCC Vol.2 table 2.2, DEDE
B12: Anthracite | C12: kg | D12: =D53*$G$53*10^-6 | E12: =E53*$G$53*10^-6 | F12: =F53*$G$53*10^-6 | G12: =D12+(E12*$K$5)+(F12*$K$6) | H12: IPCC Vol.2 table 2.2, DEDE
B13: Sub-bituminous coal | C13: kg | D13: =D54*$G$54*10^-6 | E13: =E54*$G$54*10^-6 | F13: =F54*$G$54*10^-6 | G13: =D13+(E13*$K$5)+(F13*$K$6) | H13: IPCC Vol.2 table 2.2, DEDE
B14: Jet Kerosene | C14: litre | D14: =D55*$G$55*10^-6 | E14: =E55*$G$55*10^-6 | F14: =F55*$G$55*10^-6 | G14: =D14+(E14*$K$5)+(F14*$K$6) | H14: IPCC Vol.2 table 2.2, DEDE
B15: LPG | C15: litre | D15: =D56*$G$56*10^-6 | E15: =E56*$G$56*10^-6 | F15: =F56*$G$56*10^-6 | G15: =D15+(E15*$K$5)+(F15*$K$6) | H15: IPCC Vol.2 table 2.2, DEDE
B16: LPG | C16: kg | D16: =D15/0.54 | E16: =E15/0.54 | F16: =F15/0.54 | G16: =D16+(E16*$K$5)+(F16*$K$6) | H16: IPCC Vol.2 table 2.2, DEDE LPG 1 litre = 0.54 kg
B17: Motor gasoline | C17: litre | D17: =D57*$G$57*10^-6 | E17: =E57*$G$57*10^-6 | F17: =F57*$G$57*10^-6 | G17: =D17+(E17*$K$5)+(F17*$K$6) | H17: IPCC Vol.2 table 2.2, DEDE
A19: Mobile Combustion (On road)
B20: Motor Gasoline - uncontrolled | C20: litre | D20: =D63*$G$63*10^-6 | E20: =E63*$G$63*10^-6 | F20: =F63*$G$63*10^-6 | G20: =D20+(E20*$K$5)+(F20*$K$6) | H20: IPCC Vol.2 table 3.2.1, 3.2.2, DEDE
B21: Motor Gasoline - oxydation catalyst | C21: litre | D21: =D64*$G$64*10^-6 | E21: =E64*$G$64*10^-6 | F21: =F64*$G$64*10^-6 | G21: =D21+(E21*$K$5)+(F21*$K$6) | H21: IPCC Vol.2 table 3.2.1, 3.2.2, DEDE
B22: Motor Gasoline - low mileage light duty vihicle vintage 1995 or later | C22: litre | D22: =D65*$G$65*10^-6 | E22: =E65*$G$65*10^-6 | F22: =F65*$G$65*10^-6 | G22: =D22+(E22*$K$5)+(F22*$K$6) | H22: IPCC Vol.2 table 3.2.1, 3.2.2, DEDE
B23: Gas/ Diesel Oil | C23: litre | D23: =D66*$G$66*10^-6 | E23: =E66*$G$66*10^-6 | F23: =F66*$G$66*10^-6 | G23: =D23+(E23*$K$5)+(F23*$K$6) | H23: IPCC Vol.2 table 3.2.1, 3.2.2, DEDE
B24: Compressed Natural Gas | C24: kg | D24: =D67*$G$67*10^-6 | E24: =E67*$G$67*10^-6 | F24: =F67*$G$67*10^-6 | G24: =D24+(E24*$K$5)+(F24*$K$6) | H24: IPCC Vol.2 table 3.2.1, 3.2.2, PTT
B25: Liquified Petroleum Gas | C25: litre | D25: =D68*$G$68*10^-6 | E25: =E68*$G$68*10^-6 | F25: =F68*$G$68*10^-6 | G25: =D25+(E25*$K$5)+(F25*$K$6) | H25: IPCC Vol.2 table 3.2.1, 3.2.2, DEDE
B26: Liquified Petroleum Gas | C26: kg | D26: =D25/0.54 | E26: =E25/0.54 | F26: =F25/0.54 | G26: =D26+(E26*$K$5)+(F26*$K$6) | H26: IPCC Vol.2 table 3.2.1, 3.2.2, DEDE LPG 1 litre = 0.54 kg
A27: Mobile Combustion (Off road)
B28: Diesel
B29: - Agriculture | C29: litre | D29: =D75*$G$75/(10^6) | E29: =E75*$G$75/(10^6) | F29: =F75*$G$75/(10^6) | G29: =D29+(E29*$K$5)+(F29*$K$6) | H29: IPCC Vol.2 table 3.3.1, DEDE
B30: - Forestry | C30: litre | D30: =D76*$G$76/(10^6) | E30: =E76*$G$76/(10^6) | F30: =F76*$G$76/(10^6) | G30: =D30+(E30*$K$5)+(F30*$K$6) | H30: IPCC Vol.2 table 3.3.1, DEDE
B31: - Industry | C31: litre | D31: =D77*$G$77/(10^6) | E31: =E77*$G$77/(10^6) | F31: =F77*$G$77/(10^6) | G31: =D31+(E31*$K$5)+(F31*$K$6) | H31: IPCC Vol.2 table 3.3.1, DEDE
B32: - Household | C32: litre | D32: =D78*$G$78/(10^6) | E32: =E78*$G$78/(10^6) | F32: =F78*$G$78/(10^6) | G32: =D32+(E32*$K$5)+(F32*$K$6) | H32: IPCC Vol.2 table 3.3.1, DEDE
B33: Motor Gasoline - 4 stroke
B34: - Agriculture | C34: litre | D34: =D80*$G$80/(10^6) | E34: =E80*$G$80/(10^6) | F34: =F80*$G$80/(10^6) | G34: =D34+(E34*$K$5)+(F34*$K$6) | H34: IPCC Vol.2 table 3.3.1, DEDE
B35: - Forestry | C35: litre | D35: =D81*$G$81/(10^6) | E35: =E81*$G$81/(10^6) | F35: =F81*$G$81/(10^6) | G35: =D35+(E35*$K$5)+(F35*$K$6) | H35: IPCC Vol.2 table 3.3.1, DEDE
B36: - Industry | C36: litre | D36: =D82*$G$82/(10^6) | E36: =E82*$G$82/(10^6) | F36: =F82*$G$82/(10^6) | G36: =D36+(E36*$K$5)+(F36*$K$6) | H36: IPCC Vol.2 table 3.3.1, DEDE
B37: - Household | C37: litre | D37: =D83*$G$83/(10^6) | E37: =E83*$G$83/(10^6) | F37: =F83*$G$83/(10^6) | G37: =D37+(E37*$K$5)+(F37*$K$6) | H37: IPCC Vol.2 table 3.3.1, DEDE
B38: Motor Gasoline - 2 stroke
B39: - Agriculture | C39: litre | D39: =D85*$G$85/(10^6) | E39: =E85*$G$85/(10^6) | F39: =F85*$G$85/(10^6) | G39: =D39+(E39*$K$5)+(F39*$K$6) | H39: IPCC Vol.2 table 3.3.1, DEDE
B40: - Forestry | C40: litre | D40: =D86*$G$86/(10^6) | E40: =E86*$G$86/(10^6) | F40: =F86*$G$86/(10^6) | G40: =D40+(E40*$K$5)+(F40*$K$6) | H40: IPCC Vol.2 table 3.3.1, DEDE
B41: - Industry | C41: litre | D41: =D87*$G$87/(10^6) | E41: =E87*$G$87/(10^6) | F41: =F87*$G$87/(10^6) | G41: =D41+(E41*$K$5)+(F41*$K$6) | H41: IPCC Vol.2 table 3.3.1, DEDE
B42: - Household | C42: litre | D42: =D88*$G$88/(10^6) | E42: =E88*$G$88/(10^6) | F42: =F88*$G$88/(10^6) | G42: =D42+(E42*$K$5)+(F42*$K$6) | H42: IPCC Vol.2 table 3.3.1, DEDE
A44: Stationary Combustion
E45: IPCC | G45: DEDE
D46: [kg/TJ] | G46: [MJ/unit]
C47: unit | D47: CO2 | E47: CH4 | F47: N2O | G47: NCV
B48: Natural gas | C48: scf | D48: 56100 | E48: 1 | F48: 0.1 | G48: 1.02 | H48: dry basis
B49: Lignite | C49: kg | D49: 101000 | E49: 1 | F49: 1.5 | G49: 10.47
B50: Fuel oil A | C50: litre | D50: 77400 | E50: 3 | F50: 0.6 | G50: 41.468972 | H50: *ref. from PTT
B51: Fuel oil C | C51: litre | D51: 77400 | E51: 3 | F51: 0.6 | G51: 41.80026 | H51: *ref. from PTT
B52: Gas/Diesel oil | C52: litre | D52: 74100 | E52: 3 | F52: 0.6 | G52: 36.42
B53: Anthracite | C53: kg | D53: 98300 | E53: 1 | F53: 1.5 | G53: 31.4
B54: Sub-bituminous coal | C54: kg | D54: 96100 | E54: 1 | F54: 1.5 | G54: 26.37
B55: Jet Kerosene | C55: litre | D55: 71500 | E55: 3 | F55: 0.6 | G55: 34.53
B56: LPG | C56: litre | D56: 63100 | E56: 1 | F56: 0.1 | G56: 26.62
B57: Motor gasoline | C57: litre | D57: 69300 | E57: 3 | F57: 0.6 | G57: =G63
A59: Mobile Combustion (On road)
D60: IPCC | G60: DEDE
D61: [kg/TJ] | G61: [MJ/unit]
C62: unit | D62: CO2 | E62: CH4 | F62: N2O | G62: NCV
B63: Motor Gasoline - uncontrolled | C63: litre | D63: 69300 | E63: 33 | F63: 3.2 | G63: 31.48 | H63: gasoline
B64: Motor Gasoline -oxydation catalyst | C64: litre | D64: 69300 | E64: 25 | F64: 8 | G64: 31.48
B65: Motor Gasoline - low mileage light duty vihicle vintage 1995 or later | C65: litre | D65: 69300 | E65: 3.8 | F65: 5.7 | G65: 31.48
B66: Gas/ Diesel Oil | C66: litre | D66: 74100 | E66: 3.9 | F66: 3.9 | G66: =G52
B67: Compressed Natural Gas | C67: kg | D67: 56100 | E67: 92 | F67: 3 | G67: 37.9 | H67: *ref. from PTT
B68: Liquified Petroleum Gas | C68: litre | D68: 63100 | E68: 62 | F68: 0.2 | G68: =G56
A70: Mobile Combustion (Off road)
D71: IPCC | G71: DEDE
D72: [kg/TJ] | G72: [MJ/unit]
C73: unit | D73: CO2 | E73: CH4 | F73: N2O | G73: NCV
B74: Diesel
B75: - Agriculture | C75: litre | D75: 74100 | E75: 4.15 | F75: 28.6 | G75: 36.42
B76: - Forestry | C76: litre | D76: 74100 | E76: 4.15 | F76: 28.6 | G76: 36.42
B77: - Industry | C77: litre | D77: 74100 | E77: 4.15 | F77: 28.6 | G77: 36.42
B78: - Household | C78: litre | D78: 74100 | E78: 4.15 | F78: 28.6 | G78: 36.42
B79: Motor Gasoline - 4 stroke
B80: - Agriculture | C80: litre | D80: 69300 | E80: 80 | F80: 2 | G80: 31.48
B81: - Forestry | C81: litre | D81: 69300 | G81: 31.48
B82: - Industry | C82: litre | D82: 69300 | E82: 50 | F82: 2 | G82: 31.48
B83: - Household | C83: litre | D83: 69300 | E83: 120 | F83: 2 | G83: 31.48
B84: Motor Gasoline - 2 stroke
B85: - Agriculture | C85: litre | D85: 69300 | E85: 140 | F85: 0.4 | G85: 31.48
B86: - Forestry | C86: litre | D86: 69300 | E86: 170 | F86: 0.4 | G86: 31.48
B87: - Industry | C87: litre | D87: 69300 | E87: 130 | F87: 0.4 | G87: 31.48
B88: - Household | C88: litre | D88: 69300 | E88: 180 | F88: 0.4 | G88: 31.48

Sheet EF TGO AR5
B2: ชื่อ | C2: Units | D2: EMISSION FACTORS | I2: แหล่งอ้างอิงข้อมูล | K2: GWP100
D3: CO2 | E3: Fossil CH4 | F3: CH4 | G3: N2O | H3: Total | K3: ที่มา | L3: IPCC, AR5
D4: [kg CO2/unit] | E4: [kg CH4/unit] | F4: [kg CH4/unit] | G4: [kg N2O/unit] | H4: [kg CO2eq/unit] | K4: CO2 | L4: 1
A5: Stationary Combustion | K5: Fossil CH4 | L5: 30
B6: Natural gas | C6: scf | D6: =D70*$G$70*10^-6 | E6: =E70*$G$70*10^-6 | G6: =F70*$G$70*10^-6 | H6: =D6+(E6*$L$5)+(G6*$L$7) | I6: IPCC Vol.2 table 2.2, DEDE | K6: CH4 | L6: 28
B7: Natural gas | C7: MJ | D7: =D70/1000000 | E7: =E70/1000000 | G7: =F70/1000000 | H7: =D7+(E7*$L$5)+(G7*$L$7) | I7: IPCC Vol.2 table 2.2, DEDE | K7: N2O | L7: 265
B8: Lignite | C8: kg | D8: =D71*$G$71*10^-6 | E8: =E71*$G$71*10^-6 | G8: =F71*$G$71*10^-6 | H8: =D8+(E8*$L$5)+(G8*$L$7) | I8: IPCC Vol.2 table 2.2, DEDE | K8: SF6 | L8: 23500
B9: Fuel oil A | C9: litre | D9: =D72*$G$72*10^-6 | E9: =E72*$G$72*10^-6 | G9: =F72*$G$72*10^-6 | H9: =D9+(E9*$L$5)+(G9*$L$7) | I9: IPCC Vol.2 table 2.2, PTT | K9: NF3 | L9: 16100
B10: Fuel oil C | C10: litre | D10: =D73*$G$73*10^-6 | E10: =E73*$G$73*10^-6 | G10: =F73*$G$73*10^-6 | H10: =D10+(E10*$L$5)+(G10*$L$7) | I10: IPCC Vol.2 table 2.2, PTT | K10: PASS: 12345678
B11: Gas/Diesel oil | C11: litre | D11: =D74*$G$74*10^-6 | E11: =E74*$G$74*10^-6 | G11: =F74*$G$74*10^-6 | H11: =D11+(E11*$L$5)+(G11*$L$7) | I11: IPCC Vol.2 table 2.2, DEDE
B12: Anthracite | C12: kg | D12: =D75*$G$75*10^-6 | E12: =E75*$G$75*10^-6 | G12: =F75*$G$75*10^-6 | H12: =D12+(E12*$L$5)+(G12*$L$7) | I12: IPCC Vol.2 table 2.2, DEDE
B13: Sub-bituminous coal | C13: kg | D13: =D76*$G$76*10^-6 | E13: =E76*$G$76*10^-6 | G13: =F76*$G$76*10^-6 | H13: =D13+(E13*$L$5)+(G13*$L$7) | I13: IPCC Vol.2 table 2.2, DEDE
B14: Jet Kerosene | C14: litre | D14: =D77*$G$77*10^-6 | E14: =E77*$G$77*10^-6 | G14: =F77*$G$77*10^-6 | H14: =D14+(E14*$L$5)+(G14*$L$7) | I14: IPCC Vol.2 table 2.2, DEDE
B15: LPG | C15: litre | D15: =D78*$G$78*10^-6 | E15: =E78*$G$78*10^-6 | G15: =F78*$G$78*10^-6 | H15: =D15+(E15*$L$5)+(G15*$L$7) | I15: IPCC Vol.2 table 2.2, DEDE
B16: LPG | C16: kg | D16: =D15/0.54 | E16: =E15/0.54 | G16: =G15/0.54 | H16: =D16+(E16*$L$5)+(G16*$L$7) | I16: IPCC Vol.2 table 2.2, DEDE LPG 1 litre = 0.54 kg
B17: Motor gasoline | C17: litre | D17: =D79*$G$79*10^-6 | E17: =E79*$G$79*10^-6 | G17: =F79*$G$79*10^-6 | H17: =D17+(E17*$L$5)+(G17*$L$7) | I17: IPCC Vol.2 table 2.2, DEDE
B18: FUEL WOOD | C18: kg | F18: =E80*$G$80*10^-6 | G18: =F80*$G$80*10^-6 | H18: =D18+(F18*$L$6)+(G18*$L$7) | I18: IPCC Vol.2 table 2.2, DEDE
B19: Bagasse | C19: kg | F19: =E82*$G$82*10^-6 | G19: =F82*$G$82*10^-6 | H19: =D19+(F19*$L$6)+(G19*$L$7) | I19: IPCC Vol.2 table 2.2, DEDE
B20: Palm kernel shell | C20: kg | F20: =E83*$G$83*10^-6 | G20: =F83*$G$83*10^-6 | H20: =D20+(F20*$L$6)+(G20*$L$7) | I20: IPCC Vol.2 table 2.2, DEDE
B21: Cob | C21: kg | F21: =E84*$G$84*10^-6 | G21: =F84*$G$84*10^-6 | H21: =D21+(F21*$L$6)+(G21*$L$7) | I21: IPCC Vol.2 table 2.2, DEDE
B22: Biogas | C22: m3 | F22: =E85*$G$85*10^-6 | G22: =F85*$G$85*10^-6 | H22: =D22+(F22*$L$6)+(G22*$L$7) | I22: IPCC Vol.2 table 2.2, DEDE
B23: FUEL WOOD (CO2only) | C23: kg | D23: =D80*$G$80*10^-6 | H23: =D23+(E23*$L$5)+(G23*$L$7) | I23: IPCC Vol.2 table 2.2, DEDE
B24: Bagasse (CO2only) | C24: kg | D24: =D82*$G$82*10^-6 | H24: =D24+(E24*$L$5)+(G24*$L$7) | I24: IPCC Vol.2 table 2.2, DEDE
B25: Palm kernel shell (CO2only) | C25: kg | D25: =D83*$G$83*10^-6 | H25: =D25+(E25*$L$5)+(G25*$L$7) | I25: IPCC Vol.2 table 2.2, DEDE
B26: Cob (CO2only) | C26: kg | D26: =D84*$G$84*10^-6 | H26: =D26+(E26*$L$5)+(G26*$L$7) | I26: IPCC Vol.2 table 2.2, DEDE
B27: Biogas (CO2only) | C27: m3 | D27: =D85*$G$85*10^-6 | H27: =D27+(E27*$L$5)+(G27*$L$7) | I27: IPCC Vol.2 table 2.2, DEDE
A28: Mobile Combustion (On road)
B29: Motor Gasoline - uncontrolled | C29: litre | D29: =D91*$G$91*10^-6 | E29: =E91*$G$91*10^-6 | G29: =F91*$G$91*10^-6 | H29: =D29+(E29*$L$5)+(G29*$L$7) | I29: IPCC Vol.2 table 3.2.1, 3.2.2, DEDE
B30: Motor Gasoline - oxydation catalyst | C30: litre | D30: =D92*$G$92*10^-6 | E30: =E92*$G$92*10^-6 | G30: =F92*$G$92*10^-6 | H30: =D30+(E30*$L$5)+(G30*$L$7) | I30: IPCC Vol.2 table 3.2.1, 3.2.2, DEDE
B31: Motor Gasoline - low mileage light duty vihicle vintage 1995 or later | C31: litre | D31: =D93*$G$93*10^-6 | E31: =E93*$G$93*10^-6 | G31: =F93*$G$93*10^-6 | H31: =D31+(E31*$L$5)+(G31*$L$7) | I31: IPCC Vol.2 table 3.2.1, 3.2.2, DEDE
B32: Gas/ Diesel Oil | C32: litre | D32: =D94*$G$94*10^-6 | E32: =E94*$G$94*10^-6 | G32: =F94*$G$94*10^-6 | H32: =D32+(E32*$L$5)+(G32*$L$7) | I32: IPCC Vol.2 table 3.2.1, 3.2.2, DEDE
B33: Compressed Natural Gas | C33: kg | D33: =D95*$G$95*10^-6 | E33: =E95*$G$95*10^-6 | G33: =F95*$G$95*10^-6 | H33: =D33+(E33*$L$5)+(G33*$L$7) | I33: IPCC Vol.2 table 3.2.1, 3.2.2, PTT
B34: Liquified Petroleum Gas | C34: litre | D34: =D96*$G$96*10^-6 | E34: =E96*$G$96*10^-6 | G34: =F96*$G$96*10^-6 | H34: =D34+(E34*$L$5)+(G34*$L$7) | I34: IPCC Vol.2 table 3.2.1, 3.2.2, DEDE
B35: Liquified Petroleum Gas | C35: kg | D35: =D34/0.54 | E35: =E34/0.54 | G35: =G34/0.54 | H35: =D35+(E35*$L$5)+(G35*$L$7) | I35: IPCC Vol.2 table 3.2.1, 3.2.2, DEDE LPG 1 litre = 0.54 kg
A36: Mobile Combustion (Off road)
B37: Diesel
B38: - Agriculture | C38: litre | D38: =D103*$G$103/(10^6) | E38: =E103*$G$103/(10^6) | G38: =F103*$G$103/(10^6) | H38: =D38+(E38*$L$5)+(G38*$L$7) | I38: IPCC Vol.2 table 3.3.1, DEDE
B39: - Forestry | C39: litre | D39: =D104*$G$104/(10^6) | E39: =E104*$G$104/(10^6) | G39: =F104*$G$104/(10^6) | H39: =D39+(E39*$L$5)+(G39*$L$7) | I39: IPCC Vol.2 table 3.3.1, DEDE
B40: - Industry | C40: litre | D40: =D105*$G$105/(10^6) | E40: =E105*$G$105/(10^6) | G40: =F105*$G$105/(10^6) | H40: =D40+(E40*$L$5)+(G40*$L$7) | I40: IPCC Vol.2 table 3.3.1, DEDE
B41: - Household | C41: litre | D41: =D106*$G$106/(10^6) | E41: =E106*$G$106/(10^6) | G41: =F106*$G$106/(10^6) | H41: =D41+(E41*$L$5)+(G41*$L$7) | I41: IPCC Vol.2 table 3.3.1, DEDE
B42: Motor Gasoline - 4 stroke
B43: - Agriculture | C43: litre | D43: =D108*$G$108/(10^6) | E43: =E108*$G$108/(10^6) | G43: =F108*$G$108/(10^6) | H43: =D43+(E43*$L$5)+(G43*$L$7) | I43: IPCC Vol.2 table 3.3.1, DEDE
B44: - Forestry | C44: litre | D44: =D109*$G$109/(10^6) | E44: =E109*$G$109/(10^6) | G44: =F109*$G$109/(10^6) | H44: =D44+(E44*$L$5)+(G44*$L$7) | I44: IPCC Vol.2 table 3.3.1, DEDE
B45: - Industry | C45: litre | D45: =D110*$G$110/(10^6) | E45: =E110*$G$110/(10^6) | G45: =F110*$G$110/(10^6) | H45: =D45+(E45*$L$5)+(G45*$L$7) | I45: IPCC Vol.2 table 3.3.1, DEDE
B46: - Household | C46: litre | D46: =D111*$G$111/(10^6) | E46: =E111*$G$111/(10^6) | G46: =F111*$G$111/(10^6) | H46: =D46+(E46*$L$5)+(G46*$L$7) | I46: IPCC Vol.2 table 3.3.1, DEDE
B47: Motor Gasoline - 2 stroke
B48: - Agriculture | C48: litre | D48: =D113*$G$113/(10^6) | E48: =E113*$G$113/(10^6) | G48: =F113*$G$113/(10^6) | H48: =D48+(E48*$L$5)+(G48*$L$7) | I48: IPCC Vol.2 table 3.3.1, DEDE
B49: - Forestry | C49: litre | D49: =D114*$G$114/(10^6) | E49: =E114*$G$114/(10^6) | G49: =F114*$G$114/(10^6) | H49: =D49+(E49*$L$5)+(G49*$L$7) | I49: IPCC Vol.2 table 3.3.1, DEDE
B50: - Industry | C50: litre | D50: =D115*$G$115/(10^6) | E50: =E115*$G$115/(10^6) | G50: =F115*$G$115/(10^6) | H50: =D50+(E50*$L$5)+(G50*$L$7) | I50: IPCC Vol.2 table 3.3.1, DEDE
B51: - Household | C51: litre | D51: =D116*$G$116/(10^6) | E51: =E116*$G$116/(10^6) | G51: =F116*$G$116/(10^6) | H51: =D51+(E51*$L$5)+(G51*$L$7) | I51: IPCC Vol.2 table 3.3.1, DEDE
A52: Electricity, grid mix (ไฟฟ้า)
B53: ไฟฟ้าแบบ grid mix ปี 2016-2018; LCIA method IPCC 2013 GWP 100a V1.03 | C53: kWh | D53: - | E53: - | F53: - | G53: - | H53: 0.4999 | I53: Thai National LCI Database, TIISMTEC-NSTDA, AR5 (with TGO electricity 2016-2018)
A54: Refrigerants (สารทำความเย็น)
B55: R-22 (HCFC-22) | C55: kg | D55: - | E55: - | F55: - | G55: - | H55: 1760 | I55: IPCC 2013, AR5
B56: R-32 | C56: kg | D56: - | E56: - | F56: - | G56: - | H56: 677 | I56: IPCC 2013, AR5
B57: R-125 | C57: kg | D57: - | E57: - | F57: - | G57: - | H57: 3170 | I57: IPCC 2013, AR5
B58: R-134 | C58: kg | D58: - | E58: - | F58: - | G58: - | H58: 1120 | I58: IPCC 2013, AR5
B59: R-134a | C59: kg | D59: - | E59: - | F59: - | G59: - | H59: 1300 | I59: IPCC 2013, AR5
B60: R-143 | C60: kg | D60: - | E60: - | F60: - | G60: - | H60: 328 | I60: IPCC 2013, AR5
B61: R-143a | C61: kg | D61: - | E61: - | F61: - | G61: - | H61: 4800 | I61: IPCC 2013, AR5
A63: ทั้งนี้สำหรับ Emission Factor ใน Scope 3 สามารถค้นหาได้ที่ | E63: http://thaicarbonlabel.tgo.or.th/products_emission/products_emission.pnc
A66: Stationary Combustion
E67: IPCC | G67: DEDE
D68: [kg/TJ] | G68: [MJ/unit]
C69: unit | D69: CO2 | E69: CH4 | F69: N2O | G69: NCV
B70: Natural gas | C70: scf | D70: 56100 | E70: 1 | F70: 0.1 | G70: 1.02 | H70: dry basis
B71: Lignite | C71: kg | D71: 101000 | E71: 1 | F71: 1.5 | G71: 10.47
B72: Residual fuel oil (Fuel oil A) | C72: litre | D72: 77400 | E72: 3 | F72: 0.6 | G72: 41.468972 | H72: *ref. from PTT
B73: Residual fuel oil (Fuel oil C) | C73: litre | D73: 77400 | E73: 3 | F73: 0.6 | G73: 41.80026 | H73: *ref. from PTT
B74: Gas/Diesel oil | C74: litre | D74: 74100 | E74: 3 | F74: 0.6 | G74: 36.42
B75: Anthracite | C75: kg | D75: 98300 | E75: 1 | F75: 1.5 | G75: 31.4
B76: Sub-bituminous coal | C76: kg | D76: 96100 | E76: 1 | F76: 1.5 | G76: 26.37
B77: Jet Kerosene | C77: litre | D77: 71500 | E77: 3 | F77: 0.6 | G77: 34.53
B78: LPG | C78: litre | D78: 63100 | E78: 1 | F78: 0.1 | G78: 26.62
B79: Motor gasoline | C79: litre | D79: 69300 | E79: 3 | F79: 0.6 | G79: =G91
B80: Wood / Wood Waste (FUEL WOOD) | C80: kg | D80: 112000 | E80: 30 | F80: 4 | G80: 15.99
B81: Other Primary Solid Biomass
B82: Bagasse | C82: kg | D82: 100000 | E82: 30 | F82: 4 | G82: 7.53
B83: Palm kernel shell | C83: kg | D83: 100000 | E83: 30 | F83: 4 | G83: 18.53
B84: Cob | C84: kg | D84: 100000 | E84: 30 | F84: 4 | G84: 16.78
B85: Biogas | C85: m3 | D85: 54600 | E85: 1 | F85: 0.1 | G85: 20.93
A87: Mobile Combustion (On road)
D88: IPCC | G88: DEDE
D89: [kg/TJ] | G89: [MJ/unit]
C90: unit | D90: CO2 | E90: CH4 | F90: N2O | G90: NCV
B91: Motor Gasoline - uncontrolled | C91: litre | D91: 69300 | E91: 33 | F91: 3.2 | G91: 31.48 | H91: gasoline
B92: Motor Gasoline -oxydation catalyst | C92: litre | D92: 69300 | E92: 25 | F92: 8 | G92: 31.48
B93: Motor Gasoline - low mileage light duty vihicle vintage 1995 or later | C93: litre | D93: 69300 | E93: 3.8 | F93: 5.7 | G93: 31.48
B94: Gas/ Diesel Oil | C94: litre | D94: 74100 | E94: 3.9 | F94: 3.9 | G94: =G74
B95: Compressed Natural Gas | C95: kg | D95: 56100 | E95: 92 | F95: 3 | G95: 37.9 | H95: *ref. from PTT
B96: Liquified Petroleum Gas | C96: litre | D96: 63100 | E96: 62 | F96: 0.2 | G96: =G78
A98: Mobile Combustion (Off road)
D99: IPCC | G99: DEDE
D100: [kg/TJ] | G100: [MJ/unit]
C101: unit | D101: CO2 | E101: CH4 | F101: N2O | G101: NCV
B102: Diesel
B103: - Agriculture | C103: litre | D103: 74100 | E103: 4.15 | F103: 28.6 | G103: 36.42
B104: - Forestry | C104: litre | D104: 74100 | E104: 4.15 | F104: 28.6 | G104: 36.42
B105: - Industry | C105: litre | D105: 74100 | E105: 4.15 | F105: 28.6 | G105: 36.42
B106: - Household | C106: litre | D106: 74100 | E106: 4.15 | F106: 28.6 | G106: 36.42
...

Sheet EF (1)
A1: EF of Acetylene
B3: 2C2H2 + 5O2 " 4CO2 + 2H2O
B5: MW | C5: #mole
A6: C2H2 | B6: 26 | C6: 2
A7: CO2 | B7: 44 | C7: 4
A9: Efacetylene = | B9: =(B7*C7)/(B6*C6) | C9: kg CO2/Kg C2H2
A11: สารทำความเย็น
A12: สารทำความเย็น
A13: 1 | B13: R-123 | C13: HCFC-123 | D13: kg | E13: 79 | F13: IPCC-AR5 Report
A14: 2 | B14: R-32 | C14: HFC-32 | D14: kg | E14: 677 | F14: IPCC-AR5 Report
A15: 3 | B15: R-125 | C15: HFC-125 | D15: kg | E15: 3170 | F15: IPCC-AR5 Report
A16: 4 | B16: R410a | C16: HFC-32 (50%)/HFC-125 (50%) | D16: kg | E16: 1923.5 | F16: IPCC-AR5 Report
A17: 5 | B17: HFC-236fa | C17: HFC-236fa | D17: kg | E17: 8060 | F17: IPCC-AR5 Report
A18: 6 | B18: R-404a | C18: HFC-125 (44%)/HFC-143a (52%)/HFC-134a (4%) | D18: kg | E18: =(E15*44/100)+('[1]EF TGO AR5'!H61*52/100)+('[1]EF TGO AR5'!H59*4/100) | F18: IPCC-AR5 Report
A19: 7 | B19: R-407c | C19: HFC-32 (23%)/HFC-125 (25%)/HFC-134a (52%) | D19: kg | E19: =(E14*23/100)+(E15*25/100)+('[1]EF TGO AR5'!H59*52/100) | F19: IPCC-AR5 Report
A21: อ้างอิง | B21: https://ghgprotocol.org/sites/default/files/ghgp/Global-Warming-Potential-Values%20%28Feb%2016%202016%29_1.pdf
A23: Biogenic CO2
A26: การเผาไหม้ | B26: รายการ | C26: GHG emission (kg CO2/TJ) | F26: NCV (TJ/kg) | G26: อ้างอิง
C27: CO2 | D27: CH4 | E27: N2O
A28: Stationary combustion | B28: Biodiesel | C28: 70800 | D28: 3 | E28: 0.6 | F28: 2.7e-05 | G28: IPCC, 2006, Volume 2, Chapter 2 Table 2.2
B29: Biogasoline (Ethanol) | C29: 70800 | D29: 3 | E29: 0.6 | F29: 2.7e-05 | G29: IPCC, 2006, Volume 2, Chapter 2 Table 2.2
A30: Mobile combustion (on road) | B30: Biodiesel | C30: 70800 | D30: 4.15 | E30: 28.6 | F30: 2.7e-05 | G30: IPCC, 2006, Volume 2, Chapter 3 Table 3.3.1
B31: Ethanol | C31: 70800 | D31: 260 | E31: 41 | F31: 2.7e-05 | G31: IPCC, 2006, Volume 2, Chapter 3 Table 3.2.2
A32: Mobile combustion (off road) | B32: Biodiesel | C32: 70800 | D32: 4.15 | E32: 28.6 | F32: 2.7e-05 | G32: IPCC, 2006, Volume 2, Chapter 3 Table 3.3.1
A33: การเผาไหม้ | B33: รายการ | C33: CO2 emission (kgCO2/kg)
A34: Mobile combustion (on road) | B34: Biodiesel | C34: =9.45/(3.78541*0.88)
B35: Ethanol | C35: =5.75/(3.78541*0.79)
A36: Mobile combustion (off road) | B36: Biodiesel | C36: =9.45/(3.78541*0.88)
A38: อ้างอิง
A39: https://www.ipcc-nggip.iges.or.jp/public/2006gl/pdf/2_Volume2/V2_1_Ch1_Introduction.pdf
A40: https://www.ipcc-nggip.iges.or.jp/public/2006gl/pdf/2_Volume2/V2_2_Ch2_Stationary_Combustion.pdf
A41: https://www.ipcc-nggip.iges.or.jp/public/2006gl/pdf/2_Volume2/V2_3_Ch3_Mobile_Combustion.pdf
A42: https://www.epa.gov/system/files/documents/2024-02/ghg-emission-factors-hub-2024.pdf
A113: EF of Ethanol
B115: C2H5OH + 3O2 " 2CO2 + 3H2O
B117: MW | C117: #mole
A118: C2H5OH | B118: 46 | C118: 1
A119: CO2 | B119: 44 | C119: 2
A121: Ethanol = | B121: =(B119*C119)/(B118*C118) | C121: kg CO2/Kg C2H5OH

Sheet บันทึกการปรับปรุง
A1: บันทึกการแก้ไข
A2: วันที่ | B2: ลำดับ | C2: Sheet | D2: Cell | E2: รายละเอียด | F2: ผู้ทำการแก้ไข
A4: 241864 | B4: 1 | C4: Fr-04 | D4: AM,AN,AO | E4: เพิ่มการคำนวณสัดส่วน (%) | F4: มนต์ชัย จิตติปัญญากุล
A5: 241864 | B5: 2 | C5: Fr-05 | D5: C10-C13 | E5: ลบสูตร Round up | F5: มนต์ชัย จิตติปัญญากุล
A6: 241864 | B6: 3 | C6: Fr-05 | D6: B15 | E6: เพิ่มการคำนวณรวม Scope 1 & 2 & 3 | F6: มนต์ชัย จิตติปัญญากุล
A7: 241864 | B7: 4 | C7: TGO_EF | E7: เพิ่ม EF Gasoline Stationary Combustion | F7: มนต์ชัย จิตติปัญญากุล
A8: 242229 | B8: 5 | C8: TGO_EF | E8: เพิ่ม Sheet EF TGO AR5 | F8: มนต์ชัย จิตติปัญญากุล
A9: 242229 | B9: 6 | C9: Fr-04 | E9: แก้ไขสูตรการคำนวณให้ใช้ GWP AR5 | F9: มนต์ชัย จิตติปัญญากุล
A10: 242355 | B10: 7 | C10: Fr-05 | E10: ใส่สูตร Roundup ในแต่ละ SCOPE | F10: มนต์ชัย จิตติปัญญากุล
A11: 242433 | B11: 8 | C11: TGO_EF | E11: เพิ่ม EF ไฟฟ้า และสารทำความเย็น | F11: มนต์ชัย จิตติปัญญากุล
A12: 242433 | B12: 9 | C12: Fr-01 Fr-05 | E12: เพิ่ม การคำนวณ Carbon Intensity | F12: มนต์ชัย จิตติปัญญากุล
A13: 242783 | B13: 10 | C13: Fr-01, Fr-04.2, Fr-05 | E13: เพิ่ม การคำนวณปีฐาน | F13: มนต์ชัย จิตติปัญญากุล
A14: 242783 | B14: 11 | C14: EF TGO AR5 | E14: เพิ่ม EF Biomass | F14: มนต์ชัย จิตติปัญญากุล
A15: 242783 | B15: 12 | C15: Fr-03.2 | E15: เพิ่ม Fr-03.2 ประเมินความมีนัยสำคัญของการปล่อยก๊าซเรือนกระจกทางอ้อม (SCOPE 3) | F15: มนต์ชัย จิตติปัญญากุล
A16: 242879 | B16: 13 | C16: EF TGO AR5 | E16: เพิ่มค่า GWP Fossil CH4 และแก้ไขการคำนวณ EF การเผาไหม้เชื้อเพลิงฟอสซิล | F16: มนต์ชัย จิตติปัญญากุล
A17: 242879 | B17: 14 | C17: Fr-04.1 | E17: เพิ่มค่า GWP Fossil CH4 และแก้ไขการคำนวณ Total (kgCO2e/หน่วย) | F17: มนต์ชัย จิตติปัญญากุล
A18: 243016 | B18: 15 | C18: Fr-04.1 | E18: เพิ่มคอลัมน์ Fossil CH4 | F18: มนต์ชัย จิตติปัญญากุล
... A20: 243016 | B20: 17 | C20: EF TGO AR5 | E20: เพิ่มคอลัมน์ Fossil CH4 | F20: มนต์ชัย จิตติปัญญากุล

Sheet 1.1 Stationary
A1: Stationary combustion
A2: รายการ | C2: ชนิด | D2: หลักฐาน | E2: หน่วย | F2: ปริมาณน้ำมัน | G2: Diesel | H2: Biodiesel | J2: Gasoline | K2: Ethanol
G3: L | H3: L | I3: kg | J3: L | K3: L | L3: kg
A4: =A9 | C4: B7 | D4: =B9 | E4: L | F4: =D9 | G4: =F4*0.93 | H4: =F4-G4 | I4: =H4*0.87
A5: =A10 | C5: 91/95 | D5: =B10 | E5: L | F5: =D10 | J5: =F5*0.9 | K5: =F5-J5 | L5: =K5*0.79
A7: รายการ | B7: หลักฐาน | C7: หน่วย | D7: รวม | E7: ปริมาณการใช้แต่ละเดือน/2566
E8: 1 | F8: 2 | G8: 3 | H8: 4 | I8: 5 | J8: 6 | K8: 7 | L8: 8 | M8: 9 | N8: 10 | O8: 11 | P8: 12
A9: =IFERROR(INDEX(tblScope11Stationary[ItemLabel],MATCH("DIESEL_B7_STATIONARY",tblScope11Stationary[RowId],0)),"") | B9: =IFERROR(INDEX(tblScope11Stationary[Evidence],MATCH("DIESEL_B7_STATIONARY",tblScope11Stationary[RowId],0)),"") | C9: =IFERROR(INDEX(tblScope11Stationary[Unit],MATCH("DIESEL_B7_STATIONARY",tblScope11Stationary[RowId],0)),"") | D9: =IF(A9="","",SUM(E9:P9)) | E9: =IFERROR(INDEX(tblScope11Stationary[M1],MATCH("DIESEL_B7_STATIONARY",tblScope11Stationary[RowId],0)),"") | F9: =IFERROR(INDEX(tblScope11Stationary[M2],MATCH("DIESEL_B7_STATIONARY",tblScope11Stationary[RowId],0)),"") | G9: =IFERROR(INDEX(tblScope11Stationary[M3],MATCH("DIESEL_B7_STATIONARY",tblScope11Stationary[RowId],0)),"") | H9: =IFERROR(INDEX(tblScope11Stationary[M4],MATCH("DIESEL_B7_STATIONARY",tblScope11Stationary[RowId],0)),"") | I9: =IFERROR(INDEX(tblScope11Stationary[M5],MATCH("DIESEL_B7_STATIONARY",tblScope11Stationary[RowId],0)),"") | J9: =IFERROR(INDEX(tblScope11Stationary[M6],MATCH("DIESEL_B7_STATIONARY",tblScope11Stationary[RowId],0)),"") | K9: =IFERROR(INDEX(tblScope11Stationary[M7],MATCH("DIESEL_B7_STATIONARY",tblScope11Stationary[RowId],0)),"") | L9: =IFERROR(INDEX(tblScope11Stationary[M8],MATCH("DIESEL_B7_STATIONARY",tblScope11Stationary[RowId],0)),"") | M9: =IFERROR(INDEX(tblScope11Stationary[M9],MATCH("DIESEL_B7_STATIONARY",tblScope11Stationary[RowId],0)),"") | N9: =IFERROR(INDEX(tblScope11Stationary[M10],MATCH("DIESEL_B7_STATIONARY",tblScope11Stationary[RowId],0)),"") | O9: =IFERROR(INDEX(tblScope11Stationary[M11],MATCH("DIESEL_B7_STATIONARY",tblScope11Stationary[RowId],0)),"") | P9: =IFERROR(INDEX(tblScope11Stationary[M12],MATCH("DIESEL_B7_STATIONARY",tblScope11Stationary[RowId],0)),"")
A10: =IFERROR(INDEX(tblScope11Stationary[ItemLabel],MATCH("GASOHOL_9195_STATIONARY",tblScope11Stationary[RowId],0)),"") | B10: =IFERROR(INDEX(tblScope11Stationary[Evidence],MATCH("GASOHOL_9195_STATIONARY",tblScope11Stationary[RowId],0)),"") | C10: =IFERROR(INDEX(tblScope11Stationary[Unit],MATCH("GASOHOL_9195_STATIONARY",tblScope11Stationary[RowId],0)),"") | D10: =IF(A10="","",SUM(E10:P10)) | E10: =IFERROR(INDEX(tblScope11Stationary[M1],MATCH("GASOHOL_9195_STATIONARY",tblScope11Stationary[RowId],0)),"") | F10: =IFERROR(INDEX(tblScope11Stationary[M2],MATCH("GASOHOL_9195_STATIONARY",tblScope11Stationary[RowId],0)),"") | G10: =IFERROR(INDEX(tblScope11Stationary[M3],MATCH("GASOHOL_9195_STATIONARY",tblScope11Stationary[RowId],0)),"") | H10: =IFERROR(INDEX(tblScope11Stationary[M4],MATCH("GASOHOL_9195_STATIONARY",tblScope11Stationary[RowId],0)),"") | I10: =IFERROR(INDEX(tblScope11Stationary[M5],MATCH("GASOHOL_9195_STATIONARY",tblScope11Stationary[RowId],0)),"") | J10: =IFERROR(INDEX(tblScope11Stationary[M6],MATCH("GASOHOL_9195_STATIONARY",tblScope11Stationary[RowId],0)),"") | K10: =IFERROR(INDEX(tblScope11Stationary[M7],MATCH("GASOHOL_9195_STATIONARY",tblScope11Stationary[RowId],0)),"") | L10: =IFERROR(INDEX(tblScope11Stationary[M8],MATCH("GASOHOL_9195_STATIONARY",tblScope11Stationary[RowId],0)),"") | M10: =IFERROR(INDEX(tblScope11Stationary[M9],MATCH("GASOHOL_9195_STATIONARY",tblScope11Stationary[RowId],0)),"") | N10: =IFERROR(INDEX(tblScope11Stationary[M10],MATCH("GASOHOL_9195_STATIONARY",tblScope11Stationary[RowId],0)),"") | O10: =IFERROR(INDEX(tblScope11Stationary[M11],MATCH("GASOHOL_9195_STATIONARY",tblScope11Stationary[RowId],0)),"") | P10: =IFERROR(INDEX(tblScope11Stationary[M12],MATCH("GASOHOL_9195_STATIONARY",tblScope11Stationary[RowId],0)),"")
A11: =IF(OR(A12<>"",A14<>""),"Acetylene Gas (?????????)","") | B11: ใบกำกับภาษี | C11: =IF(A11="","","kg") | D11: =IF(A11="","",D13+D15)
A12: =IFERROR(INDEX(tblScope11Stationary[ItemLabel],MATCH("ACETYLENE_TANK5_MAINT_2",tblScope11Stationary[RowId],0)),"") | B12: =IFERROR(INDEX(tblScope11Stationary[Evidence],MATCH("ACETYLENE_TANK5_MAINT_2",tblScope11Stationary[RowId],0)),"") | C12: =IFERROR(INDEX(tblScope11Stationary[Unit],MATCH("ACETYLENE_TANK5_MAINT_2",tblScope11Stationary[RowId],0)),"") | D12: =IF(A12="","",SUM(E12:P12)) | E12: =IFERROR(INDEX(tblScope11Stationary[M1],MATCH("ACETYLENE_TANK5_MAINT_2",tblScope11Stationary[RowId],0)),"") | F12: =IFERROR(INDEX(tblScope11Stationary[M2],MATCH("ACETYLENE_TANK5_MAINT_2",tblScope11Stationary[RowId],0)),"") | G12: =IFERROR(INDEX(tblScope11Stationary[M3],MATCH("ACETYLENE_TANK5_MAINT_2",tblScope11Stationary[RowId],0)),"") | H12: =IFERROR(INDEX(tblScope11Stationary[M4],MATCH("ACETYLENE_TANK5_MAINT_2",tblScope11Stationary[RowId],0)),"") | I12: =IFERROR(INDEX(tblScope11Stationary[M5],MATCH("ACETYLENE_TANK5_MAINT_2",tblScope11Stationary[RowId],0)),"") | J12: =IFERROR(INDEX(tblScope11Stationary[M6],MATCH("ACETYLENE_TANK5_MAINT_2",tblScope11Stationary[RowId],0)),"") | K12: =IFERROR(INDEX(tblScope11Stationary[M7],MATCH("ACETYLENE_TANK5_MAINT_2",tblScope11Stationary[RowId],0)),"") | L12: =IFERROR(INDEX(tblScope11Stationary[M8],MATCH("ACETYLENE_TANK5_MAINT_2",tblScope11Stationary[RowId],0)),"") | M12: =IFERROR(INDEX(tblScope11Stationary[M9],MATCH("ACETYLENE_TANK5_MAINT_2",tblScope11Stationary[RowId],0)),"") | N12: =IFERROR(INDEX(tblScope11Stationary[M10],MATCH("ACETYLENE_TANK5_MAINT_2",tblScope11Stationary[RowId],0)),"") | O12: =IFERROR(INDEX(tblScope11Stationary[M11],MATCH("ACETYLENE_TANK5_MAINT_2",tblScope11Stationary[RowId],0)),"") | P12: =IFERROR(INDEX(tblScope11Stationary[M12],MATCH("ACETYLENE_TANK5_MAINT_2",tblScope11Stationary[RowId],0)),"")
C13: kg | D13: =IF(A12="","",SUM(E13:P13)) | E13: =IF(A12="","",E12*5) | F13: =IF(A12="","",F12*5) | G13: =IF(A12="","",G12*5) | H13: =IF(A12="","",H12*5) | I13: =IF(A12="","",I12*5) | J13: =IF(A12="","",J12*5) | K13: =IF(A12="","",K12*5) | L13: =IF(A12="","",L12*5) | M13: =IF(A12="","",M12*5) | N13: =IF(A12="","",N12*5) | O13: =IF(A12="","",O12*5) | P13: =IF(A12="","",P12*5)
A14: =IFERROR(INDEX(tblScope11Stationary[ItemLabel],MATCH("ACETYLENE_TANK5_MAINT_3",tblScope11Stationary[RowId],0)),"") | B14: =IFERROR(INDEX(tblScope11Stationary[Evidence],MATCH("ACETYLENE_TANK5_MAINT_3",tblScope11Stationary[RowId],0)),"") | C14: =IFERROR(INDEX(tblScope11Stationary[Unit],MATCH("ACETYLENE_TANK5_MAINT_3",tblScope11Stationary[RowId],0)),"") | D14: =IF(A14="","",SUM(E14:P14)) | E14: =IFERROR(INDEX(tblScope11Stationary[M1],MATCH("ACETYLENE_TANK5_MAINT_3",tblScope11Stationary[RowId],0)),"") | F14: =IFERROR(INDEX(tblScope11Stationary[M2],MATCH("ACETYLENE_TANK5_MAINT_3",tblScope11Stationary[RowId],0)),"") | G14: =IFERROR(INDEX(tblScope11Stationary[M3],MATCH("ACETYLENE_TANK5_MAINT_3",tblScope11Stationary[RowId],0)),"") | H14: =IFERROR(INDEX(tblScope11Stationary[M4],MATCH("ACETYLENE_TANK5_MAINT_3",tblScope11Stationary[RowId],0)),"") | I14: =IFERROR(INDEX(tblScope11Stationary[M5],MATCH("ACETYLENE_TANK5_MAINT_3",tblScope11Stationary[RowId],0)),"") | J14: =IFERROR(INDEX(tblScope11Stationary[M6],MATCH("ACETYLENE_TANK5_MAINT_3",tblScope11Stationary[RowId],0)),"") | K14: =IFERROR(INDEX(tblScope11Stationary[M7],MATCH("ACETYLENE_TANK5_MAINT_3",tblScope11Stationary[RowId],0)),"") | L14: =IFERROR(INDEX(tblScope11Stationary[M8],MATCH("ACETYLENE_TANK5_MAINT_3",tblScope11Stationary[RowId],0)),"") | M14: =IFERROR(INDEX(tblScope11Stationary[M9],MATCH("ACETYLENE_TANK5_MAINT_3",tblScope11Stationary[RowId],0)),"") | N14: =IFERROR(INDEX(tblScope11Stationary[M10],MATCH("ACETYLENE_TANK5_MAINT_3",tblScope11Stationary[RowId],0)),"") | O14: =IFERROR(INDEX(tblScope11Stationary[M11],MATCH("ACETYLENE_TANK5_MAINT_3",tblScope11Stationary[RowId],0)),"") | P14: =IFERROR(INDEX(tblScope11Stationary[M12],MATCH("ACETYLENE_TANK5_MAINT_3",tblScope11Stationary[RowId],0)),"")
C15: Kg | D15: =IF(A14="","",SUM(E15:P15)) | E15: =IF(A14="","",E14*5) | F15: =IF(A14="","",F14*5) | G15: =IF(A14="","",G14*5) | H15: =IF(A14="","",H14*5) | I15: =IF(A14="","",I14*5) | J15: =IF(A14="","",J14*5) | K15: =IF(A14="","",K14*5) | L15: =IF(A14="","",L14*5) | M15: =IF(A14="","",M14*5) | N15: =IF(A14="","",N14*5) | O15: =IF(A14="","",O14*5) | P15: =IF(A14="","",P14*5)
A17: =IFERROR(INDEX(tblScope11Stationary[ItemLabel],ROW()-12),"") | B17: =IFERROR(INDEX(tblScope11Stationary[Evidence],ROW()-12),"") | C17: =IFERROR(INDEX(tblScope11Stationary[Unit],ROW()-12),"") | D17: =IF(A17="","",SUM(E17:P17)) | E17: =IFERROR(INDEX(tblScope11Stationary[M1],ROW()-12),"") | F17: =IFERROR(INDEX(tblScope11Stationary[M2],ROW()-12),"") | G17: =IFERROR(INDEX(tblScope11Stationary[M3],ROW()-12),"") | H17: =IFERROR(INDEX(tblScope11Stationary[M4],ROW()-12),"") | I17: =IFERROR(INDEX(tblScope11Stationary[M5],ROW()-12),"") | J17: =IFERROR(INDEX(tblScope11Stationary[M6],ROW()-12),"") | K17: =IFERROR(INDEX(tblScope11Stationary[M7],ROW()-12),"") | L17: =IFERROR(INDEX(tblScope11Stationary[M8],ROW()-12),"") | M17: =IFERROR(INDEX(tblScope11Stationary[M9],ROW()-12),"") | N17: =IFERROR(INDEX(tblScope11Stationary[M10],ROW()-12),"") | O17: =IFERROR(INDEX(tblScope11Stationary[M11],ROW()-12),"") | P17: =IFERROR(INDEX(tblScope11Stationary[M12],ROW()-12),"")
A18: =IFERROR(INDEX(tblScope11Stationary[ItemLabel],ROW()-12),"") | B18: =IFERROR(INDEX(tblScope11Stationary[Evidence],ROW()-12),"") | C18: =IFERROR(INDEX(tblScope11Stationary[Unit],ROW()-12),"") | D18: =IF(A18="","",SUM(E18:P18)) | E18: =IFERROR(INDEX(tblScope11Stationary[M1],ROW()-12),"") | F18: =IFERROR(INDEX(tblScope11Stationary[M2],ROW()-12),"") | G18: =IFERROR(INDEX(tblScope11Stationary[M3],ROW()-12),"") | H18: =IFERROR(INDEX(tblScope11Stationary[M4],ROW()-12),"") | I18: =IFERROR(INDEX(tblScope11Stationary[M5],ROW()-12),"") | J18: =IFERROR(INDEX(tblScope11Stationary[M6],ROW()-12),"") | K18: =IFERROR(INDEX(tblScope11Stationary[M7],ROW()-12),"") | L18: =IFERROR(INDEX(tblScope11Stationary[M8],ROW()-12),"") | M18: =IFERROR(INDEX(tblScope11Stationary[M9],ROW()-12),"") | N18: =IFERROR(INDEX(tblScope11Stationary[M10],ROW()-12),"") | O18: =IFERROR(INDEX(tblScope11Stationary[M11],ROW()-12),"") | P18: =IFERROR(INDEX(tblScope11Stationary[M12],ROW()-12),"")
A19: =IFERROR(INDEX(tblScope11Stationary[ItemLabel],ROW()-12),"") | B19: =IFERROR(INDEX(tblScope11Stationary[Evidence],ROW()-12),"") | C19: =IFERROR(INDEX(tblScope11Stationary[Unit],ROW()-12),"") | D19: =IF(A19="","",SUM(E19:P19)) | E19: =IFERROR(INDEX(tblScope11Stationary[M1],ROW()-12),"") | F19: =IFERROR(INDEX(tblScope11Stationary[M2],ROW()-12),"") | G19: =IFERROR(INDEX(tblScope11Stationary[M3],ROW()-12),"") | H19: =IFERROR(INDEX(tblScope11Stationary[M4],ROW()-12),"") | I19: =IFERROR(INDEX(tblScope11Stationary[M5],ROW()-12),"") | J19: =IFERROR(INDEX(tblScope11Stationary[M6],ROW()-12),"") | K19: =IFERROR(INDEX(tblScope11Stationary[M7],ROW()-12),"") | L19: =IFERROR(INDEX(tblScope11Stationary[M8],ROW()-12),"") | M19: =IFERROR(INDEX(tblScope11Stationary[M9],ROW()-12),"") | N19: =IFERROR(INDEX(tblScope11Stationary[M10],ROW()-12),"") | O19: =IFERROR(INDEX(tblScope11Stationary[M11],ROW()-12),"") | P19: =IFERROR(INDEX(tblScope11Stationary[M12],ROW()-12),"")
A20: =IFERROR(INDEX(tblScope11Stationary[ItemLabel],ROW()-12),"") | B20: =IFERROR(INDEX(tblScope11Stationary[Evidence],ROW()-12),"") | C20: =IFERROR(INDEX(tblScope11Stationary[Unit],ROW()-12),"") | D20: =IF(A20="","",SUM(E20:P20)) | E20: =IFERROR(INDEX(tblScope11Stationary[M1],ROW()-12),"") | F20: =IFERROR(INDEX(tblScope11Stationary[M2],ROW()-12),"") | G20: =IFERROR(INDEX(tblScope11Stationary[M3],ROW()-12),"") | H20: =IFERROR(INDEX(tblScope11Stationary[M4],ROW()-12),"") | I20: =IFERROR(INDEX(tblScope11Stationary[M5],ROW()-12),"") | J20: =IFERROR(INDEX(tblScope11Stationary[M6],ROW()-12),"") | K20: =IFERROR(INDEX(tblScope11Stationary[M7],ROW()-12),"") | L20: =IFERROR(INDEX(tblScope11Stationary[M8],ROW()-12),"") | M20: =IFERROR(INDEX(tblScope11Stationary[M9],ROW()-12),"") | N20: =IFERROR(INDEX(tblScope11Stationary[M10],ROW()-12),"") | O20: =IFERROR(INDEX(tblScope11Stationary[M11],ROW()-12),"") | P20: =IFERROR(INDEX(tblScope11Stationary[M12],ROW()-12),"")
A21: =IFERROR(INDEX(tblScope11Stationary[ItemLabel],ROW()-12),"") | B21: =IFERROR(INDEX(tblScope11Stationary[Evidence],ROW()-12),"") | C21: =IFERROR(INDEX(tblScope11Stationary[Unit],ROW()-12),"") | D21: =IF(A21="","",SUM(E21:P21)) | E21: =IFERROR(INDEX(tblScope11Stationary[M1],ROW()-12),"") | F21: =IFERROR(INDEX(tblScope11Stationary[M2],ROW()-12),"") | G21: =IFERROR(INDEX(tblScope11Stationary[M3],ROW()-12),"") | H21: =IFERROR(INDEX(tblScope11Stationary[M4],ROW()-12),"") | I21: =IFERROR(INDEX(tblScope11Stationary[M5],ROW()-12),"") | J21: =IFERROR(INDEX(tblScope11Stationary[M6],ROW()-12),"") | K21: =IFERROR(INDEX(tblScope11Stationary[M7],ROW()-12),"") | L21: =IFERROR(INDEX(tblScope11Stationary[M8],ROW()-12),"") | M21: =IFERROR(INDEX(tblScope11Stationary[M9],ROW()-12),"") | N21: =IFERROR(INDEX(tblScope11Stationary[M10],ROW()-12),"") | O21: =IFERROR(INDEX(tblScope11Stationary[M11],ROW()-12),"") | P21: =IFERROR(INDEX(tblScope11Stationary[M12],ROW()-12),"")
A22: =IFERROR(INDEX(tblScope11Stationary[ItemLabel],ROW()-12),"") | B22: =IFERROR(INDEX(tblScope11Stationary[Evidence],ROW()-12),"") | C22: =IFERROR(INDEX(tblScope11Stationary[Unit],ROW()-12),"") | D22: =IF(A22="","",SUM(E22:P22)) | E22: =IFERROR(INDEX(tblScope11Stationary[M1],ROW()-12),"") | F22: =IFERROR(INDEX(tblScope11Stationary[M2],ROW()-12),"") | G22: =IFERROR(INDEX(tblScope11Stationary[M3],ROW()-12),"") | H22: =IFERROR(INDEX(tblScope11Stationary[M4],ROW()-12),"") | I22: =IFERROR(INDEX(tblScope11Stationary[M5],ROW()-12),"") | J22: =IFERROR(INDEX(tblScope11Stationary[M6],ROW()-12),"") | K22: =IFERROR(INDEX(tblScope11Stationary[M7],ROW()-12),"") | L22: =IFERROR(INDEX(tblScope11Stationary[M8],ROW()-12),"") | M22: =IFERROR(INDEX(tblScope11Stationary[M9],ROW()-12),"") | N22: =IFERROR(INDEX(tblScope11Stationary[M10],ROW()-12),"") | O22: =IFERROR(INDEX(tblScope11Stationary[M11],ROW()-12),"") | P22: =IFERROR(INDEX(tblScope11Stationary[M12],ROW()-12),"")
A23: =IFERROR(INDEX(tblScope11Stationary[ItemLabel],ROW()-12),"") | B23: =IFERROR(INDEX(tblScope11Stationary[Evidence],ROW()-12),"") | C23: =IFERROR(INDEX(tblScope11Stationary[Unit],ROW()-12),"") | D23: =IF(A23="","",SUM(E23:P23)) | E23: =IFERROR(INDEX(tblScope11Stationary[M1],ROW()-12),"") | F23: =IFERROR(INDEX(tblScope11Stationary[M2],ROW()-12),"") | G23: =IFERROR(INDEX(tblScope11Stationary[M3],ROW()-12),"") | H23: =IFERROR(INDEX(tblScope11Stationary[M4],ROW()-12),"") | I23: =IFERROR(INDEX(tblScope11Stationary[M5],ROW()-12),"") | J23: =IFERROR(INDEX(tblScope11Stationary[M6],ROW()-12),"") | K23: =IFERROR(INDEX(tblScope11Stationary[M7],ROW()-12),"") | L23: =IFERROR(INDEX(tblScope11Stationary[M8],ROW()-12),"") | M23: =IFERROR(INDEX(tblScope11Stationary[M9],ROW()-12),"") | N23: =IFERROR(INDEX(tblScope11Stationary[M10],ROW()-12),"") | O23: =IFERROR(INDEX(tblScope11Stationary[M11],ROW()-12),"") | P23: =IFERROR(INDEX(tblScope11Stationary[M12],ROW()-12),"")
A24: =IFERROR(INDEX(tblScope11Stationary[ItemLabel],ROW()-12),"") | B24: =IFERROR(INDEX(tblScope11Stationary[Evidence],ROW()-12),"") | C24: =IFERROR(INDEX(tblScope11Stationary[Unit],ROW()-12),"") | D24: =IF(A24="","",SUM(E24:P24)) | E24: =IFERROR(INDEX(tblScope11Stationary[M1],ROW()-12),"") | F24: =IFERROR(INDEX(tblScope11Stationary[M2],ROW()-12),"") | G24: =IFERROR(INDEX(tblScope11Stationary[M3],ROW()-12),"") | H24: =IFERROR(INDEX(tblScope11Stationary[M4],ROW()-12),"") | I24: =IFERROR(INDEX(tblScope11Stationary[M5],ROW()-12),"") | J24: =IFERROR(INDEX(tblScope11Stationary[M6],ROW()-12),"") | K24: =IFERROR(INDEX(tblScope11Stationary[M7],ROW()-12),"") | L24: =IFERROR(INDEX(tblScope11Stationary[M8],ROW()-12),"") | M24: =IFERROR(INDEX(tblScope11Stationary[M9],ROW()-12),"") | N24: =IFERROR(INDEX(tblScope11Stationary[M10],ROW()-12),"") | O24: =IFERROR(INDEX(tblScope11Stationary[M11],ROW()-12),"") | P24: =IFERROR(INDEX(tblScope11Stationary[M12],ROW()-12),"")
A25: =IFERROR(INDEX(tblScope11Stationary[ItemLabel],ROW()-12),"") | B25: =IFERROR(INDEX(tblScope11Stationary[Evidence],ROW()-12),"") | C25: =IFERROR(INDEX(tblScope11Stationary[Unit],ROW()-12),"") | D25: =IF(A25="","",SUM(E25:P25)) | E25: =IFERROR(INDEX(tblScope11Stationary[M1],ROW()-12),"") | F25: =IFERROR(INDEX(tblScope11Stationary[M2],ROW()-12),"") | G25: =IFERROR(INDEX(tblScope11Stationary[M3],ROW()-12),"") | H25: =IFERROR(INDEX(tblScope11Stationary[M4],ROW()-12),"") | I25: =IFERROR(INDEX(tblScope11Stationary[M5],ROW()-12),"") | J25: =IFERROR(INDEX(tblScope11Stationary[M6],ROW()-12),"") | K25: =IFERROR(INDEX(tblScope11Stationary[M7],ROW()-12),"") | L25: =IFERROR(INDEX(tblScope11Stationary[M8],ROW()-12),"") | M25: =IFERROR(INDEX(tblScope11Stationary[M9],ROW()-12),"") | N25: =IFERROR(INDEX(tblScope11Stationary[M10],ROW()-12),"") | O25: =IFERROR(INDEX(tblScope11Stationary[M11],ROW()-12),"") | P25: =IFERROR(INDEX(tblScope11Stationary[M12],ROW()-12),"")
A26: =IFERROR(INDEX(tblScope11Stationary[ItemLabel],ROW()-12),"") | B26: =IFERROR(INDEX(tblScope11Stationary[Evidence],ROW()-12),"") | C26: =IFERROR(INDEX(tblScope11Stationary[Unit],ROW()-12),"") | D26: =IF(A26="","",SUM(E26:P26)) | E26: =IFERROR(INDEX(tblScope11Stationary[M1],ROW()-12),"") | F26: =IFERROR(INDEX(tblScope11Stationary[M2],ROW()-12),"") | G26: =IFERROR(INDEX(tblScope11Stationary[M3],ROW()-12),"") | H26: =IFERROR(INDEX(tblScope11Stationary[M4],ROW()-12),"") | I26: =IFERROR(INDEX(tblScope11Stationary[M5],ROW()-12),"") | J26: =IFERROR(INDEX(tblScope11Stationary[M6],ROW()-12),"") | K26: =IFERROR(INDEX(tblScope11Stationary[M7],ROW()-12),"") | L26: =IFERROR(INDEX(tblScope11Stationary[M8],ROW()-12),"") | M26: =IFERROR(INDEX(tblScope11Stationary[M9],ROW()-12),"") | N26: =IFERROR(INDEX(tblScope11Stationary[M10],ROW()-12),"") | O26: =IFERROR(INDEX(tblScope11Stationary[M11],ROW()-12),"") | P26: =IFERROR(INDEX(tblScope11Stationary[M12],ROW()-12),"")
A27: =IFERROR(INDEX(tblScope11Stationary[ItemLabel],ROW()-12),"") | B27: =IFERROR(INDEX(tblScope11Stationary[Evidence],ROW()-12),"") | C27: =IFERROR(INDEX(tblScope11Stationary[Unit],ROW()-12),"") | D27: =IF(A27="","",SUM(E27:P27)) | E27: =IFERROR(INDEX(tblScope11Stationary[M1],ROW()-12),"") | F27: =IFERROR(INDEX(tblScope11Stationary[M2],ROW()-12),"") | G27: =IFERROR(INDEX(tblScope11Stationary[M3],ROW()-12),"") | H27: =IFERROR(INDEX(tblScope11Stationary[M4],ROW()-12),"") | I27: =IFERROR(INDEX(tblScope11Stationary[M5],ROW()-12),"") | J27: =IFERROR(INDEX(tblScope11Stationary[M6],ROW()-12),"") | K27: =IFERROR(INDEX(tblScope11Stationary[M7],ROW()-12),"") | L27: =IFERROR(INDEX(tblScope11Stationary[M8],ROW()-12),"") | M27: =IFERROR(INDEX(tblScope11Stationary[M9],ROW()-12),"") | N27: =IFERROR(INDEX(tblScope11Stationary[M10],ROW()-12),"") | O27: =IFERROR(INDEX(tblScope11Stationary[M11],ROW()-12),"") | P27: =IFERROR(INDEX(tblScope11Stationary[M12],ROW()-12),"")
A28: =IFERROR(INDEX(tblScope11Stationary[ItemLabel],ROW()-12),"") | B28: =IFERROR(INDEX(tblScope11Stationary[Evidence],ROW()-12),"") | C28: =IFERROR(INDEX(tblScope11Stationary[Unit],ROW()-12),"") | D28: =IF(A28="","",SUM(E28:P28)) | E28: =IFERROR(INDEX(tblScope11Stationary[M1],ROW()-12),"") | F28: =IFERROR(INDEX(tblScope11Stationary[M2],ROW()-12),"") | G28: =IFERROR(INDEX(tblScope11Stationary[M3],ROW()-12),"") | H28: =IFERROR(INDEX(tblScope11Stationary[M4],ROW()-12),"") | I28: =IFERROR(INDEX(tblScope11Stationary[M5],ROW()-12),"") | J28: =IFERROR(INDEX(tblScope11Stationary[M6],ROW()-12),"") | K28: =IFERROR(INDEX(tblScope11Stationary[M7],ROW()-12),"") | L28: =IFERROR(INDEX(tblScope11Stationary[M8],ROW()-12),"") | M28: =IFERROR(INDEX(tblScope11Stationary[M9],ROW()-12),"") | N28: =IFERROR(INDEX(tblScope11Stationary[M10],ROW()-12),"") | O28: =IFERROR(INDEX(tblScope11Stationary[M11],ROW()-12),"") | P28: =IFERROR(INDEX(tblScope11Stationary[M12],ROW()-12),"")
... A60: =IFERROR(INDEX(tblScope11Stationary[ItemLabel],ROW()-12),"") | B60: =IFERROR(INDEX(tblScope11Stationary[Evidence],ROW()-12),"") | C60: =IFERROR(INDEX(tblScope11Stationary[Unit],ROW()-12),"") | D60: =IF(A60="","",SUM(E60:P60)) | E60: =IFERROR(INDEX(tblScope11Stationary[M1],ROW()-12),"") | F60: =IFERROR(INDEX(tblScope11Stationary[M2],ROW()-12),"") | G60: =IFERROR(INDEX(tblScope11Stationary[M3],ROW()-12),"") | H60: =IFERROR(INDEX(tblScope11Stationary[M4],ROW()-12),"") | I60: =IFERROR(INDEX(tblScope11Stationary[M5],ROW()-12),"") | J60: =IFERROR(INDEX(tblScope11Stationary[M6],ROW()-12),"") | K60: =IFERROR(INDEX(tblScope11Stationary[M7],ROW()-12),"") | L60: =IFERROR(INDEX(tblScope11Stationary[M8],ROW()-12),"") | M60: =IFERROR(INDEX(tblScope11Stationary[M9],ROW()-12),"") | N60: =IFERROR(INDEX(tblScope11Stationary[M10],ROW()-12),"") | O60: =IFERROR(INDEX(tblScope11Stationary[M11],ROW()-12),"") | P60: =IFERROR(INDEX(tblScope11Stationary[M12],ROW()-12),"")

Sheet 1.2 Mobile
A1: Mobile combustion
A2: สรุปรายการน้ำมัน
A3: รายการ | C3: ชนิด | D3: หลักฐาน | E3: หน่วย | F3: ปริมาณน้ำมัน | G3: Diesel | H3: Biodiesel | J3: Gasoline | K3: Ethanol
G4: L | H4: L | I4: kg | J4: L | K4: L | L4: kg
A5: =A13 | C5: B7 | D5: =D13 | E5: =E13 | F5: =F13 | G5: =F5*0.93 | H5: =F5-G5 | I5: =H5*0.87
A6: =A14 | C6: B10 | D6: =D14 | E6: =E14 | F6: =F14 | G6: =F6*0.9 | H6: =F6-G6 | I6: =H6*0.87
A7: =A43 | C7: 91/95 | D7: =D43 | E7: =E43 | F7: =F43 | J7: =F7*0.9 | K7: =F7-J7 | L7: =K7*0.79
A8: =A44 | C8: E20 | D8: =D44 | E8: =E44 | F8: =F44 | J8: =F8*0.8 | K8: =F8-J8 | L8: =K8*0.79
A9: =A57 | C9: B7 | D9: =D57 | E9: =E57 | F9: =F57 | G9: =F9*0.93 | H9: =F9-G9 | I9: =H9*0.87
A11: รายการ | B11: Location | C11: ชนิด | D11: หลักฐาน | E11: หน่วย | F11: รวม | G11: ปริมาณการใช้แต่ละเดือน/2566
G12: 1 | H12: 2 | I12: 3 | J12: 4 | K12: 5 | L12: 6 | M12: 7 | N12: 8 | O12: 9 | P12: 10 | Q12: 11 | R12: 12
A13: น้ำมัน Diesel B7 ที่ใช้ในรถยนต์ขององค์กร | C13: B7 | D13: ใบกำกับภาษี /Fleet Card Report | E13: L | F13: =F15+F17+F19+F21+F23+F25+F27+F29+F31+F33+F35+F37+F39+F41
A14: น้ำมัน Diesel B10 ที่ใช้ในรถยนต์ขององค์กร | C14: B10 | D14: ใบกำกับภาษี /Fleet Card Report | E14: L | F14: =F16+F18+F20+F22+F24+F26+F28+F30+F32+F34+F36+F38+F40+F42
A15: 1. จก 8296 ชบ | B15: LCB | C15: B7 | D15: ใบแจ้งหนี้ / Fleet Card Report | E15: L | F15: =SUM(G15:R15) | G15: 111.74 | H15: 176.84 | I15: 221.05 | J15: 157.78 | K15: 172.73 | L15: 144.18 | M15: 203.04 | N15: 246.02 | O15: 168.46 | P15: 224.84 | Q15: 164.94 | R15: 180.14
C16: B10 | F16: =SUM(G16:R16) | G16: 0 | H16: 0 | I16: 0 | J16: 0 | K16: 0 | L16: 0 | M16: 0 | N16: 0 | O16: 0 | P16: 0 | Q16: 0 | R16: 0
A17: 2. จก 8297 ชบ | B17: LCB | C17: B7 | D17: ใบแจ้งหนี้ / Fleet Card Report | E17: L | F17: =SUM(G17:R17) | G17: 109.83 | H17: 177.24 | I17: 88.93 | J17: 149.6 | K17: 212.11 | L17: 0 | M17: 172.84 | N17: 175.95 | O17: 118.34 | P17: 170.37 | Q17: 161.41 | R17: 179.68
C18: B10 | F18: =SUM(G18:R18) | G18: 0 | H18: 0 | I18: 0 | J18: 0 | K18: 0 | L18: 0 | M18: 0 | N18: 0 | O18: 0 | P18: 0 | Q18: 0 | R18: 0
A19: 3. นง 1084 ชบ. | B19: LCB | C19: B7 | D19: ใบแจ้งหนี้ / Fleet Card Report | E19: L | F19: =SUM(G19:R19) | G19: 164.74 | H19: 162.56 | I19: 102.89 | J19: 98.3 | K19: 152.31 | L19: 130.16 | M19: 189.03 | N19: 54.5 | O19: 109 | P19: 102.85 | Q19: 100.41 | R19: 53.14
C20: B10 | F20: =SUM(G20:R20) | G20: 53.51 | H20: 0 | I20: 0 | J20: 0 | K20: 0 | L20: 0 | M20: 0 | N20: 0 | O20: 0 | P20: 0 | Q20: 0 | R20: 0
A21: 4. ผล 4837 ชบ. | B21: LCB | C21: B7 | D21: ใบแจ้งหนี้ / Fleet Card Report | E21: L | F21: =SUM(G21:R21) | G21: 209.65 | H21: 147.35 | I21: 113.63 | J21: 116.43 | K21: 162.62 | L21: 179.29 | M21: 98.03 | N21: 62.28 | O21: 152.82 | P21: 119.89 | Q21: 154.68 | R21: 119.23
C22: B10 | F22: =SUM(G22:R22) | G22: 0 | H22: 0 | I22: 0 | J22: 0 | K22: 0 | L22: 0 | M22: 0 | N22: 0 | O22: 0 | P22: 0 | Q22: 0 | R22: 0
A23: 5. ฒอ 2780 กทม. | B23: LCB | C23: B7 | D23: ใบแจ้งหนี้ / Fleet Card Report | E23: L | F23: =SUM(G23:R23) | G23: 74.87 | H23: 105.05 | I23: 0 | J23: 0 | K23: 56.38 | L23: 0 | M23: 117.09 | N23: 0 | O23: 70.07 | P23: 60.11 | Q23: 0 | R23: 0
C24: B10 | F24: =SUM(G24:R24) | G24: 0 | H24: 0 | I24: 0 | K24: 0 | M24: 0 | N24: 0 | O24: 0
A25: 6. 6กข-9968 กทม | B25: BKK | C25: B7 | D25: ใบแจ้งหนี้ / Fleet Card Report | E25: L | F25: =SUM(G25:R25) | G25: 213.49 | H25: 171.42 | I25: 171.51 | J25: 50.79 | K25: 0 | L25: 0 | M25: 0 | N25: 0 | O25: 0 | P25: 0 | Q25: 0 | R25: 0
C26: B10 | F26: =SUM(G26:R26) | G26: 0 | H26: 0 | I26: 0 | J26: 0 | K26: 0 | L26: 0 | M26: 0 | N26: 0 | O26: 0 | P26: 0 | Q26: 0 | R26: 0
A27: 7. ฮฐ-7884 กทม | B27: BKK | C27: B7 | D27: ใบแจ้งหนี้ / Fleet Card Report | E27: L | F27: =SUM(G27:R27) | G27: 184.72 | H27: 280.02 | I27: 273.3 | J27: 255.84 | K27: 326.99 | L27: 283.78 | M27: 278.05 | N27: 340.84 | O27: 341.34 | P27: 284.67 | Q27: 316.99 | R27: 328.11
C28: B10 | F28: =SUM(G28:R28) | G28: 0 | H28: 0 | I28: 0 | J28: 0 | K28: 0 | L28: 0 | M28: 0 | N28: 0 | O28: 0 | P28: 0 | Q28: 0 | R28: 0
A29: 8. 2ฒค-421 กทม | B29: BKK | C29: B7 | D29: ใบแจ้งหนี้ / Fleet Card Report | E29: L | F29: =SUM(G29:R29) | G29: 45.8 | H29: 181.72 | I29: 129.14 | J29: 116.09 | K29: 162.25 | L29: 177.25 | M29: 41.05 | N29: 57.59 | O29: 0 | P29: 56.08 | Q29: 0 | R29: 0
C30: B10 | F30: =SUM(G30:R30) | G30: 0 | H30: 0 | I30: 0 | J30: 0 | K30: 0 | L30: 0 | M30: 0 | N30: 0 | O30: 0 | P30: 0 | Q30: 0 | R30: 0
A31: 9. 1ฒณ-8874 กทม | B31: BKK | C31: B7 | D31: ใบแจ้งหนี้ / Fleet Card Report | E31: L | F31: =SUM(G31:R31) | G31: 0 | H31: 42.91 | I31: 51.36 | J31: 0 | K31: 0 | L31: 0 | M31: 0 | N31: 0 | O31: 0 | P31: 0 | Q31: 0 | R31: 0
C32: B10 | F32: =SUM(G32:R32) | G32: 0 | H32: 0 | I32: 0 | K32: 0 | L32: 0 | M32: 0 | N32: 0 | O32: 0 | P32: 0 | Q32: 0 | R32: 0
A33: 10. ฮฐ 7884 กทม | B33: BKK | C33: B7 | D33: ใบกำกับภาษี / ใบเสร็จรับเงิน | E33: L | F33: =SUM(G33:R33) | G33: 14.302 | H33: 0 | I33: 0 | J33: 0 | K33: 0 | L33: 0 | M33: 0 | N33: 0 | O33: 0 | P33: 0 | Q33: 0 | R33: 0
C34: B10 | F34: =SUM(G34:R34) | G34: 0 | H34: 0 | I34: 0 | K34: 0 | L34: 0 | M34: 0 | N34: 0 | O34: 0 | P34: 0 | Q34: 0 | R34: 0
A35: 11. ฒอ 2780 กทม. | B35: LCB | C35: B7 | D35: ใบกำกับภาษี / ใบเสร็จรับเงิน | E35: L | F35: =SUM(G35:R35) | G35: 0 | H35: 0 | I35: 0 | J35: 0 | K35: 0 | L35: 0 | M35: 0 | N35: 0 | O35: 15.57 | P35: 0 | Q35: 0 | R35: 0
C36: B10 | F36: =SUM(G36:R36) | G36: 0 | H36: 0 | I36: 0 | K36: 0 | L36: 0 | M36: 0 | N36: 0 | O36: 0 | P36: 0 | Q36: 0 | R36: 0
A37: 12. จก 8296 ชลบุรี | B37: LCB | C37: B7 | D37: ใบกำกับภาษี / ใบเสร็จรับเงิน | E37: L | F37: =SUM(G37:R37) | G37: 69.81 | H37: 0 | I37: 0 | J37: 0 | K37: 0 | L37: 0 | M37: 0 | N37: 0 | O37: 0 | P37: 0 | Q37: 0 | R37: 0
C38: B10 | F38: =SUM(G38:R38) | G38: 0 | H38: 0 | I38: 0 | K38: 0 | L38: 0 | M38: 0 | N38: 0 | O38: 0 | P38: 0 | Q38: 0 | R38: 0
A39: 13. รถบรรทุก ทะเบียน 84-1022 | B39: LCB | C39: B7 | D39: fleet card | E39: L | F39: =SUM(G39:R39) | G39: 150.94 | H39: 153.08 | I39: 160.77 | J39: 0 | K39: 172.31 | L39: 155.4 | M39: 165.37 | N39: 164.75 | O39: 323.35 | P39: 0 | Q39: 161.74 | R39: 166.06
C40: B10 | F40: =SUM(G40:R40) | G40: 0 | H40: 0 | I40: 0 | K40: 0 | L40: 0 | M40: 0 | N40: 0 | O40: 0 | P40: 0 | Q40: 0 | R40: 0
A41: 14. รถบรรทุก ทะเบียน 86-8438 | B41: LCB | C41: B7 | D41: fleet card | E41: L | F41: =SUM(G41:R41) | G41: 144.18 | H41: 315.32 | I41: 294.42 | J41: 149.95 | K41: 294.18 | L41: 285.58 | M41: 308.31 | N41: 310.8 | O41: 298.04 | P41: 148.45 | Q41: 152.77 | R41: 298.91
C42: B10 | F42: =SUM(G42:R42) | G42: 0 | H42: 0 | I42: 0 | J42: 0 | K42: 0 | L42: 0 | M42: 0 | N42: 0 | O42: 0 | P42: 0 | Q42: 0 | R42: 0
A43: น้ำมัน Gasohol 91/95 ที่ใช้ในรถยนต์ขององค์กร | D43: ใบกำกับภาษี /Fleet Card Report | E43: L | F43: =F45+F47+F49+F51+F53+F55
A44: น้ำมัน Gasohol E20 ที่ใช้ในรถยนต์ขององค์กร | D44: ใบกำกับภาษี /Fleet Card Report | E44: L | F44: =F46+F48+F50+F52+F54+F56
A45: 1. 5กว-3489 กทม. | B45: LCB | C45: 91/95 | D45: ใบแจ้งหนี้ / Fleet Card Report | E45: L | F45: =SUM(G45:R45) | G45: 188.77 | H45: 270.87 | I45: 210.78 | J45: 53.54 | K45: 0 | L45: 0 | M45: 0 | N45: 0 | O45: 0 | P45: 0 | Q45: 0 | R45: 0
C46: E20 | F46: =SUM(G46:R46) | G46: 119.71 | H46: 31.38 | I46: 0 | J46: 0 | K46: 0 | L46: 0 | M46: 0 | O46: 0 | P46: 0 | Q46: 0 | R46: 0
A47: 2. ญล 8398 กทม. | B47: LCB | C47: 91/95 | D47: ใบแจ้งหนี้ / Fleet Card Report | E47: L | F47: =SUM(G47:R47) | G47: 0 | H47: 108.4 | I47: 93.15 | J47: 67.46 | K47: 70.5 | L47: 63.12 | M47: 80.37 | N47: 52.49 | O47: 114.88 | P47: 26.11 | Q47: 64.63 | R47: 0
C48: E20 | F48: =SUM(G48:R48) | G48: 0 | H48: 0 | I48: 0 | J48: 0 | K48: 0 | L48: 0 | M48: 0 | N48: 0 | O48: 0 | P48: 0 | Q48: 0 | R48: 0
A49: 3. 6กฉ-3489 กทม | B49: BKK | C49: 91/95 | D49: ใบแจ้งหนี้ / Fleet Card Report | E49: L | F49: =SUM(G49:R49) | G49: 112.94 | H49: 47.24 | I49: 93.05 | J49: 24.01 | K49: 0 | L49: 0 | M49: 0 | N49: 0 | O49: 0 | P49: 0 | Q49: 0 | R49: 0
C50: E20 | F50: =SUM(G50:R50) | G50: 0 | H50: 0 | I50: 0 | J50: 0 | K50: 0 | L50: 0 | M50: 0 | O50: 0 | P50: 0 | Q50: 0 | R50: 0
A51: 4. 5กม-3489 กทม | B51: BKK | C51: 91/95 | D51: ใบแจ้งหนี้ / Fleet Card Report | E51: L | F51: =SUM(G51:R51) | G51: 79.2 | H51: 141.26 | I51: 104.74 | J51: 60.07 | K51: 89.99 | L51: 95.23 | M51: 138.12 | N51: 51.64 | O51: 79.06 | P51: 132.35 | Q51: 149.24 | R51: 90.77
C52: E20 | F52: =SUM(G52:R52) | G52: 0 | H52: 0 | I52: 0 | J52: 0 | K52: 0 | L52: 0 | M52: 0 | N52: 0 | O52: 0 | P52: 0 | Q52: 0 | R52: 0
A53: 5. ฮต-6531 กทม. | B53: BKK | C53: 91/95 | D53: ใบแจ้งหนี้ / Fleet Card Report | E53: L | F53: =SUM(G53:R53) | G53: 306.98 | H53: 0 | I53: 48.9 | J53: 46.06 | K53: 39.88 | L53: 131.12 | M53: 38.52 | N53: 80.16 | O53: 66.09 | P53: 0 | Q53: 66.64 | R53: 0
C54: E20 | F54: =SUM(G54:R54) | G54: 0 | H54: 0 | I54: 0 | J54: 0 | K54: 0 | L54: 0 | M54: 0 | N54: 0 | O54: 0 | P54: 0 | Q54: 0 | R54: 0
A55: 6. 4 กฬ-8072 กทม. | B55: BKK | C55: 91/95 | D55: ใบแจ้งหนี้ / Fleet Card Report | E55: L | F55: =SUM(G55:R55) | G55: 175.81 | H55: 154.17 | I55: 81.72 | J55: 0 | K55: 0 | L55: 0 | M55: 0 | N55: 0 | O55: 0 | P55: 0 | Q55: 0 | R55: 0
C56: E20 | F56: =SUM(G56:R56) | G56: 0 | H56: 0 | I56: 0 | K56: 0 | L56: 0 | M56: 0 | O56: 0 | P56: 0 | Q56: 0 | R56: 0
A57: น้ำมัน Diesel B7 ที่ใช้ใน Forklift | D57: Fleet card | E57: L | F57: =SUM(F58)
A58: 3. รถโฟล์คลิฟท์ 3 คัน | B58: LCB | C58: B7 | D58: Fleet card | E58: L | F58: =SUM(G58:R58) | G58: 360 | H58: 360 | I58: 540 | J58: 180 | K58: 540 | L58: 360 | M58: 540 | N58: 330 | O58: 360 | P58: 360 | Q58: 360 | R58: 360

Sheet 1.4 Fugitive Emission

Sheet 1.4.1 สารทำความเย็น
A1: สารทำความเย็น
A2: เครื่องที่ใช้ | B2: สถานที่ | C2: หลักฐาน | D2: หน่วย | E2: รวม | F2: ปริมาณการใช้แต่ละเดือน/2566
F3: 1 | G3: 2 | H3: 3 | I3: 4 | J3: 5 | K3: 6 | L3: 7 | M3: 8 | N3: 9 | O3: 10 | P3: 11 | Q3: 12
A4: สารทำความเย็น R-22 Chiller/เครื่องปรับอากาศ/Air dryer | B4: LCB | C4: ใบกำกับภาษี/ใบส่งซ่อม | D4: kg | E4: =SUM(F4:Q4) | F4: =F5*13.6 | G4: 0 | H4: 0 | I4: 0 | J4: 0 | K4: 0 | L4: 0 | M4: =M5*13.6 | N4: =N5*13.6 | O4: 0 | P4: =8+13 | Q4: 0
D5: ถัง | E5: =SUM(F5:Q5) | F5: 2 | G5: 0 | H5: 0 | I5: 0 | J5: 0 | K5: 0 | L5: 0 | M5: 2 | N5: 2 | O5: 0 | P5: 0 | Q5: 0
A6: สารทำความเย็น R-32 -ครื่องปรับอากาศ | B6: LCB, BKK | C6: ใบกำกับภาษี/เอกสาร PM | D6: kg | E6: =SUM(F6:Q6) | F6: 0 | G6: 0 | H6: =(1.6*0.03)+(1.6*0.8)+(0.85*0.03)+(0.85*0.8) | I6: 0 | J6: 0 | K6: 0 | L6: 0 | M6: =(0.85*0.03)+(0.85*0.8) | O6: 0 | P6: 0 | Q6: 0
A7: สารทำความเย็น R-410a - เครื่องปรับอากาศ | B7: LCB, BKK | C7: ใบกำกับภาษี/เอกสาร PM | D7: kg | E7: =SUM(F7:Q7) | F7: 0 | G7: 0 | H7: 0 | I7: 0 | J7: 0 | K7: 0 | L7: 0 | M7: 0 | N7: 0 | O7: 0 | P7: 0 | Q7: 0
A8: สารทำความเย็น R-134a - ตู้แอร์ระบายความร้อน | B8: LCB | C8: ใบกำกับภาษี/เอกสาร PM | D8: kg | E8: =SUM(F8:Q8) | F8: 0 | G8: 0 | H8: 0 | I8: 0 | J8: 0 | K8: 0 | L8: 0 | M8: 0 | N8: 0 | O8: 0 | P8: 0 | Q8: 0
A9: สารทำความเย็น R-407c - Air dryer/Chiller | B9: LCB | C9: ใบกำกับภาษี/เอกสาร PM | D9: kg | E9: =SUM(F9:Q9) | F9: 0 | G9: 0 | H9: 0 | I9: 0 | J9: 0 | K9: 0 | L9: 0 | M9: 0 | N9: 0 | O9: 0 | P9: 0 | Q9: 0
A12: R 22 ซื้อสำรอง สำหรับฉุกเฉิน แต่ซ่อมจะเป็นจ้างเหมาภายนอก
A13: R 32, R410 a, R134a, R407C จ้างเหมา
A14: BKK มีเครื่องปรับอากาศไม่ได้ใช้งาน นานหรือยัง
A15: Chiller โรงงาน 1 -หายไป 1 ตัว
A16: ไม่เห็น PM ของ Cooling โรง 3
A17: AC -LCB ไม่มีการะบุชนิดสารทำความเย็น
A32: a

Sheet 1.4.2 สารดับเพลิง
A2: แหล่งการปล่อยก๊าซเรือนกระจก | B2: Location | C2: หลักฐาน | D2: หน่วย | F2: ปริมาณการใช้แต่ละเดือน/2566
E3: รวม | F3: 1 | G3: 2 | H3: 3 | I3: 4 | J3: 5 | K3: 6 | L3: 7 | M3: 8 | N3: 9 | O3: 10 | P3: 11 | Q3: 12
A4: สารดับเพลิง CO2 | B4: LCB/BKK | C4: ใบสั่งซื้อ/เอกสาร PM | D4: Kg | E4: =SUM(E5,E7,E9) | F4: 0 | G4: 0 | H4: 0 | I4: 0 | J4: 0 | K4: 0 | L4: 0 | M4: 0 | N4: 0 | O4: 0 | P4: 0 | Q4: 0
A5: สารดับเพลิง HCFC-123 | B5: LCB/BKK (ห้อง Server) | C5: ใบสั่งซื้อ/เอกสาร PM | D5: Kg | E5: =SUM(E6,E8,E10) | F5: 0 | G5: 0 | H5: 0 | I5: 0 | J5: 0 | K5: 0 | L5: 0 | M5: 0 | N5: 0 | O5: 0 | P5: 0 | Q5: 0

Sheet 1.4.3 Septic
A1: # 1 จำนวนพนักงานโรงงานแหลมฉบัง
B2: รูปแบบการทำงานแบบ 6 วันต่อสัปดาห์ | H2: TOW | I2: CH4 emission จาก Septic
A3: เดือน | B3: จำนวนพนักงานที่ส่งประกันสังคม (1) | C3: จำนวนวันทั้งหมดประจำเดือน (2) | D3: จำนวนวันหยุดราชการ (of Year) (3) | E3: จำนวนวันหยุดประจำเดือน (of Month) (3) | F3: No. of Working days (4) ((2)-(3)) | G3: Man-day (1)*(4)
A4: ม.ค. | B4: 939 | C4: 31 | D4: 2 | E4: 5 | F4: =C4-D4-E4 | G4: =B4*F4 | H4: =G4*0.001*$B$76*$B$78 | I4: =($B$68*$B$70*$B$71)*(H4-$B$72-$B$73)
A5: ก.พ. | B5: 928 | C5: 28 | D5: 0 | E5: 4 | F5: =C5-D5-E5 | G5: =B5*F5 | H5: =G5*0.001*$B$76*$B$78 | I5: =($B$68*$B$70*$B$71)*(H5-$B$72-$B$73)
A6: มี.ค. | B6: 894 | C6: 31 | D6: 0 | E6: 4 | F6: =C6-D6-E6 | G6: =B6*F6 | H6: =G6*0.001*$B$76*$B$78 | I6: =($B$68*$B$70*$B$71)*(H6-$B$72-$B$73)
A7: เม.ย. | B7: 853 | C7: 30 | D7: 5 | E7: 5 | F7: =C7-D7-E7 | G7: =B7*F7 | H7: =G7*0.001*$B$76*$B$78 | I7: =($B$68*$B$70*$B$71)*(H7-$B$72-$B$73)
A8: พ.ค. | B8: 765 | C8: 31 | D8: 1 | E8: 4 | F8: =C8-D8-E8 | G8: =B8*F8 | H8: =G8*0.001*$B$76*$B$78 | I8: =($B$68*$B$70*$B$71)*(H8-$B$72-$B$73)
A9: มิ.ย. | B9: 736 | C9: 30 | D9: 0 | E9: 4 | F9: =C9-D9-E9 | G9: =B9*F9 | H9: =G9*0.001*$B$76*$B$78 | I9: =($B$68*$B$70*$B$71)*(H9-$B$72-$B$73)
A10: ก.ค. | B10: 741 | C10: 31 | D10: 1 | E10: 5 | F10: =C10-D10-E10 | G10: =B10*F10 | H10: =G10*0.001*$B$76*$B$78 | I10: =($B$68*$B$70*$B$71)*(H10-$B$72-$B$73)
A11: ส.ค. | B11: 730 | C11: 31 | D11: 0 | E11: 4 | F11: =C11-D11-E11 | G11: =B11*F11 | H11: =G11*0.001*$B$76*$B$78 | I11: =($B$68*$B$70*$B$71)*(H11-$B$72-$B$73)
A12: ก.ย. | B12: 713 | C12: 30 | D12: 0 | E12: 4 | F12: =C12-D12-E12 | G12: =B12*F12 | H12: =G12*0.001*$B$76*$B$78 | I12: =($B$68*$B$70*$B$71)*(H12-$B$72-$B$73)
A13: ต.ค. | B13: 702 | C13: 31 | D13: 1 | E13: 5 | F13: =C13-D13-E13 | G13: =B13*F13 | H13: =G13*0.001*$B$76*$B$78 | I13: =($B$68*$B$70*$B$71)*(H13-$B$72-$B$73)
A14: พ.ย. | B14: 693 | C14: 30 | D14: 0 | E14: 4 | F14: =C14-D14-E14 | G14: =B14*F14 | H14: =G14*0.001*$B$76*$B$78 | I14: =($B$68*$B$70*$B$71)*(H14-$B$72-$B$73)
A15: ธ.ค. | B15: 692 | C15: 31 | D15: 3 | E15: 5 | F15: =C15-D15-E15 | G15: =B15*F15 | H15: =G15*0.001*$B$76*$B$78 | I15: =($B$68*$B$70*$B$71)*(H15-$B$72-$B$73)
F16: =SUM(F4:F15) | G16: =SUM(G4:G15) | I16: =SUM(I4:I15)
A17: # 2 จำนวนพนักงานสำนักงานกรุงเทพ
B18: รูปแบบการทำงานแบบ 5 วันต่อสัปดาห์ | H18: TOW | I18: CH4 emission จาก Septic
A19: เดือน | B19: จำนวนพนักงานที่ส่งประกันสังคม (1) | C19: จำนวนวันทั้งหมดประจำเดือน (2) | D19: จำนวนวันหยุดราชการ (of Year) (3) | E19: จำนวนวันหยุดประจำเดือน (of Month) (3) | F19: No. of Working days (4) ((2)-(3)) | G19: Man-day (1)*(4)
A20: ม.ค. | B20: 29 | C20: 31 | D20: 2 | E20: 9 | F20: =C20-D20-E20 | G20: =B20*F20 | H20: =G20*0.001*$B$76*$B$78 | I20: =($B$68*$B$70*$B$71)*(H20-$B$72-$B$73)
A21: ก.พ. | B21: 29 | C21: 28 | D21: 0 | E21: 8 | F21: =C21-D21-E21 | G21: =B21*F21 | H21: =G21*0.001*$B$76*$B$78 | I21: =($B$68*$B$70*$B$71)*(H21-$B$72-$B$73)
A22: มี.ค. | B22: 28 | C22: 31 | D22: 0 | E22: 8 | F22: =C22-D22-E22 | G22: =B22*F22 | H22: =G22*0.001*$B$76*$B$78 | I22: =($B$68*$B$70*$B$71)*(H22-$B$72-$B$73)
A23: เม.ย. | B23: 29 | C23: 30 | D23: 4 | E23: 10 | F23: =C23-D23-E23 | G23: =B23*F23 | H23: =G23*0.001*$B$76*$B$78 | I23: =($B$68*$B$70*$B$71)*(H23-$B$72-$B$73)
A24: พ.ค. | B24: 29 | C24: 31 | D24: 1 | E24: 8 | F24: =C24-D24-E24 | G24: =B24*F24 | H24: =G24*0.001*$B$76*$B$78 | I24: =($B$68*$B$70*$B$71)*(H24-$B$72-$B$73)
A25: มิ.ย. | B25: 29 | C25: 30 | D25: 0 | E25: 8 | F25: =C25-D25-E25 | G25: =B25*F25 | H25: =G25*0.001*$B$76*$B$78 | I25: =($B$68*$B$70*$B$71)*(H25-$B$72-$B$73)
A26: ก.ค. | B26: 29 | C26: 31 | D26: 1 | E26: 10 | F26: =C26-D26-E26 | G26: =B26*F26 | H26: =G26*0.001*$B$76*$B$78 | I26: =($B$68*$B$70*$B$71)*(H26-$B$72-$B$73)
A27: ส.ค. | B27: 29 | C27: 31 | D27: 1 | E27: 8 | F27: =C27-D27-E27 | G27: =B27*F27 | H27: =G27*0.001*$B$76*$B$78 | I27: =($B$68*$B$70*$B$71)*(H27-$B$72-$B$73)
A28: ก.ย. | B28: 29 | C28: 30 | D28: 0 | E28: 9 | F28: =C28-D28-E28 | G28: =B28*F28 | H28: =G28*0.001*$B$76*$B$78 | I28: =($B$68*$B$70*$B$71)*(H28-$B$72-$B$73)
A29: ต.ค. | B29: 27 | C29: 31 | D29: 2 | E29: 9 | F29: =C29-D29-E29 | G29: =B29*F29 | H29: =G29*0.001*$B$76*$B$78 | I29: =($B$68*$B$70*$B$71)*(H29-$B$72-$B$73)
A30: พ.ย. | B30: 26 | C30: 30 | D30: 0 | E30: 8 | F30: =C30-D30-E30 | G30: =B30*F30 | H30: =G30*0.001*$B$76*$B$78 | I30: =($B$68*$B$70*$B$71)*(H30-$B$72-$B$73)
A31: ธ.ค. | B31: 26 | C31: 31 | D31: 2 | E31: 10 | F31: =C31-D31-E31 | G31: =B31*F31 | H31: =G31*0.001*$B$76*$B$78 | I31: =($B$68*$B$70*$B$71)*(H31-$B$72-$B$73)
F32: =SUM(F20:F31) | G32: =SUM(G20:G31) | I32: =SUM(I20:I31)
A33: # 3 จำนวน รปภ
B34: รูปแบบการทำงานแบบ 7 วันต่อสัปดาห์ | H34: TOW | I34: CH4 emission จาก Septic
A35: เดือน | B35: จำนวน รปภ ตามสัญญาจ้าง (1) | C35: จำนวนวันทั้งหมดประจำเดือน (2) | D35: จำนวนวันหยุดราชการ (of Year) (3) | E35: จำนวนวันหยุดประจำเดือน (of Month) (3) | F35: No. of Working days (4) ((2)-(3)) | G35: Man-day (1)*(4)
A36: ม.ค. | B36: =15+3+2 | C36: 31 | D36: 0 | E36: 0 | F36: =C36-D36-E36 | G36: =B36*F36 | H36: =G36*0.001*$B$76*$B$78 | I36: =($B$68*$B$70*$B$71)*(H36-$B$72-$B$73)
A37: ก.พ. | B37: =15+3+2 | C37: 28 | D37: 0 | E37: 0 | F37: =C37-D37-E37 | G37: =B37*F37 | H37: =G37*0.001*$B$76*$B$78 | I37: =($B$68*$B$70*$B$71)*(H37-$B$72-$B$73)
A38: มี.ค. | B38: =15+3+2 | C38: 31 | D38: 0 | E38: 0 | F38: =C38-D38-E38 | G38: =B38*F38 | H38: =G38*0.001*$B$76*$B$78 | I38: =($B$68*$B$70*$B$71)*(H38-$B$72-$B$73)
A39: เม.ย. | B39: =15+3+2 | C39: 30 | D39: 0 | E39: 0 | F39: =C39-D39-E39 | G39: =B39*F39 | H39: =G39*0.001*$B$76*$B$78 | I39: =($B$68*$B$70*$B$71)*(H39-$B$72-$B$73)
A40: พ.ค. | B40: =15+3+2 | C40: 31 | D40: 0 | E40: 0 | F40: =C40-D40-E40 | G40: =B40*F40 | H40: =G40*0.001*$B$76*$B$78 | I40: =($B$68*$B$70*$B$71)*(H40-$B$72-$B$73)
A41: มิ.ย. | B41: =15+3+2 | C41: 30 | D41: 0 | E41: 0 | F41: =C41-D41-E41 | G41: =B41*F41 | H41: =G41*0.001*$B$76*$B$78 | I41: =($B$68*$B$70*$B$71)*(H41-$B$72-$B$73)
A42: ก.ค. | B42: =15+2+2 | C42: 31 | D42: 0 | E42: 0 | F42: =C42-D42-E42 | G42: =B42*F42 | H42: =G42*0.001*$B$76*$B$78 | I42: =($B$68*$B$70*$B$71)*(H42-$B$72-$B$73)
A43: ส.ค. | B43: =15+2+2 | C43: 31 | D43: 0 | E43: 0 | F43: =C43-D43-E43 | G43: =B43*F43 | H43: =G43*0.001*$B$76*$B$78 | I43: =($B$68*$B$70*$B$71)*(H43-$B$72-$B$73)
A44: ก.ย. | B44: =15+2+2 | C44: 30 | D44: 0 | E44: 0 | F44: =C44-D44-E44 | G44: =B44*F44 | H44: =G44*0.001*$B$76*$B$78 | I44: =($B$68*$B$70*$B$71)*(H44-$B$72-$B$73)
A45: ต.ค. | B45: =15+2+2 | C45: 31 | D45: 0 | E45: 0 | F45: =C45-D45-E45 | G45: =B45*F45 | H45: =G45*0.001*$B$76*$B$78 | I45: =($B$68*$B$70*$B$71)*(H45-$B$72-$B$73)
A46: พ.ย. | B46: =15+2+2 | C46: 30 | D46: 0 | E46: 0 | F46: =C46-D46-E46 | G46: =B46*F46 | H46: =G46*0.001*$B$76*$B$78 | I46: =($B$68*$B$70*$B$71)*(H46-$B$72-$B$73)
A47: ธ.ค. | B47: =15+2+2 | C47: 31 | D47: 0 | E47: 0 | F47: =C47-D47-E47 | G47: =B47*F47 | H47: =G47*0.001*$B$76*$B$78 | I47: =A49=($B$68*$B$70*$B$71)*(H47-$B$72-$B$73)
F48: =SUM(F36:F47) | G48: =SUM(G36:G47) | I48: =SUM(I36:I47)
A49: # 4 จำนวน พยาบาล
B50: รูปแบบการทำงานแบบ 7 วันต่อสัปดาห์ | H50: TOW | I50: CH4 emission จาก Septic
A51: เดือน | B51: จำนวนพนักงานที่ส่งประกันสังคม (1) | C51: จำนวนวันทั้งหมดประจำเดือน (2) | D51: จำนวนวันหยุดราชการ (of Year) (3) | E51: จำนวนวันหยุดประจำเดือน (of Month) (3) | F51: No. of Working days (4) ((2)-(3)) | G51: Man-day (1)*(4)
A52: ม.ค. | B52: 2 | C52: 31 | D52: 0 | E52: 0 | F52: =C52-D52-E52 | G52: =B52*F52 | H52: =G52*0.001*$B$76*$B$78 | I52: =($B$68*$B$70*$B$71)*(H52-$B$72-$B$73)
A53: ก.พ. | B53: 2 | C53: 28 | D53: 0 | E53: 0 | F53: =C53-D53-E53 | G53: =B53*F53 | H53: =G53*0.001*$B$76*$B$78 | I53: =($B$68*$B$70*$B$71)*(H53-$B$72-$B$73)
A54: มี.ค. | B54: 2 | C54: 31 | D54: 0 | E54: 0 | F54: =C54-D54-E54 | G54: =B54*F54 | H54: =G54*0.001*$B$76*$B$78 | I54: =($B$68*$B$70*$B$71)*(H54-$B$72-$B$73)
A55: เม.ย. | B55: 2 | C55: 30 | D55: 0 | E55: 0 | F55: =C55-D55-E55 | G55: =B55*F55 | H55: =G55*0.001*$B$76*$B$78 | I55: =($B$68*$B$70*$B$71)*(H55-$B$72-$B$73)
A56: พ.ค. | B56: 2 | C56: 31 | D56: 0 | E56: 0 | F56: =C56-D56-E56 | G56: =B56*F56 | H56: =G56*0.001*$B$76*$B$78 | I56: =($B$68*$B$70*$B$71)*(H56-$B$72-$B$73)
A57: มิ.ย. | B57: 2 | C57: 30 | D57: 0 | E57: 0 | F57: =C57-D57-E57 | G57: =B57*F57 | H57: =G57*0.001*$B$76*$B$78 | I57: =($B$68*$B$70*$B$71)*(H57-$B$72-$B$73)
A58: ก.ค. | B58: 2 | C58: 31 | D58: 0 | E58: 0 | F58: =C58-D58-E58 | G58: =B58*F58 | H58: =G58*0.001*$B$76*$B$78 | I58: =($B$68*$B$70*$B$71)*(H58-$B$72-$B$73)
A59: ส.ค. | B59: 2 | C59: 31 | D59: 0 | E59: 0 | F59: =C59-D59-E59 | G59: =B59*F59 | H59: =G59*0.001*$B$76*$B$78 | I59: =($B$68*$B$70*$B$71)*(H59-$B$72-$B$73)
A60: ก.ย. | B60: 2 | C60: 30 | D60: 0 | E60: 0 | F60: =C60-D60-E60 | G60: =B60*F60 | H60: =G60*0.001*$B$76*$B$78 | I60: =($B$68*$B$70*$B$71)*(H60-$B$72-$B$73)
A61: ต.ค. | B61: 2 | C61: 31 | D61: 0 | E61: 0 | F61: =C61-D61-E61 | G61: =B61*F61 | H61: =G61*0.001*$B$76*$B$78 | I61: =($B$68*$B$70*$B$71)*(H61-$B$72-$B$73)
A62: พ.ย. | B62: 2 | C62: 30 | D62: 0 | E62: 0 | F62: =C62-D62-E62 | G62: =B62*F62 | H62: =G62*0.001*$B$76*$B$78 | I62: =($B$68*$B$70*$B$71)*(H62-$B$72-$B$73)
A63: ธ.ค. | B63: 2 | C63: 31 | D63: 0 | E63: 0 | F63: =C63-D63-E63 | G63: =B63*F63 | H63: =G63*0.001*$B$76*$B$78 | I63: =($B$68*$B$70*$B$71)*(H63-$B$72-$B$73)
F64: =SUM(F52:F63) | G64: =SUM(G52:G63) | I64: =SUM(I52:I63)
A66: Ref. IPCC2006 Volume5 Chapter 6
A67: CH4 Emission | B67: =(B70*B71*B68)*(B69-B72)-B73 | C67: Eq 6.1 in unit kg CH4/yr
A68: EF j | B68: =B74*B75 | C68: Eq 6.2
A69: TOW | B69: =B77*B76*0.001*B78*365 | C69: Eq 6.3 (kg BOD/yr)
A70: Ui | B70: 1 | C70: Table6.5 Assume all people stay in urban high
A71: Tij | B71: 1 | C71: Table6.5 Assume all people stay in urban high
A72: S | B72: 0
A73: R | B73: 0
A74: B0 | B74: 0.6 | C74: Table 6.2 in unit kg CH4/kg BOD
A75: MCF | B75: 0.5 | C75: Table 6.3 septic system
A76: BOD | B76: 40 | C76: Table 6.4 Asia in unit g/person/day
A77: P | C77: people
A78: I | B78: 1 | C78: for uncollected the default

Sheet 1.4.4 ปุ๋ย
A1: รายการ | B1: หลักฐาน | C1: หน่วย | D1: รวม | E1: ปริมาณการใช้แต่ละเดือน/2566 | Q1: EF ปุ๋ยเคมี 16-16-16
E2: 1 | F2: 2 | G2: 3 | H2: 4 | I2: 5 | J2: 6 | K2: 7 | L2: 8 | M2: 9 | N2: 10 | O2: 11 | P2: 12
A3: ปุ๋ยเคมี 16-16-16 | B3: บิลเงินสด | C3: Kg | D3: =SUM(E3:P3) | E3: 50 | F3: 0 | G3: 0 | H3: 0 | I3: 0 | J3: 0 | K3: 0 | L3: 0 | M3: 0 | N3: 0 | O3: 0 | P3: 0 | Q3: 0.0025 | R3: kg N2O
Q4: 0.8596 | R4: Kg CO2
A5: หมายเหตุ: ขอชนิด/ประเภทปุ๋ย เช่น ปุ๋ยเคมี สูตร 16-16-16, ปุ๋ยคอก

Sheet 1.4.5 ระบบบำบัดน้ำเสีย WWTP
A1: ระบบบำบัดน้ำเสีย
A2: รายการ | B2: ระบบ WWTP | C2: หลักฐาน | D2: หน่วย | E2: มาตรฐาน (mg/L) | F2: ปริมาณการใช้แต่ละเดือน/2566
F3: 1 | G3: 2 | H3: 3 | I3: 4 | J3: 5 | K3: 6 | L3: 7 | M3: 8 | N3: 9 | O3: 10 | P3: 11 | Q3: 12
A4: BOD (น้ำออก) MBAX 1 | B4: ระบบเติมอากาศ | C4: ผลตรวจวิเคราะห์น้ำ | D4: mg/l | E4: 500 | F4: 124 | G4: 95 | H4: 120 | I4: 38 | J4: 65 | K4: 84 | L4: 72 | M4: 56 | N4: 88 | O4: 47 | P4: 136 | Q4: 137
A5: BOD (น้ำออก) MBAX 3 | B5: ระบบเติมอากาศ | C5: ผลตรวจวิเคราะห์น้ำ | D5: mg/l | E5: 500 | F5: 90 | G5: 60 | H5: 84 | I5: 111 | J5: 78 | K5: 64 | L5: 49 | M5: 47 | N5: 62 | O5: 110 | P5: 45 | Q5: 80
A6: BOD (น้ำออก) MBAX 5 | B6: ระบบเติมอากาศ | C6: ผลตรวจวิเคราะห์น้ำ | D6: mg/l | E6: 500 | F6: 90 | G6: 70 | H6: 43 | I6: 69 | J6: 66 | K6: 77 | L6: 65 | M6: 67 | N6: 83 | O6: 124 | P6: 75 | Q6: 65
A7: COD (น้ำออก) MBAX 1 | B7: ระบบเติมอากาศ | C7: ผลตรวจวิเคราะห์น้ำ | D7: mg/l | E7: 750 | F7: 236 | G7: 294 | H7: 298 | I7: 148 | J7: 155 | K7: 214 | L7: 252 | M7: 203 | N7: 222 | O7: 205 | P7: 365 | Q7: 321
A8: COD (น้ำออก) MBAX 3 | B8: ระบบเติมอากาศ | C8: ผลตรวจวิเคราะห์น้ำ | D8: mg/l | E8: 750 | F8: 172 | G8: 123 | H8: 137 | I8: 266 | J8: 219 | K8: 179 | L8: 172 | M8: 140 | N8: 191 | O8: 263 | P8: 124 | Q8: 177
A9: COD (น้ำออก) MBAX 5 | B9: ระบบเติมอากาศ | C9: ผลตรวจวิเคราะห์น้ำ | D9: mg/l | E9: 750 | F9: 176 | G9: 186 | H9: 145 | I9: 179 | J9: 179 | K9: 221 | L9: 514 | M9: 182 | N9: 198 | O9: 204 | P9: 235 | Q9: 190
A12: ตำแหน่งที่ตั้งของมิเตอร์ | B12: หลักฐาน | C12: หน่วย | D12: รวม | E12: 243254 | F12: 243285 | G12: 243313 | H12: 243344 | I12: 243374 | J12: 243405 | K12: 243435 | L12: 243466 | M12: 243497 | N12: 243527 | O12: 243558 | P12: 243588
A13: โรงงาน1,2 | B13: ใบแจ้งหนี้ | C13: m3 | D13: =SUM(E13:P13) | E13: 1024.8 | F13: 1576 | G13: 1497.6 | H13: 980 | I13: 1624.8 | J13: 1507.2 | K13: 1276 | L13: 2502.4 | M13: 1448 | N13: 1199.2 | O13: 1987.2 | P13: 819.2
A14: โรงงาน 5 | B14: ใบแจ้งหนี้ | C14: m3 | D14: =SUM(E14:P14) | E14: 1320 | F14: 1068 | G14: 1194.4 | H14: 1145.6 | I14: 1396 | J14: 1412.8 | K14: 1315.2 | L14: 1326.4 | M14: 405.6 | N14: 354.4 | O14: 504.8 | P14: 1292.8
A15: โรงงาน 3 | B15: ใบแจ้งหนี้ | C15: m3 | D15: =SUM(E15:P15) | E15: 987.2 | F15: 710.4 | G15: 740 | H15: 633.6 | I15: 1067.2 | J15: 816 | K15: 702.4 | L15: 706.4 | M15: 616 | N15: 608.8 | O15: 652.8 | P15: 715.2
A16: โรงงาน 4 | B16: ใบแจ้งหนี้ | C16: m3 | D16: =SUM(E16:P16) | E16: 508.8 | F16: 455.2 | G16: 484.8 | H16: 290.4 | I16: 309.6 | J16: 384 | K16: 389.6 | L16: 468 | M16: 405.6 | N16: 354.4 | O16: 504.8 | P16: 464

Sheet Scope 2.1 Purchased Electricity
A1: เลขมิเตอร์/เลขผู้ใช้ | B1: แหล่งไฟฟ้า | C1: หลักฐาน | D1: หน่วย | E1: รวม | F1: ปริมาณการใช้แต่ละเดือน/2566 (กิโลวัตต์-ชั่วโมง)
F2: 1 | G2: 2 | H2: 3 | I2: 4 | J2: 5 | K2: 6 | L2: 7 | M2: 8 | N2: 9 | O2: 10 | P2: 11 | Q2: 12
A3: การใช้ไฟฟ้า โรงงาน (1-3) (B. Grimm) | C3: ใบแจ้งหนี้ | D3: Kwh | E3: =SUM(E4:E6)
A4: โรงงาน 1 : MULTIBAX 1 (38486420) | B4: B.GRIMM Power (Leam Chabang) 2 Ltd. | C4: ใบแจ้งหนี้ | D4: Kwh | E4: =SUM(F4:Q4) | F4: 396689 | G4: 421188 | H4: 375540 | I4: 179888 | J4: 337638 | K4: 391507 | L4: 297730 | M4: 339396 | N4: 617131 | O4: 364367 | P4: 374402 | Q4: 352458
A5: โรงงาน 2 : MULTIBAX 2 (38486421) | B5: B.GRIMM Power (Leam Chabang) 2 Ltd. | C5: ใบแจ้งหนี้ | D5: Kwh | E5: =SUM(F5:Q5) | F5: 192523 | G5: 172985 | H5: 261500 | I5: 161156 | J5: 342525 | K5: 312308 | L5: 289479 | M5: 289238 | N5: 353855 | O5: 289241 | P5: 324452 | Q5: 279907
A6: โรงงาน 3 : MULTIBAX 3 (38486422) | B6: B.GRIMM Power (Leam Chabang) 2 Ltd. | C6: ใบแจ้งหนี้ | D6: Kwh | E6: =SUM(F6:Q6) | F6: 268656 | G6: 244025 | H6: 282428 | I6: 126483 | J6: 305790 | K6: 328801 | L6: 298659 | M6: 336884 | N6: 287843 | O6: 289617 | P6: 337676 | Q6: 291818
A7: การใช้ไฟฟ้า โรงงาน (4-5) (PEA) | C7: หนังสือแจ้งค่าไฟฟ้า | D7: Kwh | E7: =SUM(E9:E10)
A8: การใช้ไฟฟ้า โรงงาน 5 (Solar cell) | C8: SMA Solar Application | D8: Kwh | E8: =SUM(E11)
A9: โรงงาน 4 : 9846-020001853230 | B9: PEA | C9: หนังสือแจ้งค่าไฟฟ้า | D9: Kwh | E9: =SUM(F9:Q9) | F9: 20921.42 | G9: 29234.83 | H9: 25502.45 | I9: 24535.5 | J9: 28390.27 | K9: 29581.62 | L9: 31775.05 | M9: 33963.55 | N9: 26443.29 | O9: 24275.18 | P9: 28506.96 | Q9: 27514.71
A10: โรงงาน 5 : 9808-020002601835 | B10: PEA | C10: หนังสือแจ้งค่าไฟฟ้า | D10: Kwh | E10: =SUM(F10:Q10) | F10: 121592 | G10: 88168 | H10: 95592 | I10: 79488 | J10: 130208 | K10: 118536 | L10: 134056 | M10: 113136 | N10: 66472 | O10: 165256 | P10: 145344 | Q10: 100624
A11: โรงงาน 5 : Solar Rooftop F5 (265.4 KWP) | B11: MULTIBAX Own's Solar Rooftop | C11: SMA Solar Application | D11: Kwh | E11: =SUM(F11:Q11) | F11: 23780 | G11: 28380 | H11: 35420 | I11: 22240 | J11: 34750 | K11: 33020 | L11: 29460 | M11: 36580 | N11: 26350 | O11: 25790 | P11: 28550 | Q11: 23180
A12: การใช้ไฟฟ้า โกดังเช่า (PEA) | C12: หนังสือแจ้งค่าไฟฟ้า | D12: Kwh | E12: =SUM(E13:E14)
A13: โกดังเช่า (เขตประกอบการเสรี 1) : 9030-020024581960 | B13: PEA | C13: หนังสือแจ้งค่าไฟฟ้า | D13: Kwh | E13: =SUM(F13:Q13) | F13: 172.8 | G13: 175.2 | H13: 210.4 | I13: 194.4 | J13: 212.8 | K13: 192 | L13: 12
A14: โกดังเช่า (เขตประกอบการเสรี 2) : 9811-020026798136 | B14: PEA | C14: หนังสือแจ้งค่าไฟฟ้า | D14: Kwh | E14: =SUM(F14:Q14) | L14: 956.8 | M14: 2860 | N14: 1244 | O14: 1244 | P14: 584.8 | Q14: 427.2
A15: การใช้ไฟฟ้าของสำนักงาน กทม (MEA) | C15: ใบแจ้งค่าไฟฟ้า | D15: Kwh | E15: =SUM(E16:E17)
A16: สำนักงานกรุงเทพ บ้านเลขที่ 456 : 22055649 | B16: MEA | C16: ใบแจ้งค่าไฟฟ้า | D16: Kwh | E16: =SUM(F16:Q16) | F16: 3319 | G16: 3980 | H16: 3744 | I16: 3930 | J16: 4686 | K16: 4658 | L16: 4590 | M16: 4071 | N16: 4443 | O16: 3837 | P16: 4209 | Q16: 3891
A17: สำนักงานกรุงเทพ บ้านเลขที่ 458 : 22055650 | B17: MEA | C17: ใบแจ้งค่าไฟฟ้า | D17: Kwh | E17: =SUM(F17:Q17) | F17: 643 | G17: 814 | H17: 753 | I17: 908 | J17: 1036 | K17: 1003 | L17: 985 | M17: 874 | N17: 973 | O17: 805 | P17: 831 | Q17: 721
A19: หมายเหตุ: แนบภาพมิเตอร์ไฟฟ้าทุกจุดที่มีในโรงงาน/สำนักงาน
A20: * มิเตอร์ไฟฟ้าสำหรับโกดังเช่า (เขตประกอบการเสรี 1) : 9030-020024581960 ไม่สามารถหาภาพถ่ายได้ เนื่องจากยกเลิกสัญญาเช่าตั้งแต่ เดือนกรกฏาคม 2566
F22: โรงงาน 3 : MULTIBAX 3 (38486422)

Sheet Scope 3.1.1 วัตถุดิบผลิต
A2: รายการวัตถุดิบที่ใช้ | B2: กระบวนการผลิต | C2: สถานที่ใช้ | D2: หลักฐานอ้างอิง | E2: หน่วย | F2: TOTAL | G2: ชื่อผู้ขาย | H2: ปริมาณการใช้แต่ละเดือน/2566
F3: รวมทั้งสิ้น | H3: มกราคม | I3: กุมภาพันธ์ | J3: มีนาคม | K3: เมษายน | L3: พฤษภาคม | M3: มิถุนายน | N3: กรกฎาคม | O3: สิงหาคม | P3: กันยายน | Q3: ตุลาคม | R3: พฤศจิกายน | S3: ธันวาคม
A4: เม็ดพลาสติก LDPE | D4: ใบกำกับภาษี/ระบบ ERP | E4: Kg | F4: =SUM(F5:F6)
A5: วัตถุดิบชนิด : LDPE | B5: กระบวนการผสมวัตถุดิบ | C5: โรงงาน 1,2,3,5 | D5: ใบกำกับภาษี/ระบบ ERP | E5: Kg | F5: =SUM(H5:S5) | G5: BOROUGE PTE LTD. | N5: 297000 | O5: 198000 | P5: 297000 | Q5: 123750 | R5: 346500
A6: วัตถุดิบชนิด : LDPE | B6: กระบวนการผสมวัตถุดิบ | C6: โรงงาน 1,2,3,5 | D6: ใบกำกับภาษี/ระบบ ERP | E6: Kg | F6: =SUM(H6:S6) | G6: บริษัท พีทีที โกลบอล เคมิคอล จำกัด (มหาชน) | H6: 255000 | I6: 375000 | J6: 375000 | K6: 375000 | L6: 375000 | M6: 375000 | O6: 60000 | P6: 150000 | Q6: 45000 | R6: 135000 | S6: 105000
A7: เม็ดพลาสติก LLDPE | D7: ใบกำกับภาษี/ระบบ ERP | E7: Kg | F7: =SUM(F8:F11)
A8: วัตถุดิบชนิด : LLDPE | B8: กระบวนการผสมวัตถุดิบ | C8: โรงงาน 1,2,3,5 | D8: ใบกำกับภาษี/ระบบ ERP | E8: Kg | F8: =SUM(H8:S8) | G8: BOROUGE PTE LTD. | H8: 222750 | I8: 74250 | J8: 222750 | K8: 222750 | L8: 148500 | M8: 222750 | N8: 297000 | Q8: 148500
A9: วัตถุดิบชนิด : LLDPE | B9: กระบวนการผสมวัตถุดิบ | C9: โรงงาน 1,2,3,5 | D9: ใบกำกับภาษี/ระบบ ERP | E9: Kg | F9: =SUM(H9:S9) | G9: EQUATE Petrochemical Company K.S.C.C. | H9: 767250 | I9: 198000 | L9: 99000 | N9: 99000 | O9: 99000 | P9: 396000 | R9: 198000 | S9: 247500
A10: วัตถุดิบชนิด : LLDPE | B10: กระบวนการผสมวัตถุดิบ | C10: โรงงาน 1,2,3,5 | D10: ใบกำกับภาษี/ระบบ ERP | E10: Kg | F10: =SUM(H10:S10) | G10: บริษัท ไทยโพลิเอททีลีน จำกัด | I10: 15000 | L10: 15000 | P10: 15000 | R10: 15000
A11: วัตถุดิบชนิด : LLDPE | B11: กระบวนการผสมวัตถุดิบ | C11: โรงงาน 1,2,3,5 | D11: ใบกำกับภาษี/ระบบ ERP | E11: Kg | F11: =SUM(H11:S11) | G11: บริษัท พีทีที โกลบอล เคมิคอล จำกัด (มหาชน) | H11: 15000 | O11: 15000
A12: เม็ดพลาสติก HDPE | D12: ใบกำกับภาษี/ระบบ ERP | E12: Kg | F12: =SUM(F13:F14)
A13: วัตถุดิบชนิด : HDPE | B13: กระบวนการผสมวัตถุดิบ | C13: โรงงาน 1,2,3,5 | D13: ใบกำกับภาษี/ระบบ ERP | E13: Kg | F13: =SUM(H13:S13) | G13: EQUATE Petrochemical Company K.S.C.C. | N13: 24750 | S13: 49500
A14: วัตถุดิบชนิด : HDPE | B14: กระบวนการผสมวัตถุดิบ | C14: โรงงาน 1,2,3,5 | D14: ใบกำกับภาษี/ระบบ ERP | E14: Kg | F14: =SUM(H14:S14) | G14: บริษัท ไทยโพลิเอททีลีน จำกัด | H14: 30000 | I14: 90000 | J14: 90000 | K14: 30000 | L14: 45000 | M14: 90000 | N14: 45000 | O14: 45000 | P14: 60000 | Q14: 75000 | R14: 90000 | S14: 105000
A15: กระดาษกล่องแป้งหลังเทา | D15: ใบกำกับภาษี/ระบบ ERP | E15: Kg | F15: =SUM(F16:F18)
A16: =A79 | B16: =B79 | C16: โรงงาน 1,2,3,5 | D16: ใบกำกับภาษี/ระบบ ERP | E16: =E79 | F16: =F79 | G16: =G79 | H16: =H79 | I16: =I79 | J16: =J79 | K16: =K79 | L16: =L79 | ... S16: =S79
A17: =A80 | B17: =B80 | C17: โรงงาน 1,2,3,5 | D17: ใบกำกับภาษี/ระบบ ERP | E17: =E80 | F17: =F80 | G17: =G80 | H17: =H80 | I17: =I80 | J17: =J80 | K17: =K80 | L17: =L80 | ... S17: =S80
A18: =A81 | B18: =B81 | C18: โรงงาน 1,2,3,5 | D18: ใบกำกับภาษี/ระบบ ERP | E18: =E81 | F18: =F81 | G18: =G81 | H18: =H81 | I18: =I81 | J18: =J81 | K18: =K81 | L18: =L81 | ... S18: =S81
A19: กระดาษคราฟท์ ชนิดทาลอน | D19: ใบกำกับภาษี/ระบบ ERP | E19: Kg | F19: =SUM(F20:F24)
A20: =A82 | B20: =B82 | C20: โรงงาน 1,2,3,5 | D20: ใบกำกับภาษี/ระบบ ERP | E20: =E82 | F20: =F82 | G20: =G82 | H20: 205.275 | I20: 4102.184 | J20: 4773.39 | K20: 4393.636 | L20: 7258.481 | M20: 11263.31 | N20: 9333.798 | O20: 9803.64 | P20: 14696.655 | Q20: 12131.504 | R20: 10727.902 | S20: 6085.597
A21: =A83 | B21: =B83 | C21: โรงงาน 1,2,3,5 | D21: ใบกำกับภาษี/ระบบ ERP | E21: =E83 | F21: =F83 | G21: =G83 | H21: 29647.315 | I21: 31891.753 | J21: 34086.952 | K21: 12368.174 | L21: 31471.975 | M21: 40571.31 | N21: 32534.58 | O21: 47329.815 | P21: 30237.795 | Q21: 44144.949 | R21: 57992.322 | S21: 31606.817
A22: =A84 | B22: =B84 | C22: โรงงาน 1,2,3,5 | D22: ใบกำกับภาษี/ระบบ ERP | E22: =E84 | F22: =F84 | G22: =G84 | H22: 22459.65 | I22: 21515.392 | J22: 24639.293 | K22: 16926.28 | L22: 40608.392 | M22: 28433.09 | N22: 22674.177 | O22: 21616.8 | P22: 14048.225 | Q22: 15446.786 | R22: 21501.46 | S22: 18237.66
A23: =A85 | B23: =B85 | C23: โรงงาน 1,2,3,5 | D23: ใบกำกับภาษี/ระบบ ERP | E23: =E85 | F23: =F85 | G23: =G85 | H23: 620 | I23: 4336.416 | J23: 1005 | K23: 1869.654 | L23: 1239.16 | M23: 5049.5 | N23: 5514.589 | O23: 1116.018 | P23: 4728.552 | Q23: 4307.486 | R23: 3978.826 | S23: 2684.05
A24: =A86 | B24: =B86 | C24: โรงงาน 1,2,3,5 | D24: ใบกำกับภาษี/ระบบ ERP | E24: =E86 | F24: =F86 | G24: =G86 | H24: 2564.531 | I24: 4196.985 | J24: 1981 | K24: 398.3 | L24: 933 | M24: 852.1 | N24: 1088.365 | O24: 3131.23 | P24: 1941.2 | Q24: 3882.4 | R24: 2099.2 | S24: 1789.13
A27: สรุปรายการวัตถุดิบ
A28: รายการ | B28: หน่วย | C28: น้ำหนัก
A29: วัตถุดิบชนิด : LDPE | B29: Kg | C29: =SUM(F52:F53) | D29: =C29/$C$47*100 | E29: =SUM(D29:D32)
A30: วัตถุดิบชนิด : LLDPE | B30: Kg | C30: =SUM(F54:F57) | D30: =C30/$C$47*100
A31: วัตถุดิบชนิด : HDPE | B31: Kg | C31: =SUM(F58:F59) | D31: =C31/$C$47*100
A32: บรรจุภัณฑ์ : กระดาษ | B32: Kg | C32: =SUM(F79:F86) | D32: =C32/$C$47*100
A33: วัตถุดิบชนิด : Braskem (HDPE) | B33: Kg | C33: =SUM(F60:F61) | D33: =C33/$C$47*100
A34: วัตถุดิบชนิด : PCR | B34: Kg | C34: =SUM(F62:F64) | D34: =C34/$C$47*100
A35: วัตถุดิบชนิด : Masterbatch | B35: Kg | C35: =SUM(F65:F68) | D35: =C35/$C$47*100
A36: วัตถุดิบชนิด : Calcium | B36: Kg | C36: =SUM(F69) | D36: =C36/$C$47*100
A37: วัตถุดิบชนิด : Ink | B37: Kg | C37: =SUM(F70:F72) | D37: =C37/$C$47*100
A38: วัตถุดิบชนิด : Additive | B38: Kg | C38: =SUM(F73:F75) | D38: =C38/$C$47*100
A39: วัตถุดิบชนิด : Fragrance | B39: Kg | C39: =SUM(F76:F77) | D39: =C39/$C$47*100
A40: วัตถุดิบชนิด : Bio | B40: Kg | C40: =SUM(F78) | D40: =C40/$C$47*100
A41: วัสดุสิ้นเปลือง : Solvent | B41: Kg | C41: =SUM(F87) | D41: =C41/$C$47*100
A42: วัสดุสิ้นเปลือง : เทปใส | B42: Kg | C42: =SUM(F88:F89) | D42: =C42/$C$47*100
A43: วัสดุสิ้นเปลือง : กาว | B43: Kg | C43: =SUM(F90:F92) | D43: =C43/$C$47*100
A44: วัสดุสิ้นเปลือง : น้ำมัน Food Grade | B44: Kg | C44: =SUM(F93) | D44: =C44/$C$47*100
A45: วัสดุสิ้นเปลือง : ฟิล์มยืด | B45: Kg | C45: =SUM(F94:F95) | D45: =C45/$C$47*100
A46: วัสดุสิ้นเปลือง : ฟิล์มหด | B46: Kg | C46: =SUM(F96) | D46: =C46/$C$47*100
C47: =SUM(C29:C46)
A49: รายการวัตถุดิบ
A50: รายการวัตถุดิบที่ใช้ | B50: กระบวนการผลิต | C50: สถานที่ใช้ | D50: หลักฐานอ้างอิง | E50: หน่วย | F50: TOTAL | G50: ชื่อผู้ขาย | H50: ปริมาณการใช้แต่ละเดือน/2566
F51: รวมทั้งสิ้น | H51: มกราคม | I51: กุมภาพันธ์ | J51: มีนาคม | K51: เมษายน | L51: พฤษภาคม | M51: มิถุนายน | N51: กรกฎาคม | O51: สิงหาคม | P51: กันยายน | Q51: ตุลาคม | R51: พฤศจิกายน | S51: ธันวาคม
A52: วัตถุดิบชนิด : LDPE | B52: กระบวนการผสมวัตถุดิบ | C52: โรงงาน 1,2,35 | D52: ใบสั่งซื้อ/ใบกำกับภาษี | E52: Kg | F52: =SUM(H52:S52) | G52: BOROUGE PTE LTD. | N52: 297000 | O52: 198000 | P52: 297000 | Q52: 123750 | R52: 346500
A53: วัตถุดิบชนิด : LDPE | B53: กระบวนการผสมวัตถุดิบ | C53: โรงงาน 1,2,35 | D53: ใบสั่งซื้อ/ใบกำกับภาษี | E53: Kg | F53: =SUM(H53:S53) | G53: บริษัท พีทีที โกลบอล เคมิคอล จำกัด (มหาชน) | H53: 255000 | I53: 375000 | J53: 375000 | K53: 375000 | L53: 375000 | M53: 375000 | O53: 60000 | P53: 150000 | Q53: 45000 | R53: 135000 | S53: 105000
A54: วัตถุดิบชนิด : LLDPE | B54: กระบวนการผสมวัตถุดิบ | C54: โรงงาน 1,2,35 | D54: ใบสั่งซื้อ/ใบกำกับภาษี | E54: Kg | F54: =SUM(H54:S54) | G54: BOROUGE PTE LTD. | H54: 222750 | I54: 74250 | J54: 222750 | K54: 222750 | L54: 148500 | M54: 222750 | N54: 297000 | Q54: 148500
A55: วัตถุดิบชนิด : LLDPE | B55: กระบวนการผสมวัตถุดิบ | C55: โรงงาน 1,2,35 | D55: ใบสั่งซื้อ/ใบกำกับภาษี | E55: Kg | F55: =SUM(H55:S55) | G55: EQUATE Petrochemical Company K.S.C.C. | H55: 767250 | I55: 198000 | L55: 99000 | N55: 99000 | O55: 99000 | P55: 396000 | R55: 198000 | S55: 247500
A56: วัตถุดิบชนิด : LLDPE | B56: กระบวนการผสมวัตถุดิบ | C56: โรงงาน 1,2,35 | D56: ใบสั่งซื้อ/ใบกำกับภาษี | E56: Kg | F56: =SUM(H56:S56) | G56: บริษัท ไทยโพลิเอททีลีน จำกัด | I56: 15000 | L56: 15000 | P56: 15000 | R56: 15000
A57: วัตถุดิบชนิด : LLDPE | B57: กระบวนการผสมวัตถุดิบ | C57: โรงงาน 1,2,35 | D57: ใบสั่งซื้อ/ใบกำกับภาษี | E57: Kg | F57: =SUM(H57:S57) | G57: บริษัท พีทีที โกลบอล เคมิคอล จำกัด (มหาชน) | H57: 15000 | O57: 15000
A58: วัตถุดิบชนิด : HDPE | B58: กระบวนการผสมวัตถุดิบ | C58: โรงงาน 1,2,35 | D58: ใบสั่งซื้อ/ใบกำกับภาษี | E58: Kg | F58: =SUM(H58:S58) | G58: EQUATE Petrochemical Company K.S.C.C. | N58: 24750 | S58: 49500
A59: วัตถุดิบชนิด : HDPE | B59: กระบวนการผสมวัตถุดิบ | C59: โรงงาน 1,2,35 | D59: ใบสั่งซื้อ/ใบกำกับภาษี | E59: Kg | F59: =SUM(H59:S59) | G59: บริษัท ไทยโพลิเอททีลีน จำกัด | H59: 30000 | I59: 90000 | J59: 90000 | K59: 30000 | L59: 45000 | M59: 90000 | N59: 45000 | O59: 45000 | P59: 60000 | Q59: 75000 | R59: 90000 | S59: 105000
A60: วัตถุดิบชนิด : Braskem (HDPE) | B60: กระบวนการผสมวัตถุดิบ | C60: โรงงาน 1,2,35 | D60: ใบสั่งซื้อ/ใบกำกับภาษี | E60: Kg | F60: =SUM(H60:S60) | G60: SOJITZ PLA-NET CORPORATION | Q60: 49500 | S60: 24750
A61: วัตถุดิบชนิด : Braskem (HDPE) | B61: กระบวนการผสมวัตถุดิบ | C61: โรงงาน 1,2,35 | D61: ใบสั่งซื้อ/ใบกำกับภาษี | E61: Kg | F61: =SUM(H61:S61) | G61: SOJITZ PLA-NET CORPORATION OSAKA BRANCH | P61: 24750 | Q61: 24750
A62: วัตถุดิบชนิด : PCR | B62: กระบวนการผสมวัตถุดิบ | C62: โรงงาน 1,2,35 | D62: ใบสั่งซื้อ/ใบกำกับภาษี | E62: Kg | F62: =SUM(H62:S62) | G62: BOROUGE PTE LTD. | K62: 22000 | S62: 212000
A63: วัตถุดิบชนิด : PCR | B63: กระบวนการผสมวัตถุดิบ | C63: โรงงาน 1,2,35 | D63: ใบสั่งซื้อ/ใบกำกับภาษี | E63: Kg | F63: =SUM(H63:S63) | G63: Kingfa Environmental Sci. & Tech. Co.,Ltd. | R63: 12800
A64: วัตถุดิบชนิด : PCR | B64: กระบวนการผสมวัตถุดิบ | C64: โรงงาน 1,2,35 | D64: ใบสั่งซื้อ/ใบกำกับภาษี | E64: Kg | F64: =SUM(H64:S64) | G64: บริษัท ไทยโพลิเอททีลีน จำกัด | P64: 600
A65: วัตถุดิบชนิด : Masterbatch | B65: กระบวนการผสมวัตถุดิบ | C65: โรงงาน 1,2,35 | D65: ใบสั่งซื้อ/ใบกำกับภาษี | E65: Kg | F65: =SUM(H65:S65) | G65: AMPACET (Thailand) Co., Ltd. | H65: 3099 | I65: 100 | J65: 1050 | K65: 100 | L65: 5250 | M65: 4095 | N65: 1748 | O65: 2619 | P65: 2300 | Q65: 350 | R65: 5793 | S65: 700
A66: วัตถุดิบชนิด : Masterbatch | B66: กระบวนการผสมวัตถุดิบ | C66: โรงงาน 1,2,35 | D66: ใบสั่งซื้อ/ใบกำกับภาษี | E66: Kg | F66: =SUM(H66:S66) | G66: บริษัท ทีเอช คัลเล่อร์ จำกัด | H66: 33546.5 | I66: 22268.2 | J66: 13845.3 | K66: 8047.1 | L66: 16746.8 | M66: 14698.4 | N66: 15495.3 | O66: 7745 | P66: 20219.4 | Q66: 19594.4 | R66: 19692.7 | S66: 21995
A67: วัตถุดิบชนิด : Masterbatch | B67: กระบวนการผสมวัตถุดิบ | C67: โรงงาน 1,2,35 | D67: ใบสั่งซื้อ/ใบกำกับภาษี | E67: Kg | F67: =SUM(H67:S67) | G67: บริษัท เอเวียนท์ (ประเทศไทย) จำกัด | I67: 300 | J67: 250 | K67: 350 | L67: 300 | M67: 300 | N67: 300 | O67: 600 | Q67: 300 | R67: 500 | S67: 300
A68: วัตถุดิบชนิด : Masterbatch | B68: กระบวนการผสมวัตถุดิบ | C68: โรงงาน 1,2,35 | D68: ใบสั่งซื้อ/ใบกำกับภาษี | E68: Kg | F68: =SUM(H68:S68) | G68: บริษัท เอเวียนท์ คัลเลอร์แร้นท์ (ประเทศไทย) จำกัด | H68: 25 | I68: 300 | K68: 273.4 | L68: 675 | O68: 571.8 | R68: 299.4 | S68: 296.6
A69: วัตถุดิบชนิด : Calcium | B69: กระบวนการผสมวัตถุดิบ | C69: โรงงาน 1,2,35 | D69: ใบสั่งซื้อ/ใบกำกับภาษี | E69: Kg | F69: =SUM(H69:S69) | G69: บริษัท ทีเอช คัลเล่อร์ จำกัด | H69: 16250 | I69: 12100 | J69: 11450 | K69: 6000 | L69: 10050 | M69: 11100 | N69: 10900 | O69: 6000 | P69: 14425 | Q69: 18400 | R69: 12150 | S69: 13600
A70: วัตถุดิบชนิด : Ink | B70: กระบวนการผสมวัตถุดิบ | C70: โรงงาน 1,2,35 | D70: ใบสั่งซื้อ/ใบกำกับภาษี | E70: Kg | F70: =SUM(H70:S70) | G70: SIEGWERK (THAILAND) LTD. | H70: 355 | I70: 30 | J70: 60 | L70: 275 | M70: 505 | N70: 15 | O70: 160 | P70: 100 | Q70: 355 | S70: 150
A71: วัตถุดิบชนิด : Ink | B71: กระบวนการผสมวัตถุดิบ | C71: โรงงาน 1,2,35 | D71: ใบสั่งซื้อ/ใบกำกับภาษี | E71: Kg | F71: =SUM(H71:S71) | G71: บริษัท พาโนราม่า อิ้งค์ จำกัด | I71: 604 | J71: 304 | L71: 400 | M71: 300 | N71: 300 | R71: 300 | S71: 120
A72: วัตถุดิบชนิด : Ink | B72: กระบวนการผสมวัตถุดิบ | C72: โรงงาน 1,2,35 | D72: ใบสั่งซื้อ/ใบกำกับภาษี | E72: Kg | F72: =SUM(H72:S72) | G72: บริษัท อีเทอนอล ซากาตะ อิ้งซ์ จำกัด | H72: 3972 | I72: 2954 | J72: 4902 | K72: 2952 | L72: 6806 | M72: 5982 | N72: 5764 | O72: 5590 | P72: 6704 | Q72: 7230 | R72: 6038 | S72: 4036
A73: วัตถุดิบชนิด : Additive | B73: กระบวนการผสมวัตถุดิบ | C73: โรงงาน 1,2,35 | D73: ใบสั่งซื้อ/ใบกำกับภาษี | E73: Kg | F73: =SUM(H73:S73) | G73: AMPACET (Thailand) Co., Ltd. | I73: 1000 | J73: 2500 | L73: 1000 | M73: 2700 | N73: 1100 | O73: 2400 | P73: 1050 | Q73: 2800 | R73: 1450 | S73: 3100
A74: วัตถุดิบชนิด : Additive | B74: กระบวนการผสมวัตถุดิบ | C74: โรงงาน 1,2,35 | D74: ใบสั่งซื้อ/ใบกำกับภาษี | E74: Kg | F74: =SUM(H74:S74) | G74: Symphony Environmental Ltd. | I74: 1000 | K74: 1375 | L74: 2000 | N74: 1250 | R74: 2250
A75: วัตถุดิบชนิด : Additive | B75: กระบวนการผสมวัตถุดิบ | C75: โรงงาน 1,2,35 | D75: ใบสั่งซื้อ/ใบกำกับภาษี | E75: Kg | F75: =SUM(H75:S75) | G75: บริษัท ซันนา เซอเทรด จำกัด | K75: 12715 | S75: 12715
A76: วัตถุดิบชนิด : Fragrance | B76: กระบวนการผสมวัตถุดิบ | C76: โรงงาน 1,3 | D76: ใบสั่งซื้อ/ใบกำกับภาษี | E76: Kg | F76: =SUM(H76:S76) | G76: International Flavor & Fragrances (Thailand) Ltd. | P76: 380 | R76: 380
A77: วัตถุดิบชนิด : Fragrance | B77: กระบวนการผสมวัตถุดิบ | C77: โรงงาน 1,3 | D77: ใบสั่งซื้อ/ใบกำกับภาษี | E77: Kg | F77: =SUM(H77:S77) | G77: International Flavors & Fragrances Inc. | H77: 200 | J77: 200 | K77: 700 | L77: 3500 | M77: 200 | N77: 1500 | P77: 4400 | Q77: 100
A78: วัตถุดิบชนิด : Bio | B78: กระบวนการผสมวัตถุดิบ | C78: โรงงาน 5 | D78: ใบสั่งซื้อ/ใบกำกับภาษี | E78: Kg | F78: =SUM(H78:S78) | G78: Chemical Innovation Co.,Ltd. | H78: 200 | M78: 300
A79: กระดาษกล่องแป้งหลังเทา (EF597) | B79: การบรรจุ | C79: โรงงาน 1,2,35 | D79: ใบสั่งซื้อ/ใบกำกับภาษี | E79: Kg | F79: =SUM(H79:S79) | G79: บริษัท เค.อาร์.ที. แพค แอนด์ ซัพพลาย จำกัด | H79: 8637.27 | I79: 14898.16 | J79: 38001.372 | K79: 29176.53 | L79: 17209.19 | M79: 21197.48 | N79: 9096.9 | O79: 15680.76 | P79: 4173.256 | Q79: 16213.348 | R79: 26229.134 | S79: 18914.038
A80: กระดาษกล่องแป้งหลังเทา (EF597) | B80: การบรรจุ | C80: โรงงาน 1,2,35 | D80: ใบสั่งซื้อ/ใบกำกับภาษี | E80: Kg | F80: =SUM(H80:S80) | G80: บริษัท เหรียญทองการพิมพ์ จำกัด | H80: 1400.1 | I80: 960 | J80: 1380 | K80: 0 | L80: 0 | M80: 0 | N80: 0 | O80: 640 | P80: 1380 | Q80: 960 | R80: 0 | S80: 0
A81: กระดาษกล่องแป้งหลังเทา (EF597) | B81: การบรรจุ | C81: โรงงาน 1,2,35 | D81: ใบสั่งซื้อ/ใบกำกับภาษี | E81: Kg | F81: =SUM(H81:S81) | G81: บริษัท สำราญจิตต์การพิมพ์ จำกัด | H81: 54667.88 | I81: 58140.336 | J81: 47572.52 | K81: 26476.752 | L81: 78932.952 | M81: 65650.024 | N81: 70489.484 | O81: 78357.414 | P81: 56931.32 | Q81: 67031.298 | R81: 71114.556 | S81: 48161.62
A82: กระดาษคราฟท์ ชนิดทำลอน (EF596) | B82: การบรรจุ | C82: โรงงาน 1,2,35 | D82: ใบสั่งซื้อ/ใบกำกับภาษี | E82: Kg | F82: =SUM(H82:S82) | G82: บริษัท เค.อาร์.ที. แพค แอนด์ ซัพพลาย จำกัด | H82: 205.275 | I82: 4102.184 | J82: 4773.39 | K82: 4393.636 | L82: 7258.481 | M82: 11263.31 | N82: 9333.798 | O82: 9803.64 | P82: 14696.655 | Q82: 12131.504 | R82: 10727.902 | S82: 6085.597
A83: กระดาษคราฟท์ ชนิดทำลอน (EF596) | B83: การบรรจุ | C83: โรงงาน 1,2,35 | D83: ใบสั่งซื้อ/ใบกำกับภาษี | E83: Kg | F83: =SUM(H83:S83) | G83: บริษัท เอส.พี.ที.แพ็คกิ้งกรุ๊ป จำกัด | H83: 29647.315 | I83: 31891.753 | J83: 34086.952 | K83: 12368.174 | L83: 31471.975 | M83: 40571.31 | N83: 32534.58 | O83: 47329.815 | P83: 30237.795 | Q83: 44144.949 | R83: 57992.322 | S83: 31606.817
A84: กระดาษคราฟท์ ชนิดทำลอน (EF596) | B84: การบรรจุ | C84: โรงงาน 1,2,35 | D84: ใบสั่งซื้อ/ใบกำกับภาษี | E84: Kg | F84: =SUM(H84:S84) | G84: บริษัท บรรเจิดบรรจุภัณฑ์ จำกัด | H84: 22459.65 | I84: 21515.392 | J84: 24639.293 | K84: 16926.28 | L84: 40608.392 | M84: 28433.09 | N84: 22674.177 | O84: 21616.8 | P84: 14048.225 | Q84: 15446.786 | R84: 21501.46 | S84: 18237.66
A85: กระดาษคราฟท์ ชนิดทำลอน (EF596) | B85: การบรรจุ | C85: โรงงาน 1,2,35 | D85: ใบสั่งซื้อ/ใบกำกับภาษี | E85: Kg | F85: =SUM(H85:S85) | G85: บริษัท บาแล็นซ์ แพ็คกิ้ง จำกัด | H85: 620 | I85: 4336.416 | J85: 1005 | K85: 1869.654 | L85: 1239.16 | M85: 5049.5 | N85: 5514.589 | O85: 1116.018 | P85: 4728.552 | Q85: 4307.486 | R85: 3978.826 | S85: 2684.05
A86: กระดาษคราฟท์ ชนิดทำลอน (EF596) | B86: การบรรจุ | C86: โรงงาน 1,2,35 | D86: ใบสั่งซื้อ/ใบกำกับภาษี | E86: Kg | F86: =SUM(H86:S86) | G86: ห้างหุ้นส่วนจำกัด อชราบรรจุภัณฑ์ | H86: 2564.531 | I86: 4196.985 | J86: 1981 | K86: 398.3 | L86: 933 | M86: 852.1 | N86: 1088.365 | O86: 3131.23 | P86: 1941.2 | Q86: 3882.4 | R86: 2099.2 | S86: 1789.13
A87: วัสดุสิ้นเปลือง : Solvent | C87: โรงงาน 1,2,35 | D87: ใบสั่งซื้อ/ใบกำกับภาษี | E87: Kg | F87: =SUM(H87:S87) | G87: บริษัท เอ็มซี อินดัสเทรียลเคมิคัล จำกัด | I87: 850 | M87: 850 | O87: 850 | Q87: 850
A88: วัสดุสิ้นเปลือง : เทปใส | B88: การบรรจุ | C88: โรงงาน 1,2,35 | D88: ใบสั่งซื้อ/ใบกำกับภาษี | E88: Kg | F88: =SUM(H88:S88) | G88: บริษัท โชคเจริญ 2020 จำกัด | I88: 492.48 | L88: 492.48 | N88: 492.48 | O88: 492.48 | Q88: 984.96
A89: วัสดุสิ้นเปลือง : เทปใส | B89: การบรรจุ | C89: โรงงาน 1,2,35 | D89: ใบสั่งซื้อ/ใบกำกับภาษี | E89: Kg | F89: =SUM(H89:S89) | G89: บริษัท บางบอนอุตสาหกรรม จำกัด | H89: 461.7 | K89: 461.7 | M89: 461.7 | N89: 461.7 | P89: 461.7 | R89: 461.7 | S89: 461.7
A90: วัสดุสิ้นเปลือง : กาว | B90: การบรรจุ | C90: โรงงาน 1,2,35 | D90: ใบสั่งซื้อ/ใบกำกับภาษี | E90: Kg | F90: =SUM(H90:S90) | G90: บริษัท เปอร์มาเฟล็กซ์ จำกัด | K90: 550 | L90: 550 | M90: 500 | O90: 550 | Q90: 550 | S90: 550
A91: วัสดุสิ้นเปลือง : กาว | B91: การบรรจุ | C91: โรงงาน 1,2,35 | D91: ใบสั่งซื้อ/ใบกำกับภาษี | E91: Kg | F91: =SUM(H91:S91) | G91: บริษัท โพลีพลาส พรีซีชั่น จำกัด | H91: 2000 | I91: 1500 | J91: 1000 | K91: 1000 | L91: 1000 | M91: 2000 | N91: 1000 | P91: 1000 | Q91: 1000 | R91: 1000 | S91: 2000
A92: วัสดุสิ้นเปลือง : กาว | B92: การบรรจุ | C92: โรงงาน 1,2,35 | D92: ใบสั่งซื้อ/ใบกำกับภาษี | E92: Kg | F92: =SUM(H92:S92) | G92: บริษัท จาคานา จำกัด | N92: 1000 | O92: 1000
A93: วัสดุสิ้นเปลือง : น้ำมัน Food Grade | C93: โรงงาน 1,2,35 | D93: ใบสั่งซื้อ/ใบกำกับภาษี | E93: Kg | F93: =SUM(H93:S93) | G93: บริษัท อเมริกัน ปิโตรเคมิคอล (ประเทศไทย) จำกัด | H93: 90 | I93: 90 | J93: 90 | L93: 144 | M93: 90 | N93: 90 | O93: 90 | P93: 90 | Q93: 90
A94: วัสดุสิ้นเปลือง : ฟิล์มยืด | B94: การบรรจุ | C94: โรงงาน 1,2,35 | D94: ใบสั่งซื้อ/ใบกำกับภาษี | E94: Kg | F94: =SUM(H94:S94) | G94: บริษัท เอ็มเอ็มพี คอร์ปอเรชั่น จำกัด | M94: 1242 | N94: 1932 | O94: 690 | P94: 2484
A95: วัสดุสิ้นเปลือง : ฟิล์มยืด | B95: การบรรจุ | C95: โรงงาน 1,2,35 | D95: ใบสั่งซื้อ/ใบกำกับภาษี | E95: Kg | F95: =SUM(H95:S95) | G95: บริษัท วัฒนพันธุ์แพคเกจจิ้งซิสเท็ม จำกัด | H95: 2484 | I95: 1242 | J95: 690 | L95: 1242 | O95: 1242 | Q95: 690 | R95: 1242 | S95: 1932
A96: วัสดุสิ้นเปลือง : ฟิล์มหด | B96: การบรรจุ | C96: โรงงาน 1,2,35 | D96: ใบสั่งซื้อ/ใบกำกับภาษี | E96: Kg | F96: =SUM(H96:S96) | G96: บริษัท เค.เอ.มาร์เก็ตติ้ง จำกัด | Q96: 658

Sheet Scope 3.1.2 น้ำประปา
A2: รายการ | B2: ตำแหน่งที่ตั้งของมิเตอร์ | C2: หลักฐาน | D2: หน่วย | E2: รวม | F2: 243254 | G2: 243285 | H2: 243313 | I2: 243344 | J2: 243374 | K2: 243405 | L2: 243435 | M2: 243466 | N2: 243497 | O2: 243527 | P2: 243558 | Q2: 243588
A3: น้ำประปา (การนิคมฯ) | C3: ใบเสร็จ/ใบแจ้งหนี้ค่าประปา | D3: m3 | E3: =SUM(E4:E7)
A4: น้ำประปาการนิคม | B4: โรงงาน1,2 | C4: ใบเสร็จ/ใบแจ้งหนี้ค่าประปา | D4: m3 | E4: =SUM(F4:Q4) | F4: 1281 | G4: 1970 | H4: 1872 | I4: 1225 | J4: 2031 | K4: 1884 | L4: 1595 | M4: 3128 | N4: 1810 | O4: 1499 | P4: 2484 | Q4: 1024
A5: น้ำประปาการนิคม | B5: โรงงาน 5 | C5: ใบเสร็จ/ใบแจ้งหนี้ค่าประปา | D5: m3 | E5: =SUM(F5:Q5) | F5: 1650 | G5: 1335 | H5: 1493 | I5: 1432 | J5: 1745 | K5: 1766 | L5: 1644 | M5: 1658 | N5: 1540 | O5: 1599 | P5: 1613 | Q5: 1616
A6: น้ำประปาการนิคม | B6: โรงงาน 3 | C6: ใบเสร็จ/ใบแจ้งหนี้ค่าประปา | D6: m3 | E6: =SUM(F6:Q6) | F6: 1234 | G6: 888 | H6: 925 | I6: 792 | J6: 1334 | K6: 1020 | L6: 878 | M6: 883 | N6: 770 | O6: 761 | P6: 816 | Q6: 894
A7: น้ำประปาการนิคม | B7: โรงงาน 4 | C7: ใบเสร็จ/ใบแจ้งหนี้ค่าประปา | D7: m3 | E7: =SUM(F7:Q7) | F7: 636 | G7: 569 | H7: 606 | I7: 363 | J7: 387 | K7: 480 | L7: 487 | M7: 585 | N7: 507 | O7: 443 | P7: 631 | Q7: 580
A8: น้ำประปา (กปน) | C8: ใบเสร็จ/ใบแจ้งหนี้ค่าประปา | D8: m3 | E8: =SUM(E9:E10)
A9: น้ำประปานครหลวง | B9: อาคาร 456 | C9: ใบเสร็จ/ใบแจ้งหนี้ค่าประปา | D9: m3 | E9: 465 | F9: 38 | G9: 42 | H9: 35 | I9: 29 | J9: 38 | K9: 30 | L9: 47 | M9: 40 | N9: 47 | O9: 44 | P9: 39 | Q9: 36
A10: น้ำประปานครหลวง | B10: อาคาร 458 | C10: ใบเสร็จ/ใบแจ้งหนี้ค่าประปา | D10: m3 | E10: 294 | F10: 26 | G10: 22 | H10: 21 | I10: 36 | J10: 19 | K10: 18 | L10: 19 | M10: 16 | N10: 18 | O10: 18 | P10: 31 | Q10: 50
A14: หมายเหตุ: แนบภาพมิเตอร์น้ำประปาทุกจุดที่มีในโรงงาน/สำนักงาน
A15: โรงงาน 1 2 5 | B15: น53(4)-2/2541-ญนฉ.
A16: โรงงาน 3 4 7 | B16: น53(4)-4/2545-ญนฉ.

Sheet Scope 3.1.3 กระดาษ A4
A3: รายการวัตถุดิบที่ใช้ | B3: หลักฐาน | C3: หน่วย | D3: รวม | E3: ปริมาณการใช้แต่ละเดือน/2566
E4: 243254 | F4: 243285 | G4: 243313 | H4: 243344 | I4: 243374 | J4: 243405 | K4: 243435 | L4: 243466 | M4: 243497 | N4: 243527 | O4: 243558 | P4: 243588
A5: กระดาษ A4 70 แกรม | B5: ใบสั่งซื้อ | C5: kg | D5: =SUM(D6:D7)*B19
A6: กระดาษ A4 70 แกรม-BKK | D6: =SUM(E6:P6) | E6: 0 | F6: 0 | G6: 0 | H6: 0 | I6: 0 | J6: 0 | K6: 0 | L6: 0 | M6: 0 | N6: 0 | O6: 0 | P6: 0
A7: กระดาษ A4 70 แกรม-LCB | D7: =SUM(E7:P7) | E7: 0 | F7: 0 | G7: 20 | H7: 0 | I7: 0 | J7: 40 | K7: 0 | L7: 0 | M7: 40 | N7: 0 | O7: 50 | P7: 70
A8: กระดาษ A4 80 แกรม | B8: ใบสั่งซื้อ | C8: kg | D8: =SUM(D9:D10)*B20
A9: กระดาษ A4 80 แกรม-BKK | D9: =SUM(E9:P9) | E9: 0 | F9: 0 | G9: 0 | H9: 100 | I9: 0 | J9: 0 | K9: 0 | L9: 0 | M9: 0 | N9: 0 | O9: 100 | P9: 0
A10: กระดาษ A4 80 แกรม-LCB | D10: =SUM(E10:P10) | E10: 70 | F10: 100 | G10: 70 | H10: 100 | I10: 0 | J10: 200 | K10: 100 | L10: 100 | M10: 100 | N10: 0 | O10: 100 | P10: 80
A13: รายการ | B13: ค่า | C13: หน่วย
A14: พื้นที่กระดาษ (21.0 cm x 29.7 cm) | B14: =21*29.7 | C14: cm2/แผ่น
B15: =B14/10000 | C15: m2/แผ่น
A16: น้ำหนักกระดาษ 70 แกรม | B16: 70 | C16: g/m2
A17: น้ำหนักกระดาษ 80 แกรม | B17: 80 | C17: g/m2
A18: จำนวนกระดาษ | B18: 500 | C18: แผ่น/รีม
A19: น้ำหนักกระดาษ A4 70 g | B19: =B15*B18*B16/1000 | C19: kg/รีม
A20: น้ำหนักกระดาษ A4 80 g | B20: =B15*B18*B17/1000 | C20: kg/รีม

Sheet Scope 3.1.4 จ้างเหมารถพนักงาน
A2: สายรถ | B2: ต้นทาง | D2: ปลายทาง | E2: จำนวนที่นั่ง | F2: เวลา รับ-ส่งพนักงาน | H2: ชนิดยานพาหนะ | I2: ชนิดเชื้อเพลิงของยานพาหนะ | J2: ปริมาณน้ำมัน (L) | K2: ระยะทางต่อเที่ยว (ไป-กลับ) (km) | L2: จำนวนเที่ยว | M2: จำนวนเที่ยวที่วิ่ง แต่ละเดือน
F3: ขาเข้า | G3: ขาออก | M3: 1 | N3: 2 | O3: 3 | P3: 4 | Q3: 5 | R3: 6 | S3: 7 | T3: 8 | U3: 9 | V3: 10 | W3: 11 | X3: 12
A4: น้ำมัน Diesel B7 รถรับส่งพนักงาน | J4: =SUM(J5:J13)
A5: รถบัสเคหะ 1 | B5: เซเว่น เคหะแหลมฉบัง | D5: บมจ. มัลติแบกซ์ | E5: 40 | F5: 07.00 | G5: 08.10 | H5: รถโดยสารประจำทาง | I5: ดีเซล | J5: =K5*L5/2.85 | K5: =6.6+6.5 | L5: =SUM(M5:X6) | M5: 111 | N5: 112 | O5: 124 | P5: 84 | Q5: 120 | R5: 120 | S5: 120 | T5: 124 | U5: 120 | V5: 121 | W5: 120 | X5: 111
A6: รถบัสเคหะ 1 | B6: บมจ. มัลติแบกซ์ | D6: เซเว่น เคหะแหลมฉบัง | F6: 19.00 | G6: 02.10 | H6: รถโดยสารประจำทาง | I6: ดีเซล
A7: รถบัสเคหะ 2 | B7: เซเว่น เคหะแหลมฉบัง | D7: บมจ. มัลติแบกซ์ | E7: 40 | F7: 07.00 | G7: 08.10 | H7: รถโดยสารประจำทาง | I7: ดีเซล | J7: =K7*L7/2.85 | K7: =6.6+6.5 | L7: =SUM(M7:X8) | M7: 111 | N7: 112 | O7: 124 | P7: 84 | Q7: 120 | R7: 120 | S7: 0 | T7: 0 | U7: 0 | V7: 0 | W7: 0 | X7: 0
A8: รถบัสเคหะ 2 | B8: บมจ. มัลติแบกซ์ | D8: เซเว่น เคหะแหลมฉบัง | F8: 19.00 | G8: 02.10 | H8: รถโดยสารประจำทาง | I8: ดีเซล
A9: รถบัสกระทิงราย | B9: แยกกระทิงราย ต.บางละมุง | D9: บมจ. มัลติแบกซ์ | E9: 40 | F9: 07.00 | G9: 08.10 | H9: รถโดยสารประจำทาง | I9: ดีเซล | J9: =K9*L9/2.85 | K9: =12.5+12.4 | L9: =SUM(M9:X10) | M9: 111 | N9: 112 | O9: 124 | P9: 84 | Q9: 120 | R9: 120 | S9: 120 | T9: 124 | U9: 120 | V9: 121 | W9: 120 | X9: 111
A10: รถบัสกระทิงราย | B10: บมจ. มัลติแบกซ์ | D10: แยกกระทิงราย ต.บางละมุง | F10: 19.00 | G10: 20.10 | H10: รถโดยสารประจำทาง | I10: ดีเซล
A11: รถบัสศรีราชา | B11: ปากทางซอยวัดวังหิน ศรีราชา | D11: บมจ. มัลติแบกซ์ | E11: 40 | F11: 07.00 | G11: 08.10 | H11: รถโดยสารประจำทาง | I11: ดีเซล | J11: =K11*L11/2.85 | K11: =14.9+14.5 | L11: =SUM(M11:X12) | M11: 111 | N11: 112 | O11: 124 | P11: 84 | Q11: 120 | R11: 120 | S11: 120 | T11: 124 | U11: 120 | V11: 121 | W11: 120 | X11: 111
A12: รถบัสศรีราชา | B12: บมจ. มัลติแบกซ์ | D12: ปากทางซอยวัดวังหิน ศรีราชา | F12: 19.00 | G12: 20.10 | H12: รถโดยสารประจำทาง | I12: ดีเซล
A13: รถบัสเคหะ 17.00 น. | B13: บมจ. มัลติแบกซ์ | D13: เซเว่น เคหะแหลมฉบัง | E13: 30 | F13: - | G13: 17.00 | H13: รถโดยสารประจำทาง | I13: ดีเซล | J13: =K13*L13/2.85 | K13: 6.5 | L13: =SUM(M13:X13) | M13: 24 | N13: 24 | O13: 27 | P13: 17 | Q13: 26 | R13: 26 | S13: 26 | T13: 27 | U13: 26 | V13: 26 | W13: 26 | X13: 24
A15: หมายเหตุ:
E24: จาก บริษัท มัลติแบกซ์ จำกัด (มหาชน) | J24: เซเว่นการเคหะแหลมฉบัง
E26: ระยะทาง 6.5 กิโลเมตร
E28: จำนวน 2 เที่ยว / วัน
E33: จากเซเว่นการเคหะแหลมฉบัง | I33: บริษัท มัลติแบกซ์ จำกัด (มหาชน)
E35: ระยะทาง 6.6 กิโลเมตร
E37: จำนวน 2 เที่ยว / วัน
E43: ปากซอยวัดวังหิน | H43: บริษัท มัลติแบกซ์ จำกัด (มหาชน)
E45: ระยะทาง 14.9 กิโลเมตร
E47: จำนวน 2 เที่ยว / วัน
E52: บริษัท มัลติแบกซ์ จำกัด (มหาชน) | J52: ปากซอยวัดวังหิน
E54: ระยะทาง 14.5 กิโลเมตร
E56: จำนวน 2 เที่ยว / วัน
E62: บริษัท มัลติแบกซ์ จำกัด (มหาชน) | J62: แยกกระทิงราย ต.บางละมุง อ.บางละมุง
E64: ระยะทาง 12.4 กิโลเมตร
E66: จำนวน 2 เที่ยว / วัน
E71: แยกกระทิงราย ต.บางละมุง อ.บางละมุง | J71: บริษัท มัลติแบกซ์ จำกัด (มหาชน)
E73: ระยะทาง 12.5 กิโลเมตร
E75: จำนวน 2 เที่ยว / วัน

Sheet Scope 3.4
A2: รายการวัตถุดิบที่ใช้ | B2: หลักฐานอ้างอิง | C2: หน่วย | D2: TOTAL | E2: ชื่อผู้ขาย | F2: ระยะทาง ท่าเรือ - MBAX/ผู้ผลิต-MBAX (km) | G2: ประเภทรถ | H2: ระยะทาง ท่าเรือ-ท่าเรือ (km) | I2: รถตู้บรรทุก 10 ล้อ | K2: รถตุ้บรรทุก 6 ล้อ ขนาดใหญ่ | M2: รถตู้บรรทุก 4 ล้อ | O2: เรือบรรทุก Container
D3: รวมทั้งสิ้น | I3: tkm | J3: km | K3: tkm | L3: km | M3: tkm | N3: km | O3: tkm
I4: =SUM(I5:I20) | J4: =SUM(J5:J20) | K4: =SUM(K5:K20) | L4: =SUM(L5:L20) | M4: =SUM(M5:M20) | N4: =SUM(N5:N20) | O4: =SUM(O5:O20)
A5: วัตถุดิบชนิด : LDPE | B5: ใบสั่งซื้อ/ใบกำกับภาษี | C5: Kg | D5: ='[2]CAT 1-วัตถุดิบผลิต'!F5 | E5: BOROUGE PTE LTD. | F5: =$F$64 | G5: =$D$27 | H5: =$B$64 | I5: =F5*D5/1000 | J5: =I5/16 | O5: =H5*D5/1000
A6: วัตถุดิบชนิด : LDPE | B6: ใบสั่งซื้อ/ใบกำกับภาษี | C6: Kg | D6: ='[2]CAT 1-วัตถุดิบผลิต'!F6 | E6: บริษัท พีทีที โกลบอล เคมิคอล จำกัด (มหาชน) | F6: =$B$27 | G6: =$D$27 | I6: =F6*D6/1000 | J6: =I6/16
A7: วัตถุดิบชนิด : LLDPE | B7: ใบสั่งซื้อ/ใบกำกับภาษี | C7: Kg | D7: ='[2]CAT 1-วัตถุดิบผลิต'!F8 | E7: BOROUGE PTE LTD. | F7: =$F$64 | G7: =$D$27 | H7: =$B$64 | I7: =F7*D7/1000 | J7: =I7/16 | O7: =H7*D7/1000
A8: วัตถุดิบชนิด : LLDPE | B8: ใบสั่งซื้อ/ใบกำกับภาษี | C8: Kg | D8: ='[2]CAT 1-วัตถุดิบผลิต'!F9 | E8: EQUATE Petrochemical Company K.S.C.C. | F8: =$F$65 | G8: =$D$27 | H8: =$B$65 | I8: =F8*D8/1000 | J8: =I8/16 | O8: =H8*D8/1000
A9: วัตถุดิบชนิด : LLDPE | B9: ใบสั่งซื้อ/ใบกำกับภาษี | C9: Kg | D9: ='[2]CAT 1-วัตถุดิบผลิต'!F10 | E9: บริษัท ไทยโพลิเอททีลีน จำกัด | F9: =$B$28 | G9: =$D$28 | I9: =F9*D9/1000 | J9: =I9/16
A10: วัตถุดิบชนิด : LLDPE | B10: ใบสั่งซื้อ/ใบกำกับภาษี | C10: Kg | D10: ='[2]CAT 1-วัตถุดิบผลิต'!F11 | E10: บริษัท พีทีที โกลบอล เคมิคอล จำกัด (มหาชน) | F10: =$B$27 | G10: =$D$27 | I10: =F10*D10/1000 | J10: =I10/16
A11: วัตถุดิบชนิด : HDPE | B11: ใบสั่งซื้อ/ใบกำกับภาษี | C11: Kg | D11: ='[2]CAT 1-วัตถุดิบผลิต'!F13 | E11: EQUATE Petrochemical Company K.S.C.C. | F11: =$F$65 | G11: =$D$27 | H11: =$B$65 | I11: =F11*D11/1000 | J11: =I11/16 | O11: =H11*D11/1000
A12: วัตถุดิบชนิด : HDPE | B12: ใบสั่งซื้อ/ใบกำกับภาษี | C12: Kg | D12: ='[2]CAT 1-วัตถุดิบผลิต'!F14 | E12: บริษัท ไทยโพลิเอททีลีน จำกัด | F12: =$B$28 | G12: =$D$28 | I12: =F12*D12/1000 | J12: =I12/16
A13: ='Scope 3.1.1 วัตถุดิบผลิต'!A79 | B13: ใบสั่งซื้อ/ใบกำกับภาษี | C13: Kg | D13: ='Scope 3.1.1 วัตถุดิบผลิต'!F79 | E13: ='Scope 3.1.1 วัตถุดิบผลิต'!G79 | F13: =B39 | G13: =D39 | K13: =F13*D13/1000 | L13: =K13/11
A14: ='Scope 3.1.1 วัตถุดิบผลิต'!A80 | B14: ใบสั่งซื้อ/ใบกำกับภาษี | C14: Kg | D14: ='Scope 3.1.1 วัตถุดิบผลิต'!F80 | E14: ='Scope 3.1.1 วัตถุดิบผลิต'!G80 | F14: =B45 | G14: =D45 | M14: =F14*D14/1000 | N14: =M14/7
A15: ='Scope 3.1.1 วัตถุดิบผลิต'!A81 | B15: ใบสั่งซื้อ/ใบกำกับภาษี | C15: Kg | D15: ='Scope 3.1.1 วัตถุดิบผลิต'!F81 | E15: ='Scope 3.1.1 วัตถุดิบผลิต'!G81 | F15: =B38 | G15: =D38 | K15: =F15*D15/1000 | L15: =K15/11
A16: ='Scope 3.1.1 วัตถุดิบผลิต'!A82 | B16: ใบสั่งซื้อ/ใบกำกับภาษี | C16: Kg | D16: ='Scope 3.1.1 วัตถุดิบผลิต'!F82 | E16: ='Scope 3.1.1 วัตถุดิบผลิต'!G82 | F16: =B39 | G16: =D39 | K16: =F16*D16/1000 | L16: =K16/11
A17: ='Scope 3.1.1 วัตถุดิบผลิต'!A83 | B17: ใบสั่งซื้อ/ใบกำกับภาษี | C17: Kg | D17: ='Scope 3.1.1 วัตถุดิบผลิต'!F83 | E17: ='Scope 3.1.1 วัตถุดิบผลิต'!G83 | F17: =B40 | G17: =D40 | K17: =F17*D17/1000 | L17: =K17/11
A18: ='Scope 3.1.1 วัตถุดิบผลิต'!A84 | B18: ใบสั่งซื้อ/ใบกำกับภาษี | C18: Kg | D18: ='Scope 3.1.1 วัตถุดิบผลิต'!F84 | E18: ='Scope 3.1.1 วัตถุดิบผลิต'!G84 | F18: =B41 | G18: =D41 | K18: =F18*D18/1000 | L18: =K18/11
A19: ='Scope 3.1.1 วัตถุดิบผลิต'!A85 | B19: ใบสั่งซื้อ/ใบกำกับภาษี | C19: Kg | D19: ='Scope 3.1.1 วัตถุดิบผลิต'!F85 | E19: ='Scope 3.1.1 วัตถุดิบผลิต'!G85 | F19: =B43 | G19: =D43 | K19: =F19*D19/1000 | L19: =K19/11
A20: ='Scope 3.1.1 วัตถุดิบผลิต'!A86 | B20: ใบสั่งซื้อ/ใบกำกับภาษี | C20: Kg | D20: ='Scope 3.1.1 วัตถุดิบผลิต'!F86 | E20: ='Scope 3.1.1 วัตถุดิบผลิต'!G86 | F20: =B46 | G20: =D46 | K20: =F20*D20/1000 | L20: =K20/11
A23: รายการขนส่งจากผู้ผลิตวัตถุดิบ ในประเทศ
A24: ตำแหน่งที่ตั้งผู้ผลิตวัตถุดิบ | B24: ระยะทางจากผู้ผลิตมายังโรงงาน | C24: หน่วย | D24: ประเภทรถ | E24: ภาระบรรทุกขามาส่งของที่โรงงาน (%) | F24: ภาระบรรทุกขากลับออกจากโรงงาน (%) | G24: หลักฐาน
A26: 1.การขนส่งวัตถุดิบ
A27: บริษัท พีทีที โกลบอล เคมิคอล จำกัด (มหาชน) | B27: 65 | C27: km | D27: 10 ล้อ/ตู้บรรทุก | E27: 100 | F27: 0 | G27: google Map
A28: บริษัท ไทยโพลิเอททีลีน จำกัด | B28: 61 | C28: km | D28: 10 ล้อ/ตู้บรรทุก | E28: 100 | F28: 0 | G28: google Map
A29: บริษัท ทีเอช คัลเล่อร์ จำกัด | B29: 85 | C29: km | D29: 6 ล้อ/ตู้บรรทุก | E29: 100 | F29: 0 | G29: google Map
A30: AMPACET (Thailand) Co., Ltd. | B30: 40 | C30: km | D30: 4 ล้อ/บรรทุก | E30: 100 | F30: 0 | G30: google Map
A31: บริษัท อีเทอนอล ซากาตะ อิ้งซ์ จำกัด | B31: 136 | C31: km | D31: 4 ล้อ/บรรทุก | E31: 100 | F31: 0 | G31: google Map
A32: SIEGWERK (THAILAND) LTD. | B32: 155 | C32: km | D32: 4 ล้อ/บรรทุก | E32: 100 | F32: 0 | G32: google Map
A33: บริษัท เอเวียนท์ คัลเลอร์แร้นท์ (ประเทศไทย) จำกัด | B33: 50 | C33: km | D33: 4 ล้อ/บรรทุก | E33: 100 | F33: 0 | G33: google Map
A34: บริษัท เอเวียนท์ (ประเทศไทย) จำกัด | B34: 106 | C34: km | D34: 4 ล้อ/บรรทุก | E34: 100 | F34: 0 | G34: google Map
A35: Chemical Innovation Co.,Ltd. | B35: 112 | C35: km | D35: 4 ล้อ/บรรทุก | E35: 100 | F35: 0 | G35: google Map
A36: บริษัท พาโนราม่า อิ้งค์ จำกัด | B36: 118 | C36: km | D36: 4 ล้อ/บรรทุก | E36: 50 | F36: 0 | G36: google Map
A37: 2. การขนส่งบรรจุภัณฑ์
A38: บริษัท สำราญจิตต์การพิมพ์ จำกัด | B38: 108 | C38: km | D38: 6 ล้อ/ตู้บรรทุก | E38: 100 | F38: 0 | G38: google Map
A39: บริษัท เค.อาร์.ที. แพค แอนด์ ซัพพลาย จำกัด | B39: 132 | C39: km | D39: 6 ล้อ/ตู้บรรทุก | E39: 100 | F39: 0 | G39: google Map
A40: บริษัท เอส.พี.ที.แพ็คกิ้งกรุ๊ป จำกัด | B40: 172 | C40: km | D40: 6 ล้อ/ตู้บรรทุก | E40: 100 | F40: 0 | G40: google Map
A41: บริษัท บรรเจิดบรรจุภัณฑ์ จำกัด | B41: 150 | C41: km | D41: 6 ล้อ/ตู้บรรทุก | E41: 100 | F41: 0 | G41: google Map
A42: บริษัท ยูนิเวอร์ส แพ็ค จำกัด | B42: 153 | C42: km | D42: 4 ล้อ/บรรทุก | E42: 100 | F42: 0 | G42: google Map
A43: บริษัท บาแล็นซ์ แพ็คกิ้ง จำกัด | B43: 157 | C43: km | D43: 6 ล้อ/ตู้บรรทุก | E43: 100 | F43: 0 | G43: google Map
A44: บริษัท แสงศิริ กรุ๊ป จำกัด | B44: 31 | C44: km | D44: 6 ล้อ/ตู้บรรทุก | E44: 100 | F44: 0 | G44: google Map
A45: บริษัท เหรียญทองการพิมพ์ จำกัด | B45: 116 | C45: km | D45: 4 ล้อ/บรรทุก | E45: 50 | F45: 0 | G45: google Map
A46: ห้างหุ้นส่วนจำกัด อชราบรรจุภัณฑ์ | B46: 110 | C46: km | D46: 6 ล้อ/บรรทุก | E46: 100 | F46: 0 | G46: google Map
A47: บจก.ธงไชย โมลด์ แอนด์ พลาส(72) | B47: 130 | C47: km | D47: 4 ล้อ/บรรทุก | E47: 100 | F47: 0 | G47: google Map
A48: 3.การขนส่งวัสดุสิ้นเปลือง
A49: บริษัท เอ็มซี อินดัสเทรียลเคมิคัล จำกัด | B49: 127 | C49: km | D49: 4 ล้อ/บรรทุก | E49: 100 | F49: 0 | G49: google Map
A50: บริษัท โชคเจริญ 2020 จำกัด | B50: 94 | C50: km | D50: 4 ล้อ/บรรทุก | E50: 100 | F50: 0 | G50: google Map
A51: บริษัท บางบอนอุตสาหกรรม จำกัด | B51: 132 | C51: km | D51: 4 ล้อ/บรรทุก | E51: 100 | F51: 0 | G51: google Map
A52: บริษัท เปอร์มาเฟล็กซ์ จำกัด | B52: 105 | C52: km | D52: 4 ล้อ/บรรทุก | E52: 100 | F52: 0 | G52: google Map
A53: บริษัท โพลีพลาส พรีซีชั่น จำกัด | B53: 100 | C53: km | D53: 4 ล้อ/บรรทุก | E53: 100 | F53: 0 | G53: google Map
A54: บริษัท จาคานา จำกัด | B54: 113 | C54: km | D54: 4 ล้อ/บรรทุก | E54: 100 | F54: 0 | G54: google Map
A55: บริษัท อเมริกัน ปิโตรเคมิคอล (ประเทศไทย) จำกัด | B55: 150 | C55: km | D55: 4 ล้อ/บรรทุก | E55: 100 | F55: 0 | G55: google Map
A56: บริษัท เอ็มเอ็มพี คอร์ปอเรชั่น จำกัด | B56: 105 | C56: km | D56: 4 ล้อ/บรรทุก | E56: 100 | F56: 0 | G56: google Map
A57: บริษัท วัฒนพันธุ์แพคเกจจิ้งซิสเท็ม จำกัด | B57: 16 | C57: km | D57: 4 ล้อ/บรรทุก | E57: 100 | F57: 0 | G57: google Map
A58: บริษัท เค.เอ.มาร์เก็ตติ้ง จำกัด | B58: 133 | C58: km | D58: 4 ล้อ/บรรทุก | E58: 100 | F58: 0 | G58: google Map
A60: รายการขนส่งจากผู้ผลิตวัตถุดิบ ต่างประเทศ
A61: ตำแหน่งที่ตั้งผู้ผลิตวัตถุดิบ | B61: ระยะทางจากผู้ผลิตมายังท่าเรือของ Supplier (km) | C61: หน่วย | D61: ชื่อท่าเรือของ Supplier | E61: ชื่อท่าเรือของ ผู้ซื้อ | F61: ระยะทางจากท่าเรือในประเทศมายังโรงงานของผู้ผลิต (km) | G61: ประเภทพาหนะ | H61: ภาระบรรทุกขามาส่งของที่โรงงาน (%) | I61: ภาระบรรทุกขากลับออกจากโรงงาน (%) | J61: หลักฐาน
A63: 1.การขนส่งวัตถุดิบ
A64: BOROUGE PTE LTD. | B64: 7944.93 | C64: km | D64: KHALIFA PORT, ABU DHABI | E64: แหลมฉบัง | F64: 2 | G64: เรือ | H64: 100 | I64: 0 | J64: google Map | K64: 7944.93
A65: EQUATE Petrochemical Company K.S.C.C. | B65: 8560.68 | C65: km | D65: SHUAIBA PORT, KUWAIT | E65: แหลมฉบัง | F65: 2 | G65: เรือ | H65: 100 | I65: 0 | J65: google Map | K65: 8560.68
A66: SOJITZ PLA-NET CORPORATION | B66: 18132.08 | C66: km | D66: RIO GRANDE PORT IN BRAZIL | E66: แหลมฉบัง | F66: 2 | G66: เรือ | H66: 100 | I66: 0 | J66: google Map | K66: 18132.08
A67: SOJITZ PLA-NET CORPORATION OSAKA BRANCH | B67: 18132.08 | C67: km | D67: RIO GRANDE PORT IN BRAZIL | E67: แหลมฉบัง | F67: 2 | G67: เรือ | H67: 100 | I67: 0 | J67: google Map | K67: 18132.08
A68: International Flavors & Fragrances Inc. | B68: 23759.14 | C68: km | D68: NEW YORK PORT | E68: แหลมฉบัง | F68: 2 | G68: เรือ | H68: 100 | I68: 0 | J68: google Map | K68: 23759.14
A69: International Flavor & Fragrances (Thailand) Ltd. | B69: 23759.14 | C69: km | D69: NEW YORK PORT | E69: แหลมฉบัง | F69: 2 | G69: เรือ | H69: 100 | I69: 0 | J69: google Map | K69: 23759.14
A70: บริษัท ซันนา เซอเทรด จำกัด | B70: 16507.2 | C70: km | D70: FELIXSTOWE PORT | E70: แหลมฉบัง | F70: 2 | G70: เรือ | H70: 100 | I70: 0 | J70: google Map | K70: 16507.2
A71: Symphony Environmental Ltd. | B71: 2424.08 | C71: km | D71: KAOHSIUNG PORT | E71: แหลมฉบัง | F71: 2 | G71: เรือ | H71: 100 | I71: 0 | J71: google Map | K71: 2424.08
A72: Kingfa Environmental Sci. & Tech. Co.,Ltd. | B72: 2570.59 | C72: km | D72: NANSHA NEW PORT | E72: แหลมฉบัง | F72: 2 | G72: เรือ | H72: 100 | I72: 0 | J72: google Map | K72: 2570.59

Sheet Scope 3.5
A2: รายการของเสียจากการผลิต/อาคารสำนักงาน | B2: ตำแหน่งที่เกิดของเสีย | C2: หลักฐาน | D2: วิธีการกำจัด/รหัสกำจัดตามเอกสาร Manifest | E2: หน่วย | F2: รวม | G2: ปริมาณการเกิดของเสียแต่ละเดือน/2566
G3: 1 | H3: 2 | I3: 3 | J3: 4 | K3: 5 | L3: 6 | M3: 7 | N3: 8 | O3: 9 | P3: 10 | Q3: 11 | R3: 12
A4: ขยะมูลฝอยทั่วไป | B4: จากร้านค้าโรงอาหาร / จากพนักงาน เช่น เศษถุงอาหาร ซองขนม แก้วพลาสติก ใบไม้ | C4: ใบกำกับการขนส่งขยะมูลฝอยประจำเดือน | D4: ฝังกลบ | E4: Kg | F4: =SUM(G4:R4) | G4: 12000 | H4: 12000 | I4: 13000 | J4: 9000 | K4: 13000 | L4: 13000 | M4: 13000 | N4: 14000 | O4: 13000 | P4: 13000 | Q4: 13000 | R4: 12000
A5: ขยะอันตราย | C5: ใบ manifest | D5: ฝังกลบ (073) | E5: Kg | F5: =F14
A6: ขยะรีไซเคิล | D6: ใช้ประโยชน์ (042,049,011) | E6: Kg | F6: =SUM(F7:F13,F15:F18)
A7: สีพิมพ์เสื่อมสภาพ | B7: กระบวนการเกิดของเสีย เนื่องจากการผสมสีพิมพ์ที่ไม่ได้ตามคุณภาพ และเกิดสีพิมพ์หมดอายุไม่สามารถใช้งานได้ | C7: ใบกำกับการขนส่งวัสดุที่ไม่ใช้แล้ว (Manifest) | D7: 042 | E7: Kgs. | F7: =SUM(G7:R7) | G7: - | H7: 2156 | J7: 1000 | K7: - | L7: 1200 | M7: - | N7: - | O7: 1800 | P7: - | Q7: 2000 | R7: -
A8: น้ำมันใช้แล้ว | B8: กระบวนการเกิดของเสียเนื่องจากการทำ PM เครื่องจักรไม่สามารถนำกลับมาใช้งานได้ | C8: ใบกำกับการขนส่งวัสดุที่ไม่ใช้แล้ว (Manifest) | D8: 042 | E8: Kgs. | F8: =SUM(G8:R8) | G8: - | H8: - | J8: 800 | K8: - | L8: 400 | M8: - | N8: - | O8: 1400 | P8: - | Q8: 600 | R8: -
A9: ภาชนะปนเปื้อน | B9: กระบวนการเกิดของเสียเนื่องจากเป็นภาชนะบรรจุสีพิมพ์ที่ใช้งานแล้ว และภาชนะมีการปนเปื้อนของสีพิมพ์ | C9: ใบกำกับการขนส่งวัสดุที่ไม่ใช้แล้ว (Manifest) | D9: 049 | E9: Kgs. | F9: =SUM(G9:R9) | G9: - | H9: 156 | J9: 505 | K9: - | L9: 323.3 | M9: - | N9: - | O9: 106.2 | P9: - | Q9: 130 | R9: -
A10: เศษผ้าปนเปื้อน | B10: กระบวนการเกิดของเสีย เนื่องจาก การนำเศษผ้าเช็ดทำความสะอาดตามเครื่องจักรเกิดการปนเปื้อน น้ำมันหรือสีพิมพ์ | C10: ใบกำกับการขนส่งวัสดุที่ไม่ใช้แล้ว (Manifest) | D10: 042 | E10: Kgs. | F10: =SUM(G10:R10) | G10: - | H10: 2010 | J10: 1251.2 | K10: - | L10: 2654.8 | M10: - | N10: - | O10: 2383.9 | P10: - | Q10: 2690 | R10: -
A11: เม็ดพลาสติกเสื่อมสภาพ | B11: เกิดจากกระบวนการผลิตเนื่องจากการผสมวัตถุดิบที่ไม่ได้ตามคุณภาพ และเม็ดพลาสติกหมดอายุไม่สามารถนำมาผลิตได้ | C11: ใบกำกับการขนส่งวัสดุที่ไม่ใช้แล้ว (Manifest) | D11: 011 | E11: Kgs. | F11: =SUM(G11:R11) | G11: - | H11: 4452 | I11: - | J11: - | K11: - | L11: - | M11: - | N11: - | O11: 2600 | P11: - | Q11: - | R11: -
A12: เม็ดพลาสติกเสื่อมสภาพ | B12: กระบวนการเกิดของเสียเนื่องจากเป็นเม็ดพลาสติกที่หมดอายุ และเสื่อมสภาพ ซึ่งไม่สามารถนำมาใช้ขึ้นรูปในการผลิตได้ | C12: ใบกำกับการขนส่งวัสดุที่ไม่ใช้แล้ว (Manifest) | D12: 042 | E12: Kgs. | F12: =SUM(G12:R12) | G12: - | H12: - | I12: - | J12: - | K12: 62597 | L12: - | M12: - | N12: - | O12: - | P12: - | Q12: - | R12: -
A13: หลอดไฟ | B13: กระบวนการเกิดของเสีย เนื่องจากการหลอดไฟหมดอายุการใช้งาน | C13: ใบกำกับการขนส่งวัสดุที่ไม่ใช้แล้ว (Manifest) | D13: 049 | E13: Kgs. | F13: =SUM(G13:R13) | G13: - | H13: 7.6 | I13: - | J13: - | K13: - | L13: - | M13: - | N13: - | O13: 8 | P13: - | Q13: - | R13: -
A14: ขยะอิเล็กทรอนิกส์ | B14: อุปกรณ์อิเล็กทรอนิกส์เสื่อมสภาพ เช่น แผงวงจร คอมเพรสเซอร์ หน้าจอทัชสกรีน ที่เสื่อมสภาพเก็บรวบรวมส่งกำจัด | C14: ใบกำกับการขนส่งวัสดุที่ไม่ใช้แล้ว (Manifest) | D14: 073 | E14: Kgs. | F14: =SUM(G14:R14) | G14: - | H14: - | I14: - | J14: - | K14: - | L14: - | M14: - | N14: - | O14: - | P14: - | Q14: 680 | R14: -
A15: เศษเหล็ก | B15: เศษเหล็ก จากการซ่อมแซม เช่น การตัด เจียร ตะไบ ไส กลึง หรือเปลี่ยนใหม่ เนื่องจากเกิดสนิม | C15: ใบกำกับการขนส่งวัสดุที่ไม่ใช้แล้ว (Manifest) | D15: 011 | E15: Kgs. | F15: =SUM(G15:R15) | G15: 400 | H15: 1550 | I15: 2595 | J15: 1450 | K15: 470 | L15: 1030 | M15: 1060 | N15: 470 | O15: 495 | P15: 695 | Q15: 5200 | R15: 2990
A16: เศษพลาสติก | B16: เศษพลาสติกจากการห่อหุ้มสินค้าและวัตถุดิบ และจากการผลิตสินค้าในโรงงาน ที่ขาด ไม่สามารถใช้งานได้ | C16: ใบกำกับการขนส่งวัสดุที่ไม่ใช้แล้ว (Manifest) | D16: 011 | E16: Kgs. | F16: =SUM(G16:R16) | G16: 3568.8 | H16: 4253.8 | I16: 3686.4 | J16: 2574.4 | K16: 6233.2 | L16: 4925.6 | M16: 7195.2 | N16: 8567.2 | O16: 5861.2 | P16: 5961.4 | Q16: 10500 | R16: 12600
A17: เศษไม้ | B17: เศษไม้ เป็นไม้พาเลทที่ใช้รองวัตถุดิบ หรือสินค้าจากทางผู้ผลิต เกิดการชำรุดหัก แตก ใช้งานไม่ได้ | C17: ใบกำกับการขนส่งวัสดุที่ไม่ใช้แล้ว (Manifest) | D17: 011 | E17: Kgs. | F17: =SUM(G17:R17) | G17: - | H17: 165 | I17: 0 | J17: 110 | K17: 0 | L17: 155 | M17: 0 | N17: 70 | O17: 100 | P17: 119 | Q17: 13000 | R17: 10280
A18: เศษกระดาษหรือกระดาษแข็ง | B18: เป็นเศษกระดาษจากการใช้ในงานผลิตหรือกระดาษรองสินค้า กระดาษแข็งจากกล่องที่ขาดชำรุดแล้ว ของเสียประเภทบรรจุภัณฑ์ประเภทกระดาษ ได้แก่ กล่องหรือลังกระดาษ | C18: ใบกำกับการขนส่งวัสดุที่ไม่ใช้แล้ว (Manifest) | D18: 011 | E18: Kgs. | F18: =SUM(G18:R18) | G18: 2275.4 | H18: 2398 | I18: 2166.1 | J18: 2904.9 | K18: 1948.2 | L18: 2929.2 | M18: 2596.8 | N18: 5274.1 | O18: 2684.4 | P18: 3419.1 | Q18: 12000 | R18: 11000
A20: การขนส่ง
A21: ลำดับ | B21: บริษัทผู้ก่อกำเนิด | C21: บริษัทที่รับกำจัด | D21: ระยะทาง (km) | E21: น้ำหนัก (kg) | F21: รถกระบะบรรทุก 10 ล้อ วิ่งปกติ | H21: รถกระบะ 4 ล้อ | J21: รถบรรทุกขยะ 6 ล้อ
F22: tkm | G22: km | H22: tkm | I22: km | J22: tkm | K22: km
F23: =SUM(F24:F26) | G23: =SUM(G24:G26) | H23: =SUM(H24:H26) | I23: =SUM(I24:I26) | J23: =SUM(J24:J26) | K23: =SUM(K24:K26)
A24: ขยะมูลฝอยทั่วไป | B24: MBAX | C24: หลุมฝังกลบชุมชน | D24: 40 | E24: =E4 | J24: =D24*F4/1000 | K24: =J24/11
A25: ขยะอันตราย | B25: MBAX | C25: บริษัท กรีน เอ็นไวรอนเม้นท์ แลนด์ฟิล จำกัด | D25: 118 | E25: =E5 | F25: =D25*F5/1000 | G25: =F25/16
A26: ขยะรีไซเคิล | B26: MBAX | C26: บริษัท กรีน เอ็นไวรอนเม้นท์ แลนด์ฟิล จำกัด | D26: 118 | E26: =E6 | F26: =D26*F6/1000 | G26: =F26/16

Sheet Scope 3.7
A2: ลำดับ | B2: รหัส | C2: ชื่อ - สกุล | D2: เพศ | E2: ประเภท | F2: สัญชาติ | G2: รายละเอียด | H2: ระยะทาง(กม.) เที่ยวเดียว | I2: Link ภาพ GPS จากบ้านถึงบริษัท | J2: พาหนะ ในการเดินทางมาบริษัท | K2: ประเภทเชื้อเพลิง | L2: คนขับ+ผู้ร่วมเดินทาง | M2: หมายเหตุ | N2: วันทำงาน | O2: อัตราการสิ้นเปลือง | P2: Diesel | Q2: Gasoline
P3: L | Q3: L
P4: =SUM(P5:P482) | Q4: =SUM(Q5:Q482)
A5: 1 | B5: 380003 | C5: เสมียน ศิลป์ชัย | D5: ชาย | E5: รายเดือน | F5: ไทย | G5: 101/249 ม.10 ต.บึง อ.ศรีราชา จ.ชลบุรี 20230 | H5: 10 | I5: 1-380003.pdf | J5: รถยนต์เฉลี่ยทุกขนาด | K5: แก๊สโซฮอล์ 95 | L5: 2 | N5: ='[2]1.4 Septic'!$F$16 | O5: =$G$487 | Q5: =H5*2*L5*N5/O5
A6: =+A5+1 | B6: 380005 | C6: สุชาติ สุกรินทร์ | D6: ชาย | E6: รายเดือน | F6: ไทย | G6: 101/248 ม.10 ต.บึง อ.ศรีราชา จ.ชลบุรี 20230 | H6: 12 | J6: รถกระบะบรรทุก | K6: ดีเซล | L6: 1 | N6: ='[2]1.4 Septic'!$F$16 | O6: 6.369 | P6: =H6*2*L6*N6/O6
A7: =+A6+1 | B7: 380006 | C7: สมพร หอมชะลูด | D7: ชาย | E7: รายเดือน | F7: ไทย | G7: 101/246 ม.10 ต.บึง อ.ศรีราชา จ.ชลบุรี 20230 | H7: 10 | J7: รถยนต์เฉลี่ยทุกขนาด | K7: แก๊สโซฮอล์ 91 | L7: 1 | N7: ='[2]1.4 Septic'!$F$16 | O7: =$G$487 | Q7: =H7*2*L7*N7/O7
A8: =+A7+1 | B8: 380007 | C8: ศรชัย บุญปลื้ม | D8: ชาย | E8: รายเดือน | F8: ไทย | G8: 101/247 ม.10 ต.บึง อ.ศรีราชา จ.ชลบุรี 20230 | H8: 8 | J8: รถจักรยานยนต์ 4 จังหวะเครื่องยนต์ขนาดเล็กกว่า 125 cc | K8: แก๊สโซฮอล์ 95 | L8: 2 | N8: ='[2]1.4 Septic'!$F$16 | O8: =$G$492 | Q8: =H8*2*L8*N8/O8
A9: =+A8+1 | B9: 380010 | C9: สำรวย อาจน้อย | D9: ชาย | E9: รายเดือน | F9: ไทย | G9: 101/245 ม.10 ต.ทุ่งสุขลา อ.ศรีราชา จ.ชลบุรี 20230 | H9: 9 | J9: รถกระบะบรรทุก | K9: ดีเซล | L9: 2 | N9: ='[2]1.4 Septic'!$F$16 | O9: 6.369 | P9: =H9*2*L9*N9/O9
A10: =+A9+1 | B10: 380017 | C10: อธิวัฒน์ ธีรวริยาภัสร์ | D10: ชาย | E10: รายเดือน | F10: ไทย | G10: เลขที่ 8 หมู่บ้านท่าทรายนิเวศน์2 ซ.นนทบุรี35 ต.ท่าทราย อ.เมืองนนทบุรี จ.นนทบุรี 11000 | H10: 38 | J10: รถยนต์ขนาดใหญ่ (2000 cc) | K10: แก๊สโซฮอล์ 91 | L10: 2 | M10: สนง.กทม. | N10: ='[2]1.4 Septic'!$F$34 | O10: =$G$495 | Q10: =H10*2*L10*N10/O10
A11: =+A10+1 | B11: 380026 | C11: วิชัย ธีระสาสน์ | D11: ชาย | E11: รายเดือน | F11: ไทย | G11: 13/282 ม.18 ต.คูคต อ.ลำลูกกา จ.ปทุมธานี 12130 | H11: 40 | J11: รถจักรยานยนต์ 4 จังหวะเครื่องยนต์ขนาดเล็กกว่า 125 cc | K11: แก๊สโซฮอล์ 95 | L11: 1 | M11: สนง.กทม. | N11: ='[2]1.4 Septic'!$F$34 | O11: =$G$492 | Q11: =H11*2*L11*N11/O11
A12: =+A11+1 | B12: 390030 | C12: ภาสกร อ้อนอุบล | D12: ชาย | E12: รายเดือน | F12: ไทย | G12: 101/250 ม.10 ต.บึง อ.ศรีราชา จ.ชลบุรี 20230 | H12: 10 | J12: รถกระบะบรรทุก | K12: ดีเซล | L12: 1 | N12: ='[2]1.4 Septic'!$F$16 | O12: 6.369 | P12: =H12*2*L12*N12/O12
A13: =+A12+1 | B13: 390031 | C13: สมพงษ์ ศิลป์ชัย | D13: ชาย | E13: รายเดือน | F13: ไทย | G13: การเคหะ แหลมฉบัง ม.6 ต.บางละมุง อ.บางละมุง จ.ชลบุรี 20150 | H13: 15 | J13: รถกระบะบรรทุก | K13: ดีเซล | L13: 1 | N13: ='[2]1.4 Septic'!$F$16 | O13: 6.369 | P13: =H13*2*L13*N13/O13
A14: =+A13+1 | B14: 400040 | C14: นิตยา ทองหล่อ | D14: หญิง | E14: รายเดือน | F14: ไทย | G14: 198/38 ม.8 ต.บางละมุง อ.บางละมุง จ.ชลบุรี 20150 | H14: 8.5 | J14: รถกระบะบรรทุก | K14: ดีเซล | L14: 2 | N14: ='[2]1.4 Septic'!$F$16 | O14: 6.369 | P14: =H14*2*L14*N14/O14
A15: =+A14+1 | B15: 400042 | C15: เฉลิม สุมทุม | D15: ชาย | E15: รายเดือน | F15: ไทย | G15: 101/240 ม.10 ต.บึง อ.ศรีราชา จ.ชลบุรี 20230 | H15: 20 | J15: รถกระบะบรรทุก | K15: ดีเซล | L15: 1 | N15: ='[2]1.4 Septic'!$F$16 | O15: 6.369 | P15: =H15*2*L15*N15/O15
A16: =+A15+1 | B16: 400044 | C16: วิชัย ประธรรมยันเต | D16: ชาย | E16: รายเดือน | F16: ไทย | G16: การเคหะแหลมฉบัง ต.บางละมุง อ.บางละมุง จ.ชลบุรี 20150 | H16: 14 | J16: รถจักรยานยนต์ 4 จังหวะเครื่องยนต์ขนาดเล็กกว่า 125 cc | K16: แก๊สโซฮอล์ 95 | L16: 1 | N16: ='[2]1.4 Septic'!$F$16 | O16: =$G$492 | Q16: =H16*2*L16*N16/O16
A17: =+A16+1 | B17: 410048 | C17: ธวัชชัย เสาร์ศรี | D17: ชาย | E17: รายเดือน | F17: ไทย | G17: การเคหะแหลมฉบัง บางละมุง ชลบุรี | H17: 5 | J17: รถยนต์เฉลี่ยทุกขนาด | K17: แก๊สโซฮอล์ 91 | L17: 1 | N17: ='[2]1.4 Septic'!$F$16 | O17: =$G$487 | Q17: =H17*2*L17*N17/O17
A18: =+A17+1 | B18: 410049 | C18: พิเชษฐ อภิโชติกุล | D18: ชาย | E18: รายเดือน | F18: ไทย | G18: 2021 ถ.สุขุมวิท ต.พระโขนงเหนือ อ.วัฒนา จ.กรุงเทพมหานคร 10110 | H18: 15 | J18: รถจักรยานยนต์ 4 จังหวะเครื่องยนต์ขนาดเล็กกว่า 125 cc | K18: แก๊สโซฮอล์ 91 | L18: 1 | M18: สนง.กทม. | N18: ='[2]1.4 Septic'!$F$34 | O18: =$G$492 | Q18: =H18*2*L18*N18/O18
A19: =+A18+1 | B19: 410050 | C19: พเยาว์ นิลทร | D19: หญิง | E19: รายเดือน | F19: ไทย | G19: 234 ซ มิตคาม ต.วชิรพยาบาล อ.ดุสิต จ.กรุงเทพมหานคร 10300 | H19: 25 | J19: รถยนต์ขนาดเล็ก (1500 cc) | K19: แก๊สโซฮอล์ 95 | L19: 1 | M19: สนง.กทม. | N19: ='[2]1.4 Septic'!$F$34 | O19: =$G$498 | Q19: =H19*2*L19*N19/O19
A20: =+A19+1 | B20: 410053 | C20: จิรวัฒน์ บุญสุวรรณ | D20: ชาย | E20: รายเดือน | F20: ไทย | G20: 101/253 ม.10 ต.บึง อ.ศรีราชา จ.ชลบุรี 20230 | H20: 10 | J20: รถกระบะบรรทุก | K20: ดีเซล | L20: 2 | N20: ='[2]1.4 Septic'!$F$16 | O20: 6.369 | P20: =H20*2*L20*N20/O20
A21: =+A20+1 | B21: 410054 | C21: ชวนชม อัศวแก้วมงคล | D21: หญิง | E21: รายเดือน | F21: ไทย | G21: 5/159 หมู่ที่ 16 ต.บางแก้ว อ.บางพลี จ.สมุทรปราการ 10540 | H21: 46 | J21: รถยนต์ขนาดกลาง (1800 cc) | K21: แก๊สโซฮอล์ 95 | L21: 1 | M21: สนง.กทม. | N21: ='[2]1.4 Septic'!$F$34 | O21: =$G$496 | Q21: =H21*2*L21*N21/O21
A22: =+A21+1 | B22: 410057 | C22: สุพัตรา ปานเพชร | D22: หญิง | E22: รายเดือน | F22: ไทย | G22: 101/238 ม.10 ต.บึง อ.ศรีราชา จ.ชลบุรี 20230 | H22: 10 | J22: รถยนต์ขนาดเล็ก (1500 cc) | K22: แก๊สโซฮอล์ E20 | L22: 1 | N22: ='[2]1.4 Septic'!$F$16 | O22: =$G$498 | Q22: =H22*2*L22*N22/O22
A23: =+A22+1 | B23: 410060 | C23: เพ็ญศรี อุทะนุต | D23: หญิง | E23: รายเดือน | F23: ไทย | G23: 101/247 ม. 10 ต.บึง อ.ศรีราชา จ.ชลบุรี 20230 | H23: 10 | J23: รถจักรยานยนต์ 4 จังหวะเครื่องยนต์ขนาด 125 cc | K23: แก๊สโซฮอล์ 91 | L23: 1 | N23: ='[2]1.4 Septic'!$F$16 | O23: =$G$492 | Q23: =H23*2*L23*N23/O23
A24: =+A23+1 | B24: 420068 | C24: ชัยยา นุโทน | D24: ชาย | E24: รายเดือน | F24: ไทย | G24: 136/11 ม.10 หมู่บ้านวราสิริ เฟส 2 ต.ทุ่งสุขลา อ.ศรีราชา จ.ชลบุรี 20230 | H24: 7 | J24: รถกระบะบรรทุก | K24: ดีเซล | L24: 1 | N24: ='[2]1.4 Septic'!$F$16 | O24: 6.369 | P24: =H24*2*L24*N24/O24
A25: =+A24+1 | B25: 420070 | C25: มลเทียร บุญยัง | D25: ชาย | E25: รายเดือน | F25: ไทย | G25: 101/238 ม.10 ต ต..บึง อ.ศรีราชา จ.ชลบุรี 20230 | H25: 10 | J25: รถยนต์ขนาดเล็ก (1500 cc) | K25: แก๊สโซฮอล์ E20 | L25: 1 | N25: ='[2]1.4 Septic'!$F$16 | O25: =$G$498 | Q25: =H25*2*L25*N25/O25
A26: =+A25+1 | B26: 430074 | C26: วิชัย ศรีภักดี | D26: ชาย | E26: รายเดือน | F26: ไทย | G26: 220/97 ม.6 ต.บางละมุง อ.บางละมุง จ.ชลบุรี 20150 | H26: 14 | J26: รถจักรยานยนต์ 4 จังหวะเครื่องยนต์ขนาดเล็กกว่า 125 cc | K26: แก๊สโซฮอล์ 91 | L26: 1 | N26: ='[2]1.4 Septic'!$F$16 | O26: =$G$492 | Q26: =H26*2*L26*N26/O26
A27: =+A26+1 | B27: 430076 | C27: นันธิชา ประสิทธิ์ | D27: หญิง | E27: รายเดือน | F27: ไทย | G27: 889/38 ม.9 ต. ทุ่งสุขลา อ. ศรีราชา ชลบุรี 20230 | H27: 4 | J27: รถยนต์ขนาดใหญ่ (2000 cc) | K27: แก๊สโซฮอล์ 95 | L27: 1 | N27: ='[2]1.4 Septic'!$F$16 | O27: =$G$495 | Q27: =H27*2*L27*N27/O27
A28: =+A27+1 | B28: 440089 | C28: ภิรมย์ สุราศรี | D28: ชาย | E28: รายเดือน | F28: ไทย | G28: 101/297 ม.10 ต.บึง อ.ศรีราชา จ.ชลบุรี 20230 | H28: 9 | J28: รถจักรยานยนต์ 4 จังหวะเครื่องยนต์ขนาดเล็กกว่า 125 cc | K28: แก๊สโซฮอล์ 91 | L28: 2 | N28: ='[2]1.4 Septic'!$F$16 | O28: =$G$492 | Q28: =H28*2*L28*N28/O28
A29: =+A28+1 | B29: 440090 | C29: บุญรวม ไทยประเสริฐ | D29: หญิง | E29: รายเดือน | F29: ไทย | G29: 316/26 ม. 6 ต.บางละมุง อ.บางละมุง จ.ชลบุรี 20260 | H29: 5 | J29: รถยนต์ขนาดเล็ก (1500 cc) | K29: แก๊สโซฮอล์ E85 | L29: 1 | N29: ='[2]1.4 Septic'!$F$16 | O29: =$G$498 | Q29: =H29*2*L29*N29/O29
A30: =+A29+1 | B30: 440095 | C30: พัชศิริ ยิ่งเลิศ | E30: รายเดือน | G30: 429 ซ.หมู่บ้านเศรษฐกิจ 31 บางแค กรุงเทพมหานคร 10160 | H30: 29 | J30: รถยนต์ขนาดเล็ก (1500 cc) | K30: แก๊สโซฮอล์ 91 | L30: 1 | M30: สนง.กทม. | N30: ='[2]1.4 Septic'!$F$34 | O30: =$G$498 | Q30: =H30*2*L30*N30/O30
A31: =+A30+1 | B31: 440108 | C31: เยาวรัตน์ หงษ์วิหก | D31: หญิง | E31: รายเดือน | F31: ไทย | G31: 9/6 หมู่7 ต.บางละมุง อ.บางละมุง จ.ชลบุรี 20150 | H31: 10 | J31: รถกระบะบรรทุก | K31: ดีเซล | L31: 2 | N31: ='[2]1.4 Septic'!$F$16 | O31: 6.369 | P31: =H31*2*L31*N31/O31
A32: =+A31+1 | B32: 450111 | C32: บุญทำ ฤทธิ์ธา | D32: ชาย | E32: รายเดือน | F32: ไทย | G32: เคหะแหลมฉบัง ม.6 ต.บางละมุง อ.บางละมุง จ.ชลบุรี 20150 | H32: 6 | J32: รถจักรยานยนต์ 2 จังหวะเครื่องยนต์ขนาด 120cc | K32: แก๊สโซฮอล์ 91 | L32: 1 | N32: ='[2]1.4 Septic'!$F$16 | O32: =$G$491 | Q32: =H32*2*L32*N32/O32
A33: =+A32+1 | B33: 450114 | C33: พุทธวรรณ แก้วไผ่ซอ | D33: หญิง | E33: รายเดือน | F33: ไทย | G33: 101/251 ม.10 ต.บึง อ.ศรีราชา จ.ชลบุรี 20230 | H33: 10 | J33: รถจักรยานยนต์ 2 จังหวะเครื่องยนต์ขนาด 150cc | K33: แก๊สโซฮอล์ 91 | L33: 1 | N33: ='[2]1.4 Septic'!$F$16 | O33: =$G$491 | Q33: =H33*2*L33*N33/O33
A34: =+A33+1 | B34: 450116 | C34: ประยงค์ สายเคน | D34: ชาย | E34: รายเดือน | F34: ไทย | G34: 33/80 ม.4 ต.บางละมุง อ.บางละมุง จ.ชลบุรี 20150 | H34: 6 | J34: รถกระบะบรรทุก | K34: ดีเซล | L34: 2 | N34: ='[2]1.4 Septic'!$F$16 | O34: 6.369 | P34: =H34*2*L34*N34/O34
A35: =+A34+1 | B35: 450119 | C35: เอนก ยาพรม | D35: ชาย | E35: รายเดือน | F35: ไทย | G35: 101/259 ม.10 ต.บึง อ.ศรีราชา จ.ชลบุรี 20230 | H35: 10 | J35: รถจักรยานยนต์ 4 จังหวะเครื่องยนต์ขนาดเล็กกว่า 125 cc | K35: แก๊สโซฮอล์ 91 | L35: 1 | N35: ='[2]1.4 Septic'!$F$16 | O35: =$G$492 | Q35: =H35*2*L35*N35/O35
A36: =+A35+1 | B36: 450121 | C36: วัฒนา สาระมัด | D36: ชาย | E36: รายเดือน | F36: ไทย | G36: เคหะแหลมฉบัง ตึก 20 ม.6 ต.บางละมุง อ.บางละมุง จ.ชลบุรี 20150 | H36: 12 | J36: รถกระบะบรรทุก | K36: ดีเซล | L36: 2 | N36: ='[2]1.4 Septic'!$F$16 | O36: 6.369 | P36: =H36*2*L36*N36/O36
A37: =+A36+1 | B37: 450122 | C37: สมชาย สุทธิประเสริฐ | D37: ชาย | E37: รายเดือน | F37: ไทย | G37: เคหะแหลมฉบัง ม.6 บางละมุง บางละมุง ชลบุรี 20150 | H37: 7 | J37: รถยนต์เฉลี่ยทุกขนาด | K37: แก๊สโซฮอล์ 95 | L37: 1 | N37: ='[2]1.4 Septic'!$F$16 | O37: =$G$487 | Q37: =H37*2*L37*N37/O37
A38: =+A37+1 | B38: 460138 | C38: มนทิรา ไตยโส | D38: หญิง | E38: รายเดือน | F38: ไทย | G38: 133/220 ม.6 ต.บางละมุง อ.บางละมุง จ.ชลบุรี 20150 | H38: 14 | J38: รถยนต์เฉลี่ยทุกขนาด | K38: แก๊สโซฮอล์ 91 | L38: 1 | N38: ='[2]1.4 Septic'!$F$16 | O38: =$G$487 | Q38: =H38*2*L38*N38/O38
A39: =+A38+1 | B39: 460139 | C39: พิษมัย ปินะถา | D39: หญิง | E39: รายเดือน | F39: ไทย | G39: 142/140 ม.7 ต.สุรศักดิ์ อ.ศรีราชา จ.ชลบุรี 20230 | H39: 5 | J39: รถกระบะบรรทุก | K39: ดีเซล | L39: 2 | N39: ='[2]1.4 Septic'!$F$16 | O39: 6.369 | P39: =H39*2*L39*N39/O39
A40: =+A39+1 | B40: 460140 | C40: สุรารักษ์ เทพนา | D40: ชาย | E40: รายเดือน | F40: ไทย | G40: การเคหะแหลมฉบัง ต.บางละมุง อ.บางละมุง จ.ชลบุรี | H40: 7 | J40: รถจักรยานยนต์ 2 จังหวะเฉลี่ยทุกขนาด | K40: แก๊สโซฮอล์ 91 | L40: 1 | N40: ='[2]1.4 Septic'!$F$16 | O40: =$G$491 | Q40: =H40*2*L40*N40/O40
A41: =+A40+1 | B41: 460142 | C41: สนอง สุขนวน | D41: ชาย | E41: รายเดือน | F41: ไทย | G41: 220/137 การเคหะแห่งชาติ ต.บางละมุง อ.บางละมุง จ.ชลบุรี 20150 | H41: 5 | J41: รถยนต์ขนาดกลาง (1600 cc) | K41: แก๊สโซฮอล์ 91 | L41: 1 | N41: ='[2]1.4 Septic'!$F$16 | O41: =$G$497 | Q41: =H41*2*L41*N41/O41
A42: =+A41+1 | B42: 460149 | C42: บรรหาญ คล้อยมาตร์ | D42: ชาย | E42: รายเดือน | F42: ไทย | G42: 101/85 ม.10 ต.บึง อ.ศรีราชา จ.ชลบุรี 20230 | H42: 9 | J42: รถจักรยานยนต์ 4 จังหวะเครื่องยนต์ขนาดเล็กกว่า 125 cc | K42: แก๊สโซฮอล์ 91 | L42: 1 | N42: ='[2]1.4 Septic'!$F$16 | O42: =$G$492 | Q42: =H42*2*L42*N42/O42
A43: =+A42+1 | B43: 460154 | C43: จรัญ จันทร์บุปผา | D43: ชาย | E43: รายเดือน | F43: ไทย | G43: 10/22 ม.4 ต.บางไผ่ อ.บางแค จ.กรุงเทพมหานคร 10160 | H43: 40 | J43: รถยนต์ขนาดกลาง (1800 cc) | K43: แก๊สโซฮอล์ 95 | L43: 2 | M43: สนง.กทม. | N43: ='[2]1.4 Septic'!$F$34 | O43: =$G$496 | Q43: =H43*2*L43*N43/O43
A44: =+A43+1 | B44: 460155 | C44: บรรจง ยาพรม | D44: หญิง | E44: รายเดือน | F44: ไทย | G44: 101/259 ม.10 ต.บึง อ.ศรีราชา จ.ชลบุรี 20230 | H44: 9.8 | J44: รถจักรยานยนต์ 4 จังหวะเครื่องยนต์ขนาดเล็กกว่า 125 cc | K44: แก๊สโซฮอล์ 91 | L44: 1 | N44: ='[2]1.4 Septic'!$F$16 | O44: =$G$492 | Q44: =H44*2*L44*N44/O44
A45: =+A44+1 | B45: 460156 | C45: รัชฎาพร ศรีจันทร์ | D45: หญิง | E45: รายเดือน | F45: ไทย | G45: 101/261 ม.10 ต.บึง อ.ศรีราชา จ.ชลบุรี 20230 | H45: 10 | J45: รถจักรยานยนต์ 4 จังหวะเฉลี่ยทุกขนาด | K45: แก๊สโซฮอล์ 91 | L45: 2 | N45: ='[2]1.4 Septic'!$F$16 | O45: =$G$492 | Q45: =H45*2*L45*N45/O45
A46: =+A45+1 | B46: 460157 | C46: ทวีป ตะกุดสงฆ์ | D46: ชาย | E46: รายเดือน | F46: ไทย | G46: การเคหะแหลมฉบัง ม.6 ต.บางละมุง อ.บางละมุง จ.ชลบุรี | H46: 7 | J46: รถจักรยานยนต์ 4 จังหวะเครื่องยนต์ขนาดเล็กกว่า 125 cc | K46: แก๊สโซฮอล์ 95 | L46: 2 | N46: ='[2]1.4 Septic'!$F$16 | O46: =$G$492 | Q46: =H46*2*L46*N46/O46
A47: =+A46+1 | B47: 460162 | C47: วรวุฒิ สุขจันทร์ | D47: ชาย | E47: รายเดือน | F47: ไทย | G47: การเคหะแหลมฉบัง ต.บางละมุง อ.บางละมุง จ.ชลบุรี | H47: 7 | J47: รถกระบะบรรทุก | K47: ดีเซล | L47: 2 | N47: ='[2]1.4 Septic'!$F$16 | O47: 6.369 | P47: =H47*2*L47*N47/O47
